{
  "{\"departure_date\": \"2025-06-03\", \"end_location\": {\"name\": \"GER02\", \"type\": \"TERM\"}, \"start_location\": {\"name\": \"GER01\", \"type\": \"PLANT\"}, \"truck_number\": 11}": {
    "load": [
      0,
      3,
      5,
      7,
      8,
      9,
      11,
      13,
      246,
      248,
      395,
      396,
      397,
      398,
      399
    ]
  },
  "{\"departure_date\": \"2025-06-09\", \"end_location\": {\"name\": \"FRA01\", \"type\": \"DEAL\"}, \"start_location\": {\"name\": \"GER02\", \"type\": \"TERM\"}, \"truck_number\": 1}": {
    "load": [
      0,
      3,
      5,
      9,
      11,
      15,
      16,
      21,
      33,
      36
    ]
  },
  "{\"departure_date\": \"2025-06-03\", \"end_location\": {\"name\": \"BEL01\", \"type\": \"TERM\"}, \"start_location\": {\"name\": \"GER01\", \"type\": \"PLANT\"}, \"truck_number\": 1}": {
    "load": [
      1,
      6,
      10,
      12
    ]
  },
  "{\"departure_date\": \"2025-06-06\", \"end_location\": {\"name\": \"FRA01\", \"type\": \"DEAL\"}, \"start_location\": {\"name\": \"BEL01\", \"type\": \"TERM\"}, \"truck_number\": 1}": {
    "load": [
      1,
      6,
      10,
      12
    ]
  },
  "{\"departure_date\": \"2025-06-04\", \"end_location\": {\"name\": \"BEL01\", \"type\": \"TERM\"}, \"start_location\": {\"name\": \"GER01\", \"type\": \"PLANT\"}, \"truck_number\": 11}": {
    "load": [
      2,
      4,
      14,
      17,
      18,
      19,
      241,
      244,
      247,
      251,
      401,
      404
    ]
  },
  "{\"departure_date\": \"2025-06-09\", \"end_location\": {\"name\": \"FRA01\", \"type\": \"DEAL\"}, \"start_location\": {\"name\": \"BEL01\", \"type\": \"TERM\"}, \"truck_number\": 1}": {
    "load": [
      2,
      4,
      17,
      18,
      19,
      22,
      23,
      24,
      26,
      28
    ]
  },
  "{\"departure_date\": \"2025-06-10\", \"end_location\": {\"name\": \"FRA01\", \"type\": \"DEAL\"}, \"start_location\": {\"name\": \"GER02\", \"type\": \"TERM\"}, \"truck_number\": 1}": {
    "load": [
      7,
      8,
      13,
      25,
      32,
      34,
      35,
      37,
      38,
      39
    ]
  },
  "{\"departure_date\": \"2025-06-10\", \"end_location\": {\"name\": \"FRA01\", \"type\": \"DEAL\"}, \"start_location\": {\"name\": \"BEL01\", \"type\": \"TERM\"}, \"truck_number\": 1}": {
    "load": [
      14,
      20,
      27,
      29
    ]
  },
  "{\"departure_date\": \"2025-06-06\", \"end_location\": {\"name\": \"GER02\", \"type\": \"TERM\"}, \"start_location\": {\"name\": \"GER01\", \"type\": \"PLANT\"}, \"truck_number\": 1}": {
    "load": [
      15,
      21,
      25,
      30,
      32,
      33,
      34,
      35,
      36,
      37,
      38,
      39,
      258,
      390,
      400,
      411,
      416,
      422
    ]
  },
  "{\"departure_date\": \"2025-06-05\", \"end_location\": {\"name\": \"GER02\", \"type\": \"TERM\"}, \"start_location\": {\"name\": \"GER01\", \"type\": \"PLANT\"}, \"truck_number\": 11}": {
    "load": [
      16,
      402,
      406,
      407,
      409,
      410,
      413,
      414,
      415,
      417,
      418,
      420,
      421,
      423,
      424
    ]
  },
  "{\"departure_date\": \"2025-06-05\", \"end_location\": {\"name\": \"BEL01\", \"type\": \"TERM\"}, \"start_location\": {\"name\": \"GER01\", \"type\": \"PLANT\"}, \"truck_number\": 1}": {
    "load": [
      20,
      22,
      23,
      24,
      26,
      27,
      28,
      240,
      242,
      245,
      249,
      250,
      252,
      403,
      405,
      408,
      412,
      419
    ]
  },
  "{\"departure_date\": \"2025-06-06\", \"end_location\": {\"name\": \"BEL01\", \"type\": \"TERM\"}, \"start_location\": {\"name\": \"GER01\", \"type\": \"PLANT\"}, \"truck_number\": 11}": {
    "load": [
      29,
      253,
      254,
      255,
      256,
      257,
      259,
      260,
      261,
      262,
      263,
      264
    ]
  },
  "{\"departure_date\": \"2025-06-11\", \"end_location\": {\"name\": \"FRA01\", \"type\": \"DEAL\"}, \"start_location\": {\"name\": \"GER02\", \"type\": \"TERM\"}, \"truck_number\": 1}": {
    "load": [
      30
    ]
  },
  "{\"departure_date\": \"2025-06-10\", \"end_location\": {\"name\": \"GER02\", \"type\": \"TERM\"}, \"start_location\": {\"name\": \"GER01\", \"type\": \"PLANT\"}, \"truck_number\": 11}": {
    "load": [
      31,
      40,
      41,
      43,
      44,
      45,
      47,
      48,
      51,
      52,
      53,
      54,
      270,
      273,
      274
    ]
  },
  "{\"departure_date\": \"2025-06-16\", \"end_location\": {\"name\": \"FRA01\", \"type\": \"DEAL\"}, \"start_location\": {\"name\": \"GER02\", \"type\": \"TERM\"}, \"truck_number\": 1}": {
    "load": [
      31,
      41,
      45,
      47,
      48,
      54,
      62,
      63,
      65,
      66,
      68,
      69,
      71,
      73
    ]
  },
  "{\"departure_date\": \"2025-06-18\", \"end_location\": {\"name\": \"FRA01\", \"type\": \"DEAL\"}, \"start_location\": {\"name\": \"GER02\", \"type\": \"TERM\"}, \"truck_number\": 1}": {
    "load": [
      40,
      51,
      67,
      77
    ]
  },
  "{\"departure_date\": \"2025-06-09\", \"end_location\": {\"name\": \"BEL01\", \"type\": \"TERM\"}, \"start_location\": {\"name\": \"GER01\", \"type\": \"PLANT\"}, \"truck_number\": 1}": {
    "load": [
      42,
      46,
      49,
      265,
      268,
      269
    ]
  },
  "{\"departure_date\": \"2025-06-12\", \"end_location\": {\"name\": \"FRA01\", \"type\": \"DEAL\"}, \"start_location\": {\"name\": \"BEL01\", \"type\": \"TERM\"}, \"truck_number\": 1}": {
    "load": [
      42,
      46,
      49
    ]
  },
  "{\"departure_date\": \"2025-06-17\", \"end_location\": {\"name\": \"FRA01\", \"type\": \"DEAL\"}, \"start_location\": {\"name\": \"GER02\", \"type\": \"TERM\"}, \"truck_number\": 1}": {
    "load": [
      43,
      44,
      52,
      53,
      58,
      60,
      61,
      64,
      70,
      72,
      74,
      75,
      76,
      78,
      79
    ]
  },
  "{\"departure_date\": \"2025-06-10\", \"end_location\": {\"name\": \"BEL01\", \"type\": \"TERM\"}, \"start_location\": {\"name\": \"GER01\", \"type\": \"PLANT\"}, \"truck_number\": 1}": {
    "load": [
      50
    ]
  },
  "{\"departure_date\": \"2025-06-13\", \"end_location\": {\"name\": \"FRA01\", \"type\": \"DEAL\"}, \"start_location\": {\"name\": \"BEL01\", \"type\": \"TERM\"}, \"truck_number\": 1}": {
    "load": [
      50
    ]
  },
  "{\"departure_date\": \"2025-06-11\", \"end_location\": {\"name\": \"BEL01\", \"type\": \"TERM\"}, \"start_location\": {\"name\": \"GER01\", \"type\": \"PLANT\"}, \"truck_number\": 11}": {
    "load": [
      55,
      56,
      57,
      59,
      275,
      276,
      277,
      278,
      279,
      435,
      436,
      438
    ]
  },
  "{\"departure_date\": \"2025-06-16\", \"end_location\": {\"name\": \"FRA01\", \"type\": \"DEAL\"}, \"start_location\": {\"name\": \"BEL01\", \"type\": \"TERM\"}, \"truck_number\": 1}": {
    "load": [
      55,
      56,
      57,
      59
    ]
  },
  "{\"departure_date\": \"2025-06-12\", \"end_location\": {\"name\": \"GER02\", \"type\": \"TERM\"}, \"start_location\": {\"name\": \"GER01\", \"type\": \"PLANT\"}, \"truck_number\": 11}": {
    "load": [
      58,
      60,
      61,
      63,
      64,
      66,
      67,
      68,
      69,
      437,
      444,
      447,
      449,
      455,
      456
    ]
  },
  "{\"departure_date\": \"2025-06-13\", \"end_location\": {\"name\": \"GER02\", \"type\": \"TERM\"}, \"start_location\": {\"name\": \"GER01\", \"type\": \"PLANT\"}, \"truck_number\": 1}": {
    "load": [
      62,
      65,
      70,
      71,
      72,
      73,
      74,
      75,
      76,
      77,
      78,
      79,
      280,
      282,
      283,
      284,
      285,
      286,
      288
    ]
  },
  "{\"departure_date\": \"2025-06-17\", \"end_location\": {\"name\": \"BEL01\", \"type\": \"TERM\"}, \"start_location\": {\"name\": \"GER01\", \"type\": \"PLANT\"}, \"truck_number\": 1}": {
    "load": [
      80,
      86,
      87,
      89,
      440,
      443,
      464
    ]
  },
  "{\"departure_date\": \"2025-06-20\", \"end_location\": {\"name\": \"FRA01\", \"type\": \"DEAL\"}, \"start_location\": {\"name\": \"BEL01\", \"type\": \"TERM\"}, \"truck_number\": 1}": {
    "load": [
      80,
      86,
      87,
      89
    ]
  },
  "{\"departure_date\": \"2025-06-17\", \"end_location\": {\"name\": \"GER02\", \"type\": \"TERM\"}, \"start_location\": {\"name\": \"GER01\", \"type\": \"PLANT\"}, \"truck_number\": 11}": {
    "load": [
      81,
      82,
      83,
      84,
      85,
      90,
      92,
      93,
      94,
      290,
      446,
      461,
      462,
      466,
      468
    ]
  },
  "{\"departure_date\": \"2025-06-23\", \"end_location\": {\"name\": \"FRA01\", \"type\": \"DEAL\"}, \"start_location\": {\"name\": \"GER02\", \"type\": \"TERM\"}, \"truck_number\": 1}": {
    "load": [
      81,
      82,
      83,
      85,
      90,
      93,
      94
    ]
  },
  "{\"departure_date\": \"2025-06-24\", \"end_location\": {\"name\": \"FRA01\", \"type\": \"DEAL\"}, \"start_location\": {\"name\": \"GER02\", \"type\": \"TERM\"}, \"truck_number\": 1}": {
    "load": [
      84,
      88,
      91,
      92
    ]
  },
  "{\"departure_date\": \"2025-06-17\", \"end_location\": {\"name\": \"GER02\", \"type\": \"TERM\"}, \"start_location\": {\"name\": \"GER01\", \"type\": \"PLANT\"}, \"truck_number\": 1}": {
    "load": [
      88,
      91,
      292,
      295,
      439,
      452,
      453,
      460,
      465,
      469
    ]
  },
  "{\"departure_date\": \"2025-06-19\", \"end_location\": {\"name\": \"BEL01\", \"type\": \"TERM\"}, \"start_location\": {\"name\": \"GER01\", \"type\": \"PLANT\"}, \"truck_number\": 1}": {
    "load": [
      95,
      96,
      97,
      98,
      100,
      101,
      102,
      103,
      104,
      105,
      106,
      107,
      108,
      109,
      302,
      463,
      467,
      473,
      476,
      479,
      488,
      494
    ]
  },
  "{\"departure_date\": \"2025-06-23\", \"end_location\": {\"name\": \"FRA01\", \"type\": \"DEAL\"}, \"start_location\": {\"name\": \"BEL01\", \"type\": \"TERM\"}, \"truck_number\": 1}": {
    "load": [
      95,
      97,
      99,
      100,
      104,
      105
    ]
  },
  "{\"departure_date\": \"2025-06-24\", \"end_location\": {\"name\": \"FRA01\", \"type\": \"DEAL\"}, \"start_location\": {\"name\": \"BEL01\", \"type\": \"TERM\"}, \"truck_number\": 1}": {
    "load": [
      96,
      98,
      101,
      102,
      103,
      106,
      107,
      108,
      109,
      112
    ]
  },
  "{\"departure_date\": \"2025-06-18\", \"end_location\": {\"name\": \"BEL01\", \"type\": \"TERM\"}, \"start_location\": {\"name\": \"GER01\", \"type\": \"PLANT\"}, \"truck_number\": 11}": {
    "load": [
      99,
      291,
      293,
      294,
      296,
      297,
      298,
      299,
      300,
      301,
      303,
      304
    ]
  },
  "{\"departure_date\": \"2025-06-23\", \"end_location\": {\"name\": \"BEL01\", \"type\": \"TERM\"}, \"start_location\": {\"name\": \"GER01\", \"type\": \"PLANT\"}, \"truck_number\": 1}": {
    "load": [
      110,
      111,
      113,
      114,
      115,
      116,
      117,
      118,
      119,
      120,
      121,
      122,
      123,
      124,
      125,
      126,
      127,
      128,
      129,
      305,
      307,
      309,
      313,
      314,
      315,
      319
    ]
  },
  "{\"departure_date\": \"2025-06-27\", \"end_location\": {\"name\": \"FRA01\", \"type\": \"DEAL\"}, \"start_location\": {\"name\": \"BEL01\", \"type\": \"TERM\"}, \"truck_number\": 1}": {
    "load": [
      110,
      115,
      116,
      117,
      118,
      119,
      128,
      129,
      130,
      134
    ]
  },
  "{\"departure_date\": \"2025-06-30\", \"end_location\": {\"name\": \"FRA01\", \"type\": \"DEAL\"}, \"start_location\": {\"name\": \"BEL01\", \"type\": \"TERM\"}, \"truck_number\": 1}": {
    "load": [
      111,
      113,
      114,
      125,
      135,
      141,
      143,
      146
    ]
  },
  "{\"departure_date\": \"2025-06-20\", \"end_location\": {\"name\": \"BEL01\", \"type\": \"TERM\"}, \"start_location\": {\"name\": \"GER01\", \"type\": \"PLANT\"}, \"truck_number\": 1}": {
    "load": [
      112,
      306,
      308,
      310,
      312
    ]
  },
  "{\"departure_date\": \"2025-06-26\", \"end_location\": {\"name\": \"FRA01\", \"type\": \"DEAL\"}, \"start_location\": {\"name\": \"BEL01\", \"type\": \"TERM\"}, \"truck_number\": 1}": {
    "load": [
      120,
      121,
      122,
      123,
      124,
      126
    ]
  },
  "{\"departure_date\": \"2025-07-01\", \"end_location\": {\"name\": \"FRA01\", \"type\": \"DEAL\"}, \"start_location\": {\"name\": \"BEL01\", \"type\": \"TERM\"}, \"truck_number\": 1}": {
    "load": [
      127,
      137,
      138,
      140,
      154,
      157
    ]
  },
  "{\"departure_date\": \"2025-06-24\", \"end_location\": {\"name\": \"BEL01\", \"type\": \"TERM\"}, \"start_location\": {\"name\": \"GER01\", \"type\": \"PLANT\"}, \"truck_number\": 1}": {
    "load": [
      130,
      134
    ]
  },
  "{\"departure_date\": \"2025-06-24\", \"end_location\": {\"name\": \"GER02\", \"type\": \"TERM\"}, \"start_location\": {\"name\": \"GER01\", \"type\": \"PLANT\"}, \"truck_number\": 11}": {
    "load": [
      131,
      133,
      311,
      316,
      317,
      321,
      322,
      323,
      324,
      485,
      495,
      496,
      498,
      501,
      503
    ]
  },
  "{\"departure_date\": \"2025-06-30\", \"end_location\": {\"name\": \"FRA01\", \"type\": \"DEAL\"}, \"start_location\": {\"name\": \"GER02\", \"type\": \"TERM\"}, \"truck_number\": 1}": {
    "load": [
      131,
      133
    ]
  },
  "{\"departure_date\": \"2025-06-25\", \"end_location\": {\"name\": \"BEL01\", \"type\": \"TERM\"}, \"start_location\": {\"name\": \"GER01\", \"type\": \"PLANT\"}, \"truck_number\": 11}": {
    "load": [
      132,
      135,
      136,
      137,
      138,
      139,
      318,
      325,
      326,
      327,
      328,
      329
    ]
  },
  "{\"departure_date\": \"2025-07-02\", \"end_location\": {\"name\": \"FRA01\", \"type\": \"DEAL\"}, \"start_location\": {\"name\": \"BEL01\", \"type\": \"TERM\"}, \"truck_number\": 1}": {
    "load": [
      132,
      136,
      139,
      142,
      145,
      147,
      148,
      155
    ]
  },
  "{\"departure_date\": \"2025-06-26\", \"end_location\": {\"name\": \"BEL01\", \"type\": \"TERM\"}, \"start_location\": {\"name\": \"GER01\", \"type\": \"PLANT\"}, \"truck_number\": 1}": {
    "load": [
      140,
      141,
      142,
      143,
      146,
      513,
      515,
      522,
      525,
      529
    ]
  },
  "{\"departure_date\": \"2025-06-30\", \"end_location\": {\"name\": \"BEL01\", \"type\": \"TERM\"}, \"start_location\": {\"name\": \"GER01\", \"type\": \"PLANT\"}, \"truck_number\": 1}": {
    "load": [
      144,
      149,
      150,
      151,
      152,
      153,
      156,
      158,
      159,
      160,
      161,
      162,
      163,
      165,
      166,
      168,
      169,
      331,
      333,
      341,
      531,
      533,
      534
    ]
  },
  "{\"departure_date\": \"2025-07-04\", \"end_location\": {\"name\": \"FRA01\", \"type\": \"DEAL\"}, \"start_location\": {\"name\": \"BEL01\", \"type\": \"TERM\"}, \"truck_number\": 1}": {
    "load": [
      144,
      149,
      156,
      158,
      159,
      161,
      162,
      165,
      166,
      168,
      169,
      170,
      172
    ]
  },
  "{\"departure_date\": \"2025-06-27\", \"end_location\": {\"name\": \"BEL01\", \"type\": \"TERM\"}, \"start_location\": {\"name\": \"GER01\", \"type\": \"PLANT\"}, \"truck_number\": 11}": {
    "load": [
      145,
      147,
      148,
      154,
      155,
      157,
      330,
      332,
      334,
      335,
      337,
      339
    ]
  },
  "{\"departure_date\": \"2025-07-03\", \"end_location\": {\"name\": \"FRA01\", \"type\": \"DEAL\"}, \"start_location\": {\"name\": \"BEL01\", \"type\": \"TERM\"}, \"truck_number\": 1}": {
    "load": [
      150,
      151,
      152,
      153,
      160,
      163
    ]
  },
  "{\"departure_date\": \"2025-07-01\", \"end_location\": {\"name\": \"GER02\", \"type\": \"TERM\"}, \"start_location\": {\"name\": \"GER01\", \"type\": \"PLANT\"}, \"truck_number\": 11}": {
    "load": [
      164,
      167,
      171,
      173,
      174,
      338,
      343,
      345,
      346,
      348,
      530,
      532,
      535,
      536,
      537
    ]
  },
  "{\"departure_date\": \"2025-07-09\", \"end_location\": {\"name\": \"FRA01\", \"type\": \"DEAL\"}, \"start_location\": {\"name\": \"GER02\", \"type\": \"TERM\"}, \"truck_number\": 1}": {
    "load": [
      164,
      167,
      173,
      174,
      183,
      185,
      191,
      198
    ]
  },
  "{\"departure_date\": \"2025-07-01\", \"end_location\": {\"name\": \"BEL01\", \"type\": \"TERM\"}, \"start_location\": {\"name\": \"GER01\", \"type\": \"PLANT\"}, \"truck_number\": 1}": {
    "load": [
      170,
      172,
      336,
      342,
      349,
      538,
      539
    ]
  },
  "{\"departure_date\": \"2025-07-07\", \"end_location\": {\"name\": \"FRA01\", \"type\": \"DEAL\"}, \"start_location\": {\"name\": \"GER02\", \"type\": \"TERM\"}, \"truck_number\": 1}": {
    "load": [
      171,
      180,
      181,
      182,
      184,
      186,
      187,
      188,
      193,
      194,
      197
    ]
  },
  "{\"departure_date\": \"2025-07-02\", \"end_location\": {\"name\": \"BEL01\", \"type\": \"TERM\"}, \"start_location\": {\"name\": \"GER01\", \"type\": \"PLANT\"}, \"truck_number\": 11}": {
    "load": [
      175,
      176,
      177,
      178,
      179,
      351,
      352,
      353,
      354,
      541,
      542,
      543
    ]
  },
  "{\"departure_date\": \"2025-07-07\", \"end_location\": {\"name\": \"FRA01\", \"type\": \"DEAL\"}, \"start_location\": {\"name\": \"BEL01\", \"type\": \"TERM\"}, \"truck_number\": 1}": {
    "load": [
      175,
      176,
      177,
      178,
      179
    ]
  },
  "{\"departure_date\": \"2025-07-03\", \"end_location\": {\"name\": \"GER02\", \"type\": \"TERM\"}, \"start_location\": {\"name\": \"GER01\", \"type\": \"PLANT\"}, \"truck_number\": 1}": {
    "load": [
      180,
      181,
      184,
      540,
      544,
      546,
      549,
      552,
      558,
      559,
      561
    ]
  },
  "{\"departure_date\": \"2025-07-03\", \"end_location\": {\"name\": \"GER02\", \"type\": \"TERM\"}, \"start_location\": {\"name\": \"GER01\", \"type\": \"PLANT\"}, \"truck_number\": 11}": {
    "load": [
      182,
      183,
      185,
      186,
      187,
      188,
      547,
      548,
      551,
      553,
      556,
      557,
      560,
      562,
      564
    ]
  },
  "{\"departure_date\": \"2025-07-08\", \"end_location\": {\"name\": \"GER02\", \"type\": \"TERM\"}, \"start_location\": {\"name\": \"GER01\", \"type\": \"PLANT\"}, \"truck_number\": 11}": {
    "load": [
      189,
      195,
      196,
      208,
      212,
      214,
      355,
      360,
      368,
      369,
      370,
      371,
      374,
      572,
      574
    ]
  },
  "{\"departure_date\": \"2025-07-15\", \"end_location\": {\"name\": \"FRA01\", \"type\": \"DEAL\"}, \"start_location\": {\"name\": \"GER02\", \"type\": \"TERM\"}, \"truck_number\": 1}": {
    "load": [
      189,
      212,
      214,
      218,
      223
    ]
  },
  "{\"departure_date\": \"2025-07-09\", \"end_location\": {\"name\": \"BEL01\", \"type\": \"TERM\"}, \"start_location\": {\"name\": \"GER01\", \"type\": \"PLANT\"}, \"truck_number\": 11}": {
    "load": [
      190,
      199,
      200,
      202,
      203,
      209,
      210,
      363,
      376,
      377,
      378,
      570
    ]
  },
  "{\"departure_date\": \"2025-07-14\", \"end_location\": {\"name\": \"FRA01\", \"type\": \"DEAL\"}, \"start_location\": {\"name\": \"BEL01\", \"type\": \"TERM\"}, \"truck_number\": 1}": {
    "load": [
      190,
      199,
      200,
      202,
      203,
      209,
      210
    ]
  },
  "{\"departure_date\": \"2025-07-04\", \"end_location\": {\"name\": \"GER02\", \"type\": \"TERM\"}, \"start_location\": {\"name\": \"GER01\", \"type\": \"PLANT\"}, \"truck_number\": 1}": {
    "load": [
      191,
      193,
      194,
      197,
      198,
      350,
      357
    ]
  },
  "{\"departure_date\": \"2025-07-04\", \"end_location\": {\"name\": \"BEL01\", \"type\": \"TERM\"}, \"start_location\": {\"name\": \"GER01\", \"type\": \"PLANT\"}, \"truck_number\": 11}": {
    "load": [
      192,
      356,
      358,
      359,
      361,
      362,
      364,
      545,
      550,
      554,
      555,
      563
    ]
  },
  "{\"departure_date\": \"2025-07-08\", \"end_location\": {\"name\": \"FRA01\", \"type\": \"DEAL\"}, \"start_location\": {\"name\": \"BEL01\", \"type\": \"TERM\"}, \"truck_number\": 1}": {
    "load": [
      192
    ]
  },
  "{\"departure_date\": \"2025-07-14\", \"end_location\": {\"name\": \"FRA01\", \"type\": \"DEAL\"}, \"start_location\": {\"name\": \"GER02\", \"type\": \"TERM\"}, \"truck_number\": 1}": {
    "load": [
      195,
      196,
      201,
      205,
      208,
      211,
      213,
      224,
      225,
      226,
      231,
      236
    ]
  },
  "{\"departure_date\": \"2025-07-10\", \"end_location\": {\"name\": \"GER02\", \"type\": \"TERM\"}, \"start_location\": {\"name\": \"GER01\", \"type\": \"PLANT\"}, \"truck_number\": 1}": {
    "load": [
      201,
      205,
      211,
      213,
      218,
      223,
      226,
      587,
      592,
      597
    ]
  },
  "{\"departure_date\": \"2025-07-15\", \"end_location\": {\"name\": \"BEL01\", \"type\": \"TERM\"}, \"start_location\": {\"name\": \"GER01\", \"type\": \"PLANT\"}, \"truck_number\": 1}": {
    "load": [
      204,
      206,
      207,
      215,
      219,
      220,
      227,
      228,
      230
    ]
  },
  "{\"departure_date\": \"2025-07-18\", \"end_location\": {\"name\": \"FRA01\", \"type\": \"DEAL\"}, \"start_location\": {\"name\": \"BEL01\", \"type\": \"TERM\"}, \"truck_number\": 1}": {
    "load": [
      204,
      206,
      207,
      215,
      219,
      220,
      227,
      228,
      230
    ]
  },
  "{\"departure_date\": \"2025-07-16\", \"end_location\": {\"name\": \"BEL01\", \"type\": \"TERM\"}, \"start_location\": {\"name\": \"GER01\", \"type\": \"PLANT\"}, \"truck_number\": 11}": {
    "load": [
      216,
      217,
      221,
      235,
      237,
      373,
      375,
      379,
      381,
      384,
      385,
      386
    ]
  },
  "{\"departure_date\": \"2025-07-21\", \"end_location\": {\"name\": \"FRA01\", \"type\": \"DEAL\"}, \"start_location\": {\"name\": \"BEL01\", \"type\": \"TERM\"}, \"truck_number\": 1}": {
    "load": [
      216,
      217,
      221,
      235,
      237
    ]
  },
  "{\"departure_date\": \"2025-07-15\", \"end_location\": {\"name\": \"GER02\", \"type\": \"TERM\"}, \"start_location\": {\"name\": \"GER01\", \"type\": \"PLANT\"}, \"truck_number\": 11}": {
    "load": [
      222,
      229,
      232,
      233,
      234,
      238,
      239
    ]
  },
  "{\"departure_date\": \"2025-07-21\", \"end_location\": {\"name\": \"FRA01\", \"type\": \"DEAL\"}, \"start_location\": {\"name\": \"GER02\", \"type\": \"TERM\"}, \"truck_number\": 1}": {
    "load": [
      222,
      229,
      232,
      233,
      234,
      238,
      239
    ]
  },
  "{\"departure_date\": \"2025-07-11\", \"end_location\": {\"name\": \"GER02\", \"type\": \"TERM\"}, \"start_location\": {\"name\": \"GER01\", \"type\": \"PLANT\"}, \"truck_number\": 1}": {
    "load": [
      224,
      225,
      231,
      236,
      565,
      568,
      575
    ]
  },
  "{\"departure_date\": \"2025-06-09\", \"end_location\": {\"name\": \"GER03\", \"type\": \"DEAL\"}, \"start_location\": {\"name\": \"BEL01\", \"type\": \"TERM\"}, \"truck_number\": 1}": {
    "load": [
      240,
      241,
      242,
      245,
      249
    ]
  },
  "{\"departure_date\": \"2025-06-02\", \"end_location\": {\"name\": \"GER02\", \"type\": \"TERM\"}, \"start_location\": {\"name\": \"GER01\", \"type\": \"PLANT\"}, \"truck_number\": 1}": {
    "load": [
      243,
      391,
      392,
      393,
      394
    ]
  },
  "{\"departure_date\": \"2025-06-05\", \"end_location\": {\"name\": \"GER03\", \"type\": \"DEAL\"}, \"start_location\": {\"name\": \"GER02\", \"type\": \"TERM\"}, \"truck_number\": 1}": {
    "load": [
      243
    ]
  },
  "{\"departure_date\": \"2025-06-11\", \"end_location\": {\"name\": \"GER03\", \"type\": \"DEAL\"}, \"start_location\": {\"name\": \"BEL01\", \"type\": \"TERM\"}, \"truck_number\": 1}": {
    "load": [
      244,
      247,
      254,
      255,
      256,
      260,
      261,
      262,
      264
    ]
  },
  "{\"departure_date\": \"2025-06-12\", \"end_location\": {\"name\": \"GER03\", \"type\": \"DEAL\"}, \"start_location\": {\"name\": \"GER02\", \"type\": \"TERM\"}, \"truck_number\": 1}": {
    "load": [
      246,
      248,
      258,
      266,
      267
    ]
  },
  "{\"departure_date\": \"2025-06-10\", \"end_location\": {\"name\": \"GER03\", \"type\": \"DEAL\"}, \"start_location\": {\"name\": \"BEL01\", \"type\": \"TERM\"}, \"truck_number\": 1}": {
    "load": [
      250,
      251,
      253,
      263
    ]
  },
  "{\"departure_date\": \"2025-06-16\", \"end_location\": {\"name\": \"GER03\", \"type\": \"DEAL\"}, \"start_location\": {\"name\": \"BEL01\", \"type\": \"TERM\"}, \"truck_number\": 1}": {
    "load": [
      252,
      257,
      259,
      265,
      268,
      269,
      276,
      277
    ]
  },
  "{\"departure_date\": \"2025-06-09\", \"end_location\": {\"name\": \"GER02\", \"type\": \"TERM\"}, \"start_location\": {\"name\": \"GER01\", \"type\": \"PLANT\"}, \"truck_number\": 1}": {
    "load": [
      266,
      267
    ]
  },
  "{\"departure_date\": \"2025-06-18\", \"end_location\": {\"name\": \"GER03\", \"type\": \"DEAL\"}, \"start_location\": {\"name\": \"GER02\", \"type\": \"TERM\"}, \"truck_number\": 1}": {
    "load": [
      270,
      282,
      285,
      288
    ]
  },
  "{\"departure_date\": \"2025-06-10\", \"end_location\": {\"name\": \"GER02\", \"type\": \"TERM\"}, \"start_location\": {\"name\": \"GER01\", \"type\": \"PLANT\"}, \"truck_number\": 1}": {
    "load": [
      271,
      272,
      425,
      426,
      427,
      428,
      429,
      430,
      431,
      432,
      433,
      434
    ]
  },
  "{\"departure_date\": \"2025-06-13\", \"end_location\": {\"name\": \"GER03\", \"type\": \"DEAL\"}, \"start_location\": {\"name\": \"GER02\", \"type\": \"TERM\"}, \"truck_number\": 1}": {
    "load": [
      271,
      272
    ]
  },
  "{\"departure_date\": \"2025-06-16\", \"end_location\": {\"name\": \"GER03\", \"type\": \"DEAL\"}, \"start_location\": {\"name\": \"GER02\", \"type\": \"TERM\"}, \"truck_number\": 1}": {
    "load": [
      273,
      274,
      280,
      283,
      284,
      286
    ]
  },
  "{\"departure_date\": \"2025-06-18\", \"end_location\": {\"name\": \"GER03\", \"type\": \"DEAL\"}, \"start_location\": {\"name\": \"BEL01\", \"type\": \"TERM\"}, \"truck_number\": 1}": {
    "load": [
      275,
      278,
      279
    ]
  },
  "{\"departure_date\": \"2025-06-13\", \"end_location\": {\"name\": \"BEL01\", \"type\": \"TERM\"}, \"start_location\": {\"name\": \"GER01\", \"type\": \"PLANT\"}, \"truck_number\": 11}": {
    "load": [
      281,
      287,
      289,
      441,
      442,
      445,
      450,
      451,
      454,
      457,
      458,
      459
    ]
  },
  "{\"departure_date\": \"2025-06-17\", \"end_location\": {\"name\": \"GER03\", \"type\": \"DEAL\"}, \"start_location\": {\"name\": \"BEL01\", \"type\": \"TERM\"}, \"truck_number\": 1}": {
    "load": [
      281,
      287,
      289
    ]
  },
  "{\"departure_date\": \"2025-06-27\", \"end_location\": {\"name\": \"GER03\", \"type\": \"DEAL\"}, \"start_location\": {\"name\": \"GER02\", \"type\": \"TERM\"}, \"truck_number\": 1}": {
    "load": [
      290,
      320
    ]
  },
  "{\"departure_date\": \"2025-06-23\", \"end_location\": {\"name\": \"GER03\", \"type\": \"DEAL\"}, \"start_location\": {\"name\": \"BEL01\", \"type\": \"TERM\"}, \"truck_number\": 1}": {
    "load": [
      291,
      293,
      294,
      297,
      300,
      308
    ]
  },
  "{\"departure_date\": \"2025-06-20\", \"end_location\": {\"name\": \"GER03\", \"type\": \"DEAL\"}, \"start_location\": {\"name\": \"GER02\", \"type\": \"TERM\"}, \"truck_number\": 1}": {
    "load": [
      292,
      295
    ]
  },
  "{\"departure_date\": \"2025-06-24\", \"end_location\": {\"name\": \"GER03\", \"type\": \"DEAL\"}, \"start_location\": {\"name\": \"BEL01\", \"type\": \"TERM\"}, \"truck_number\": 1}": {
    "load": [
      296,
      299,
      301
    ]
  },
  "{\"departure_date\": \"2025-06-25\", \"end_location\": {\"name\": \"GER03\", \"type\": \"DEAL\"}, \"start_location\": {\"name\": \"BEL01\", \"type\": \"TERM\"}, \"truck_number\": 1}": {
    "load": [
      298,
      302,
      303,
      304,
      306,
      310,
      312
    ]
  },
  "{\"departure_date\": \"2025-07-01\", \"end_location\": {\"name\": \"GER03\", \"type\": \"DEAL\"}, \"start_location\": {\"name\": \"BEL01\", \"type\": \"TERM\"}, \"truck_number\": 1}": {
    "load": [
      305,
      307,
      339
    ]
  },
  "{\"departure_date\": \"2025-07-02\", \"end_location\": {\"name\": \"GER03\", \"type\": \"DEAL\"}, \"start_location\": {\"name\": \"BEL01\", \"type\": \"TERM\"}, \"truck_number\": 1}": {
    "load": [
      309,
      326,
      330,
      332,
      334,
      335,
      337
    ]
  },
  "{\"departure_date\": \"2025-06-30\", \"end_location\": {\"name\": \"GER03\", \"type\": \"DEAL\"}, \"start_location\": {\"name\": \"GER02\", \"type\": \"TERM\"}, \"truck_number\": 1}": {
    "load": [
      311,
      321
    ]
  },
  "{\"departure_date\": \"2025-06-30\", \"end_location\": {\"name\": \"GER03\", \"type\": \"DEAL\"}, \"start_location\": {\"name\": \"BEL01\", \"type\": \"TERM\"}, \"truck_number\": 1}": {
    "load": [
      313,
      314,
      315,
      318,
      319,
      325,
      328,
      329
    ]
  },
  "{\"departure_date\": \"2025-07-04\", \"end_location\": {\"name\": \"GER03\", \"type\": \"DEAL\"}, \"start_location\": {\"name\": \"GER02\", \"type\": \"TERM\"}, \"truck_number\": 1}": {
    "load": [
      316,
      322,
      323,
      324,
      347
    ]
  },
  "{\"departure_date\": \"2025-07-02\", \"end_location\": {\"name\": \"GER03\", \"type\": \"DEAL\"}, \"start_location\": {\"name\": \"GER02\", \"type\": \"TERM\"}, \"truck_number\": 1}": {
    "load": [
      317
    ]
  },
  "{\"departure_date\": \"2025-06-24\", \"end_location\": {\"name\": \"GER02\", \"type\": \"TERM\"}, \"start_location\": {\"name\": \"GER01\", \"type\": \"PLANT\"}, \"truck_number\": 1}": {
    "load": [
      320,
      500,
      502,
      504
    ]
  },
  "{\"departure_date\": \"2025-07-08\", \"end_location\": {\"name\": \"GER03\", \"type\": \"DEAL\"}, \"start_location\": {\"name\": \"BEL01\", \"type\": \"TERM\"}, \"truck_number\": 1}": {
    "load": [
      327,
      336,
      353,
      358
    ]
  },
  "{\"departure_date\": \"2025-07-07\", \"end_location\": {\"name\": \"GER03\", \"type\": \"DEAL\"}, \"start_location\": {\"name\": \"BEL01\", \"type\": \"TERM\"}, \"truck_number\": 1}": {
    "load": [
      331,
      351,
      352,
      354
    ]
  },
  "{\"departure_date\": \"2025-07-09\", \"end_location\": {\"name\": \"GER03\", \"type\": \"DEAL\"}, \"start_location\": {\"name\": \"BEL01\", \"type\": \"TERM\"}, \"truck_number\": 1}": {
    "load": [
      333,
      341,
      342,
      349,
      356,
      359,
      361,
      362,
      364
    ]
  },
  "{\"departure_date\": \"2025-07-07\", \"end_location\": {\"name\": \"GER03\", \"type\": \"DEAL\"}, \"start_location\": {\"name\": \"GER02\", \"type\": \"TERM\"}, \"truck_number\": 1}": {
    "load": [
      338,
      348
    ]
  },
  "{\"departure_date\": \"2025-06-30\", \"end_location\": {\"name\": \"GER02\", \"type\": \"TERM\"}, \"start_location\": {\"name\": \"GER01\", \"type\": \"PLANT\"}, \"truck_number\": 1}": {
    "load": [
      340,
      344
    ]
  },
  "{\"departure_date\": \"2025-07-03\", \"end_location\": {\"name\": \"GER03\", \"type\": \"DEAL\"}, \"start_location\": {\"name\": \"GER02\", \"type\": \"TERM\"}, \"truck_number\": 1}": {
    "load": [
      340,
      344
    ]
  },
  "{\"departure_date\": \"2025-07-09\", \"end_location\": {\"name\": \"GER03\", \"type\": \"DEAL\"}, \"start_location\": {\"name\": \"GER02\", \"type\": \"TERM\"}, \"truck_number\": 1}": {
    "load": [
      343,
      345,
      346,
      350,
      357
    ]
  },
  "{\"departure_date\": \"2025-07-01\", \"end_location\": {\"name\": \"GER02\", \"type\": \"TERM\"}, \"start_location\": {\"name\": \"GER01\", \"type\": \"PLANT\"}, \"truck_number\": 1}": {
    "load": [
      347
    ]
  },
  "{\"departure_date\": \"2025-07-14\", \"end_location\": {\"name\": \"GER03\", \"type\": \"DEAL\"}, \"start_location\": {\"name\": \"GER02\", \"type\": \"TERM\"}, \"truck_number\": 1}": {
    "load": [
      355,
      360,
      368,
      369,
      370,
      371,
      374
    ]
  },
  "{\"departure_date\": \"2025-07-15\", \"end_location\": {\"name\": \"GER03\", \"type\": \"DEAL\"}, \"start_location\": {\"name\": \"BEL01\", \"type\": \"TERM\"}, \"truck_number\": 1}": {
    "load": [
      363,
      376,
      377,
      378,
      380,
      387,
      388
    ]
  },
  "{\"departure_date\": \"2025-07-15\", \"end_location\": {\"name\": \"GER02\", \"type\": \"TERM\"}, \"start_location\": {\"name\": \"GER01\", \"type\": \"PLANT\"}, \"truck_number\": 1}": {
    "load": [
      365,
      372,
      382,
      383,
      389
    ]
  },
  "{\"departure_date\": \"2025-07-18\", \"end_location\": {\"name\": \"GER03\", \"type\": \"DEAL\"}, \"start_location\": {\"name\": \"GER02\", \"type\": \"TERM\"}, \"truck_number\": 1}": {
    "load": [
      365,
      372,
      382,
      383,
      389
    ]
  },
  "{\"departure_date\": \"2025-07-07\", \"end_location\": {\"name\": \"GER02\", \"type\": \"TERM\"}, \"start_location\": {\"name\": \"GER01\", \"type\": \"PLANT\"}, \"truck_number\": 1}": {
    "load": [
      366,
      367,
      566,
      569
    ]
  },
  "{\"departure_date\": \"2025-07-10\", \"end_location\": {\"name\": \"GER03\", \"type\": \"DEAL\"}, \"start_location\": {\"name\": \"GER02\", \"type\": \"TERM\"}, \"truck_number\": 1}": {
    "load": [
      366,
      367
    ]
  },
  "{\"departure_date\": \"2025-07-21\", \"end_location\": {\"name\": \"GER03\", \"type\": \"DEAL\"}, \"start_location\": {\"name\": \"BEL01\", \"type\": \"TERM\"}, \"truck_number\": 1}": {
    "load": [
      373,
      375,
      379,
      381,
      384,
      385,
      386
    ]
  },
  "{\"departure_date\": \"2025-07-11\", \"end_location\": {\"name\": \"BEL01\", \"type\": \"TERM\"}, \"start_location\": {\"name\": \"GER01\", \"type\": \"PLANT\"}, \"truck_number\": 11}": {
    "load": [
      380,
      387,
      388,
      573,
      583,
      586,
      591,
      593,
      594,
      595,
      598,
      599
    ]
  },
  "{\"departure_date\": \"2025-06-11\", \"end_location\": {\"name\": \"ITA01\", \"type\": \"DEAL\"}, \"start_location\": {\"name\": \"GER02\", \"type\": \"TERM\"}, \"truck_number\": 1}": {
    "load": [
      390,
      395,
      396,
      397,
      398,
      399,
      400,
      402,
      406,
      407,
      409,
      410,
      411,
      413,
      414,
      415,
      416,
      417,
      418,
      420,
      421,
      422,
      423,
      424
    ]
  },
  "{\"departure_date\": \"2025-06-06\", \"end_location\": {\"name\": \"ITA01\", \"type\": \"DEAL\"}, \"start_location\": {\"name\": \"GER02\", \"type\": \"TERM\"}, \"truck_number\": 1}": {
    "load": [
      391,
      392,
      393,
      394
    ]
  },
  "{\"departure_date\": \"2025-06-09\", \"end_location\": {\"name\": \"ITA01\", \"type\": \"DEAL\"}, \"start_location\": {\"name\": \"BEL01\", \"type\": \"TERM\"}, \"truck_number\": 1}": {
    "load": [
      401,
      419
    ]
  },
  "{\"departure_date\": \"2025-06-10\", \"end_location\": {\"name\": \"ITA01\", \"type\": \"DEAL\"}, \"start_location\": {\"name\": \"BEL01\", \"type\": \"TERM\"}, \"truck_number\": 1}": {
    "load": [
      403,
      404,
      405,
      408,
      412
    ]
  },
  "{\"departure_date\": \"2025-06-13\", \"end_location\": {\"name\": \"ITA01\", \"type\": \"DEAL\"}, \"start_location\": {\"name\": \"GER02\", \"type\": \"TERM\"}, \"truck_number\": 1}": {
    "load": [
      425,
      426,
      427,
      428,
      429,
      430,
      431,
      432,
      433,
      434
    ]
  },
  "{\"departure_date\": \"2025-06-17\", \"end_location\": {\"name\": \"ITA01\", \"type\": \"DEAL\"}, \"start_location\": {\"name\": \"BEL01\", \"type\": \"TERM\"}, \"truck_number\": 1}": {
    "load": [
      435,
      436,
      438,
      441,
      445,
      448,
      450,
      451,
      454,
      457,
      458,
      459
    ]
  },
  "{\"departure_date\": \"2025-06-20\", \"end_location\": {\"name\": \"ITA01\", \"type\": \"DEAL\"}, \"start_location\": {\"name\": \"GER02\", \"type\": \"TERM\"}, \"truck_number\": 1}": {
    "load": [
      437,
      439,
      444,
      447,
      449,
      452,
      453,
      455,
      456,
      460,
      469
    ]
  },
  "{\"departure_date\": \"2025-06-20\", \"end_location\": {\"name\": \"ITA01\", \"type\": \"DEAL\"}, \"start_location\": {\"name\": \"BEL01\", \"type\": \"TERM\"}, \"truck_number\": 1}": {
    "load": [
      440,
      443,
      464
    ]
  },
  "{\"departure_date\": \"2025-06-18\", \"end_location\": {\"name\": \"ITA01\", \"type\": \"DEAL\"}, \"start_location\": {\"name\": \"BEL01\", \"type\": \"TERM\"}, \"truck_number\": 1}": {
    "load": [
      442
    ]
  },
  "{\"departure_date\": \"2025-06-25\", \"end_location\": {\"name\": \"ITA01\", \"type\": \"DEAL\"}, \"start_location\": {\"name\": \"GER02\", \"type\": \"TERM\"}, \"truck_number\": 1}": {
    "load": [
      446,
      461,
      462,
      465,
      466,
      468,
      470,
      471,
      472,
      474,
      475,
      477,
      480,
      481,
      482,
      483,
      484,
      486,
      487,
      489,
      490,
      491,
      493
    ]
  },
  "{\"departure_date\": \"2025-06-12\", \"end_location\": {\"name\": \"BEL01\", \"type\": \"TERM\"}, \"start_location\": {\"name\": \"GER01\", \"type\": \"PLANT\"}, \"truck_number\": 1}": {
    "load": [
      448
    ]
  },
  "{\"departure_date\": \"2025-06-24\", \"end_location\": {\"name\": \"ITA01\", \"type\": \"DEAL\"}, \"start_location\": {\"name\": \"BEL01\", \"type\": \"TERM\"}, \"truck_number\": 1}": {
    "load": [
      463,
      488,
      494
    ]
  },
  "{\"departure_date\": \"2025-06-25\", \"end_location\": {\"name\": \"ITA01\", \"type\": \"DEAL\"}, \"start_location\": {\"name\": \"BEL01\", \"type\": \"TERM\"}, \"truck_number\": 1}": {
    "load": [
      467,
      476,
      479
    ]
  },
  "{\"departure_date\": \"2025-06-19\", \"end_location\": {\"name\": \"GER02\", \"type\": \"TERM\"}, \"start_location\": {\"name\": \"GER01\", \"type\": \"PLANT\"}, \"truck_number\": 1}": {
    "load": [
      470,
      471,
      475,
      478,
      480,
      483,
      486,
      487,
      490,
      491,
      492
    ]
  },
  "{\"departure_date\": \"2025-06-20\", \"end_location\": {\"name\": \"GER02\", \"type\": \"TERM\"}, \"start_location\": {\"name\": \"GER01\", \"type\": \"PLANT\"}, \"truck_number\": 1}": {
    "load": [
      472,
      474,
      477,
      481,
      482,
      484,
      489,
      493
    ]
  },
  "{\"departure_date\": \"2025-06-23\", \"end_location\": {\"name\": \"ITA01\", \"type\": \"DEAL\"}, \"start_location\": {\"name\": \"BEL01\", \"type\": \"TERM\"}, \"truck_number\": 1}": {
    "load": [
      473
    ]
  },
  "{\"departure_date\": \"2025-06-27\", \"end_location\": {\"name\": \"ITA01\", \"type\": \"DEAL\"}, \"start_location\": {\"name\": \"GER02\", \"type\": \"TERM\"}, \"truck_number\": 1}": {
    "load": [
      478,
      492,
      497,
      499,
      500,
      502,
      504
    ]
  },
  "{\"departure_date\": \"2025-07-02\", \"end_location\": {\"name\": \"ITA01\", \"type\": \"DEAL\"}, \"start_location\": {\"name\": \"GER02\", \"type\": \"TERM\"}, \"truck_number\": 1}": {
    "load": [
      485,
      495,
      496,
      498,
      501,
      503,
      505,
      506,
      507,
      508,
      509,
      510,
      511,
      512,
      514,
      516,
      517,
      518,
      519,
      520,
      521,
      523,
      524,
      526,
      527,
      528
    ]
  },
  "{\"departure_date\": \"2025-06-23\", \"end_location\": {\"name\": \"GER02\", \"type\": \"TERM\"}, \"start_location\": {\"name\": \"GER01\", \"type\": \"PLANT\"}, \"truck_number\": 1}": {
    "load": [
      497,
      499
    ]
  },
  "{\"departure_date\": \"2025-06-25\", \"end_location\": {\"name\": \"GER02\", \"type\": \"TERM\"}, \"start_location\": {\"name\": \"GER01\", \"type\": \"PLANT\"}, \"truck_number\": 1}": {
    "load": [
      505,
      506,
      507,
      508,
      509
    ]
  },
  "{\"departure_date\": \"2025-06-26\", \"end_location\": {\"name\": \"GER02\", \"type\": \"TERM\"}, \"start_location\": {\"name\": \"GER01\", \"type\": \"PLANT\"}, \"truck_number\": 11}": {
    "load": [
      510,
      511,
      512,
      514,
      516,
      517,
      518,
      519,
      520,
      521,
      523,
      524,
      526,
      527,
      528
    ]
  },
  "{\"departure_date\": \"2025-06-30\", \"end_location\": {\"name\": \"ITA01\", \"type\": \"DEAL\"}, \"start_location\": {\"name\": \"BEL01\", \"type\": \"TERM\"}, \"truck_number\": 1}": {
    "load": [
      513,
      515,
      522,
      525,
      529
    ]
  },
  "{\"departure_date\": \"2025-07-09\", \"end_location\": {\"name\": \"ITA01\", \"type\": \"DEAL\"}, \"start_location\": {\"name\": \"GER02\", \"type\": \"TERM\"}, \"truck_number\": 1}": {
    "load": [
      530,
      532,
      535,
      536,
      537,
      540,
      544,
      546,
      547,
      548,
      549,
      551,
      552,
      553,
      556,
      557,
      558,
      559,
      560,
      561,
      562,
      564
    ]
  },
  "{\"departure_date\": \"2025-07-04\", \"end_location\": {\"name\": \"ITA01\", \"type\": \"DEAL\"}, \"start_location\": {\"name\": \"BEL01\", \"type\": \"TERM\"}, \"truck_number\": 1}": {
    "load": [
      531,
      533,
      534,
      539
    ]
  },
  "{\"departure_date\": \"2025-07-08\", \"end_location\": {\"name\": \"ITA01\", \"type\": \"DEAL\"}, \"start_location\": {\"name\": \"BEL01\", \"type\": \"TERM\"}, \"truck_number\": 1}": {
    "load": [
      538,
      541,
      542,
      543,
      545,
      550,
      554,
      555,
      563
    ]
  },
  "{\"departure_date\": \"2025-07-16\", \"end_location\": {\"name\": \"ITA01\", \"type\": \"DEAL\"}, \"start_location\": {\"name\": \"GER02\", \"type\": \"TERM\"}, \"truck_number\": 1}": {
    "load": [
      565,
      567,
      568,
      571,
      572,
      574,
      575,
      576,
      577,
      578,
      579,
      580,
      581,
      582,
      584,
      585,
      587,
      588,
      589,
      590,
      592,
      596,
      597
    ]
  },
  "{\"departure_date\": \"2025-07-11\", \"end_location\": {\"name\": \"ITA01\", \"type\": \"DEAL\"}, \"start_location\": {\"name\": \"GER02\", \"type\": \"TERM\"}, \"truck_number\": 1}": {
    "load": [
      566,
      569
    ]
  },
  "{\"departure_date\": \"2025-07-10\", \"end_location\": {\"name\": \"GER02\", \"type\": \"TERM\"}, \"start_location\": {\"name\": \"GER01\", \"type\": \"PLANT\"}, \"truck_number\": 11}": {
    "load": [
      567,
      571,
      576,
      577,
      578,
      579,
      580,
      581,
      582,
      584,
      585,
      588,
      589,
      590,
      596
    ]
  },
  "{\"departure_date\": \"2025-07-15\", \"end_location\": {\"name\": \"ITA01\", \"type\": \"DEAL\"}, \"start_location\": {\"name\": \"BEL01\", \"type\": \"TERM\"}, \"truck_number\": 1}": {
    "load": [
      570,
      573,
      583,
      586,
      591,
      593,
      594,
      595,
      598,
      599
    ]
  },
  "{\"departure_date\": \"2025-06-03\", \"end_location\": {\"name\": \"GER02\", \"type\": \"TERM\"}, \"start_location\": {\"name\": \"GER01\", \"type\": \"PLANT\"}, \"truck_number\": 1}": {
    "load": []
  },
  "{\"departure_date\": \"2025-06-05\", \"end_location\": {\"name\": \"GER02\", \"type\": \"TERM\"}, \"start_location\": {\"name\": \"GER01\", \"type\": \"PLANT\"}, \"truck_number\": 1}": {
    "load": []
  },
  "{\"departure_date\": \"2025-06-11\", \"end_location\": {\"name\": \"GER02\", \"type\": \"TERM\"}, \"start_location\": {\"name\": \"GER01\", \"type\": \"PLANT\"}, \"truck_number\": 1}": {
    "load": []
  },
  "{\"departure_date\": \"2025-06-12\", \"end_location\": {\"name\": \"GER02\", \"type\": \"TERM\"}, \"start_location\": {\"name\": \"GER01\", \"type\": \"PLANT\"}, \"truck_number\": 1}": {
    "load": []
  },
  "{\"departure_date\": \"2025-06-16\", \"end_location\": {\"name\": \"GER02\", \"type\": \"TERM\"}, \"start_location\": {\"name\": \"GER01\", \"type\": \"PLANT\"}, \"truck_number\": 1}": {
    "load": []
  },
  "{\"departure_date\": \"2025-06-18\", \"end_location\": {\"name\": \"GER02\", \"type\": \"TERM\"}, \"start_location\": {\"name\": \"GER01\", \"type\": \"PLANT\"}, \"truck_number\": 1}": {
    "load": []
  },
  "{\"departure_date\": \"2025-06-26\", \"end_location\": {\"name\": \"GER02\", \"type\": \"TERM\"}, \"start_location\": {\"name\": \"GER01\", \"type\": \"PLANT\"}, \"truck_number\": 1}": {
    "load": []
  },
  "{\"departure_date\": \"2025-06-27\", \"end_location\": {\"name\": \"GER02\", \"type\": \"TERM\"}, \"start_location\": {\"name\": \"GER01\", \"type\": \"PLANT\"}, \"truck_number\": 1}": {
    "load": []
  },
  "{\"departure_date\": \"2025-07-02\", \"end_location\": {\"name\": \"GER02\", \"type\": \"TERM\"}, \"start_location\": {\"name\": \"GER01\", \"type\": \"PLANT\"}, \"truck_number\": 1}": {
    "load": []
  },
  "{\"departure_date\": \"2025-07-09\", \"end_location\": {\"name\": \"GER02\", \"type\": \"TERM\"}, \"start_location\": {\"name\": \"GER01\", \"type\": \"PLANT\"}, \"truck_number\": 1}": {
    "load": []
  },
  "{\"departure_date\": \"2025-07-14\", \"end_location\": {\"name\": \"GER02\", \"type\": \"TERM\"}, \"start_location\": {\"name\": \"GER01\", \"type\": \"PLANT\"}, \"truck_number\": 1}": {
    "load": []
  },
  "{\"departure_date\": \"2025-07-16\", \"end_location\": {\"name\": \"GER02\", \"type\": \"TERM\"}, \"start_location\": {\"name\": \"GER01\", \"type\": \"PLANT\"}, \"truck_number\": 1}": {
    "load": []
  },
  "{\"departure_date\": \"2025-07-17\", \"end_location\": {\"name\": \"GER02\", \"type\": \"TERM\"}, \"start_location\": {\"name\": \"GER01\", \"type\": \"PLANT\"}, \"truck_number\": 1}": {
    "load": []
  },
  "{\"departure_date\": \"2025-07-18\", \"end_location\": {\"name\": \"GER02\", \"type\": \"TERM\"}, \"start_location\": {\"name\": \"GER01\", \"type\": \"PLANT\"}, \"truck_number\": 1}": {
    "load": []
  },
  "{\"departure_date\": \"2025-07-21\", \"end_location\": {\"name\": \"GER02\", \"type\": \"TERM\"}, \"start_location\": {\"name\": \"GER01\", \"type\": \"PLANT\"}, \"truck_number\": 1}": {
    "load": []
  },
  "{\"departure_date\": \"2025-07-22\", \"end_location\": {\"name\": \"GER02\", \"type\": \"TERM\"}, \"start_location\": {\"name\": \"GER01\", \"type\": \"PLANT\"}, \"truck_number\": 1}": {
    "load": []
  },
  "{\"departure_date\": \"2025-07-23\", \"end_location\": {\"name\": \"GER02\", \"type\": \"TERM\"}, \"start_location\": {\"name\": \"GER01\", \"type\": \"PLANT\"}, \"truck_number\": 1}": {
    "load": []
  },
  "{\"departure_date\": \"2025-07-24\", \"end_location\": {\"name\": \"GER02\", \"type\": \"TERM\"}, \"start_location\": {\"name\": \"GER01\", \"type\": \"PLANT\"}, \"truck_number\": 1}": {
    "load": []
  },
  "{\"departure_date\": \"2025-07-25\", \"end_location\": {\"name\": \"GER02\", \"type\": \"TERM\"}, \"start_location\": {\"name\": \"GER01\", \"type\": \"PLANT\"}, \"truck_number\": 1}": {
    "load": []
  },
  "{\"departure_date\": \"2025-07-28\", \"end_location\": {\"name\": \"GER02\", \"type\": \"TERM\"}, \"start_location\": {\"name\": \"GER01\", \"type\": \"PLANT\"}, \"truck_number\": 1}": {
    "load": []
  },
  "{\"departure_date\": \"2025-07-29\", \"end_location\": {\"name\": \"GER02\", \"type\": \"TERM\"}, \"start_location\": {\"name\": \"GER01\", \"type\": \"PLANT\"}, \"truck_number\": 1}": {
    "load": []
  },
  "{\"departure_date\": \"2025-07-30\", \"end_location\": {\"name\": \"GER02\", \"type\": \"TERM\"}, \"start_location\": {\"name\": \"GER01\", \"type\": \"PLANT\"}, \"truck_number\": 1}": {
    "load": []
  },
  "{\"departure_date\": \"2025-07-31\", \"end_location\": {\"name\": \"GER02\", \"type\": \"TERM\"}, \"start_location\": {\"name\": \"GER01\", \"type\": \"PLANT\"}, \"truck_number\": 1}": {
    "load": []
  },
  "{\"departure_date\": \"2025-08-01\", \"end_location\": {\"name\": \"GER02\", \"type\": \"TERM\"}, \"start_location\": {\"name\": \"GER01\", \"type\": \"PLANT\"}, \"truck_number\": 1}": {
    "load": []
  },
  "{\"departure_date\": \"2025-08-04\", \"end_location\": {\"name\": \"GER02\", \"type\": \"TERM\"}, \"start_location\": {\"name\": \"GER01\", \"type\": \"PLANT\"}, \"truck_number\": 1}": {
    "load": []
  },
  "{\"departure_date\": \"2025-08-05\", \"end_location\": {\"name\": \"GER02\", \"type\": \"TERM\"}, \"start_location\": {\"name\": \"GER01\", \"type\": \"PLANT\"}, \"truck_number\": 1}": {
    "load": []
  },
  "{\"departure_date\": \"2025-08-06\", \"end_location\": {\"name\": \"GER02\", \"type\": \"TERM\"}, \"start_location\": {\"name\": \"GER01\", \"type\": \"PLANT\"}, \"truck_number\": 1}": {
    "load": []
  },
  "{\"departure_date\": \"2025-08-07\", \"end_location\": {\"name\": \"GER02\", \"type\": \"TERM\"}, \"start_location\": {\"name\": \"GER01\", \"type\": \"PLANT\"}, \"truck_number\": 1}": {
    "load": []
  },
  "{\"departure_date\": \"2025-08-08\", \"end_location\": {\"name\": \"GER02\", \"type\": \"TERM\"}, \"start_location\": {\"name\": \"GER01\", \"type\": \"PLANT\"}, \"truck_number\": 1}": {
    "load": []
  },
  "{\"departure_date\": \"2025-08-11\", \"end_location\": {\"name\": \"GER02\", \"type\": \"TERM\"}, \"start_location\": {\"name\": \"GER01\", \"type\": \"PLANT\"}, \"truck_number\": 1}": {
    "load": []
  },
  "{\"departure_date\": \"2025-08-12\", \"end_location\": {\"name\": \"GER02\", \"type\": \"TERM\"}, \"start_location\": {\"name\": \"GER01\", \"type\": \"PLANT\"}, \"truck_number\": 1}": {
    "load": []
  },
  "{\"departure_date\": \"2025-08-13\", \"end_location\": {\"name\": \"GER02\", \"type\": \"TERM\"}, \"start_location\": {\"name\": \"GER01\", \"type\": \"PLANT\"}, \"truck_number\": 1}": {
    "load": []
  },
  "{\"departure_date\": \"2025-08-14\", \"end_location\": {\"name\": \"GER02\", \"type\": \"TERM\"}, \"start_location\": {\"name\": \"GER01\", \"type\": \"PLANT\"}, \"truck_number\": 1}": {
    "load": []
  },
  "{\"departure_date\": \"2025-08-15\", \"end_location\": {\"name\": \"GER02\", \"type\": \"TERM\"}, \"start_location\": {\"name\": \"GER01\", \"type\": \"PLANT\"}, \"truck_number\": 1}": {
    "load": []
  },
  "{\"departure_date\": \"2025-08-18\", \"end_location\": {\"name\": \"GER02\", \"type\": \"TERM\"}, \"start_location\": {\"name\": \"GER01\", \"type\": \"PLANT\"}, \"truck_number\": 1}": {
    "load": []
  },
  "{\"departure_date\": \"2025-08-19\", \"end_location\": {\"name\": \"GER02\", \"type\": \"TERM\"}, \"start_location\": {\"name\": \"GER01\", \"type\": \"PLANT\"}, \"truck_number\": 1}": {
    "load": []
  },
  "{\"departure_date\": \"2025-08-20\", \"end_location\": {\"name\": \"GER02\", \"type\": \"TERM\"}, \"start_location\": {\"name\": \"GER01\", \"type\": \"PLANT\"}, \"truck_number\": 1}": {
    "load": []
  },
  "{\"departure_date\": \"2025-08-21\", \"end_location\": {\"name\": \"GER02\", \"type\": \"TERM\"}, \"start_location\": {\"name\": \"GER01\", \"type\": \"PLANT\"}, \"truck_number\": 1}": {
    "load": []
  },
  "{\"departure_date\": \"2025-08-22\", \"end_location\": {\"name\": \"GER02\", \"type\": \"TERM\"}, \"start_location\": {\"name\": \"GER01\", \"type\": \"PLANT\"}, \"truck_number\": 1}": {
    "load": []
  },
  "{\"departure_date\": \"2025-08-26\", \"end_location\": {\"name\": \"GER02\", \"type\": \"TERM\"}, \"start_location\": {\"name\": \"GER01\", \"type\": \"PLANT\"}, \"truck_number\": 1}": {
    "load": []
  },
  "{\"departure_date\": \"2025-08-27\", \"end_location\": {\"name\": \"GER02\", \"type\": \"TERM\"}, \"start_location\": {\"name\": \"GER01\", \"type\": \"PLANT\"}, \"truck_number\": 1}": {
    "load": []
  },
  "{\"departure_date\": \"2025-08-28\", \"end_location\": {\"name\": \"GER02\", \"type\": \"TERM\"}, \"start_location\": {\"name\": \"GER01\", \"type\": \"PLANT\"}, \"truck_number\": 1}": {
    "load": []
  },
  "{\"departure_date\": \"2025-08-29\", \"end_location\": {\"name\": \"GER02\", \"type\": \"TERM\"}, \"start_location\": {\"name\": \"GER01\", \"type\": \"PLANT\"}, \"truck_number\": 1}": {
    "load": []
  },
  "{\"departure_date\": \"2025-07-17\", \"end_location\": {\"name\": \"GER02\", \"type\": \"TERM\"}, \"start_location\": {\"name\": \"GER01\", \"type\": \"PLANT\"}, \"truck_number\": 11}": {
    "load": []
  },
  "{\"departure_date\": \"2025-07-24\", \"end_location\": {\"name\": \"GER02\", \"type\": \"TERM\"}, \"start_location\": {\"name\": \"GER01\", \"type\": \"PLANT\"}, \"truck_number\": 11}": {
    "load": []
  },
  "{\"departure_date\": \"2025-07-31\", \"end_location\": {\"name\": \"GER02\", \"type\": \"TERM\"}, \"start_location\": {\"name\": \"GER01\", \"type\": \"PLANT\"}, \"truck_number\": 11}": {
    "load": []
  },
  "{\"departure_date\": \"2025-08-05\", \"end_location\": {\"name\": \"GER02\", \"type\": \"TERM\"}, \"start_location\": {\"name\": \"GER01\", \"type\": \"PLANT\"}, \"truck_number\": 11}": {
    "load": []
  },
  "{\"departure_date\": \"2025-08-12\", \"end_location\": {\"name\": \"GER02\", \"type\": \"TERM\"}, \"start_location\": {\"name\": \"GER01\", \"type\": \"PLANT\"}, \"truck_number\": 11}": {
    "load": []
  },
  "{\"departure_date\": \"2025-08-14\", \"end_location\": {\"name\": \"GER02\", \"type\": \"TERM\"}, \"start_location\": {\"name\": \"GER01\", \"type\": \"PLANT\"}, \"truck_number\": 11}": {
    "load": []
  },
  "{\"departure_date\": \"2025-08-19\", \"end_location\": {\"name\": \"GER02\", \"type\": \"TERM\"}, \"start_location\": {\"name\": \"GER01\", \"type\": \"PLANT\"}, \"truck_number\": 11}": {
    "load": []
  },
  "{\"departure_date\": \"2025-08-21\", \"end_location\": {\"name\": \"GER02\", \"type\": \"TERM\"}, \"start_location\": {\"name\": \"GER01\", \"type\": \"PLANT\"}, \"truck_number\": 11}": {
    "load": []
  },
  "{\"departure_date\": \"2025-08-28\", \"end_location\": {\"name\": \"GER02\", \"type\": \"TERM\"}, \"start_location\": {\"name\": \"GER01\", \"type\": \"PLANT\"}, \"truck_number\": 11}": {
    "load": []
  },
  "{\"departure_date\": \"2025-06-02\", \"end_location\": {\"name\": \"BEL01\", \"type\": \"TERM\"}, \"start_location\": {\"name\": \"GER01\", \"type\": \"PLANT\"}, \"truck_number\": 1}": {
    "load": []
  },
  "{\"departure_date\": \"2025-06-06\", \"end_location\": {\"name\": \"BEL01\", \"type\": \"TERM\"}, \"start_location\": {\"name\": \"GER01\", \"type\": \"PLANT\"}, \"truck_number\": 1}": {
    "load": []
  },
  "{\"departure_date\": \"2025-06-11\", \"end_location\": {\"name\": \"BEL01\", \"type\": \"TERM\"}, \"start_location\": {\"name\": \"GER01\", \"type\": \"PLANT\"}, \"truck_number\": 1}": {
    "load": []
  },
  "{\"departure_date\": \"2025-06-16\", \"end_location\": {\"name\": \"BEL01\", \"type\": \"TERM\"}, \"start_location\": {\"name\": \"GER01\", \"type\": \"PLANT\"}, \"truck_number\": 1}": {
    "load": []
  },
  "{\"departure_date\": \"2025-07-04\", \"end_location\": {\"name\": \"BEL01\", \"type\": \"TERM\"}, \"start_location\": {\"name\": \"GER01\", \"type\": \"PLANT\"}, \"truck_number\": 1}": {
    "load": []
  },
  "{\"departure_date\": \"2025-07-10\", \"end_location\": {\"name\": \"BEL01\", \"type\": \"TERM\"}, \"start_location\": {\"name\": \"GER01\", \"type\": \"PLANT\"}, \"truck_number\": 1}": {
    "load": []
  },
  "{\"departure_date\": \"2025-07-11\", \"end_location\": {\"name\": \"BEL01\", \"type\": \"TERM\"}, \"start_location\": {\"name\": \"GER01\", \"type\": \"PLANT\"}, \"truck_number\": 1}": {
    "load": []
  },
  "{\"departure_date\": \"2025-07-14\", \"end_location\": {\"name\": \"BEL01\", \"type\": \"TERM\"}, \"start_location\": {\"name\": \"GER01\", \"type\": \"PLANT\"}, \"truck_number\": 1}": {
    "load": []
  },
  "{\"departure_date\": \"2025-07-17\", \"end_location\": {\"name\": \"BEL01\", \"type\": \"TERM\"}, \"start_location\": {\"name\": \"GER01\", \"type\": \"PLANT\"}, \"truck_number\": 1}": {
    "load": []
  },
  "{\"departure_date\": \"2025-07-18\", \"end_location\": {\"name\": \"BEL01\", \"type\": \"TERM\"}, \"start_location\": {\"name\": \"GER01\", \"type\": \"PLANT\"}, \"truck_number\": 1}": {
    "load": []
  },
  "{\"departure_date\": \"2025-07-21\", \"end_location\": {\"name\": \"BEL01\", \"type\": \"TERM\"}, \"start_location\": {\"name\": \"GER01\", \"type\": \"PLANT\"}, \"truck_number\": 1}": {
    "load": []
  },
  "{\"departure_date\": \"2025-07-22\", \"end_location\": {\"name\": \"BEL01\", \"type\": \"TERM\"}, \"start_location\": {\"name\": \"GER01\", \"type\": \"PLANT\"}, \"truck_number\": 1}": {
    "load": []
  },
  "{\"departure_date\": \"2025-07-28\", \"end_location\": {\"name\": \"BEL01\", \"type\": \"TERM\"}, \"start_location\": {\"name\": \"GER01\", \"type\": \"PLANT\"}, \"truck_number\": 1}": {
    "load": []
  },
  "{\"departure_date\": \"2025-07-29\", \"end_location\": {\"name\": \"BEL01\", \"type\": \"TERM\"}, \"start_location\": {\"name\": \"GER01\", \"type\": \"PLANT\"}, \"truck_number\": 1}": {
    "load": []
  },
  "{\"departure_date\": \"2025-07-31\", \"end_location\": {\"name\": \"BEL01\", \"type\": \"TERM\"}, \"start_location\": {\"name\": \"GER01\", \"type\": \"PLANT\"}, \"truck_number\": 1}": {
    "load": []
  },
  "{\"departure_date\": \"2025-08-01\", \"end_location\": {\"name\": \"BEL01\", \"type\": \"TERM\"}, \"start_location\": {\"name\": \"GER01\", \"type\": \"PLANT\"}, \"truck_number\": 1}": {
    "load": []
  },
  "{\"departure_date\": \"2025-08-04\", \"end_location\": {\"name\": \"BEL01\", \"type\": \"TERM\"}, \"start_location\": {\"name\": \"GER01\", \"type\": \"PLANT\"}, \"truck_number\": 1}": {
    "load": []
  },
  "{\"departure_date\": \"2025-08-05\", \"end_location\": {\"name\": \"BEL01\", \"type\": \"TERM\"}, \"start_location\": {\"name\": \"GER01\", \"type\": \"PLANT\"}, \"truck_number\": 1}": {
    "load": []
  },
  "{\"departure_date\": \"2025-08-08\", \"end_location\": {\"name\": \"BEL01\", \"type\": \"TERM\"}, \"start_location\": {\"name\": \"GER01\", \"type\": \"PLANT\"}, \"truck_number\": 1}": {
    "load": []
  },
  "{\"departure_date\": \"2025-08-11\", \"end_location\": {\"name\": \"BEL01\", \"type\": \"TERM\"}, \"start_location\": {\"name\": \"GER01\", \"type\": \"PLANT\"}, \"truck_number\": 1}": {
    "load": []
  },
  "{\"departure_date\": \"2025-08-14\", \"end_location\": {\"name\": \"BEL01\", \"type\": \"TERM\"}, \"start_location\": {\"name\": \"GER01\", \"type\": \"PLANT\"}, \"truck_number\": 1}": {
    "load": []
  },
  "{\"departure_date\": \"2025-08-15\", \"end_location\": {\"name\": \"BEL01\", \"type\": \"TERM\"}, \"start_location\": {\"name\": \"GER01\", \"type\": \"PLANT\"}, \"truck_number\": 1}": {
    "load": []
  },
  "{\"departure_date\": \"2025-08-18\", \"end_location\": {\"name\": \"BEL01\", \"type\": \"TERM\"}, \"start_location\": {\"name\": \"GER01\", \"type\": \"PLANT\"}, \"truck_number\": 1}": {
    "load": []
  },
  "{\"departure_date\": \"2025-08-21\", \"end_location\": {\"name\": \"BEL01\", \"type\": \"TERM\"}, \"start_location\": {\"name\": \"GER01\", \"type\": \"PLANT\"}, \"truck_number\": 1}": {
    "load": []
  },
  "{\"departure_date\": \"2025-08-22\", \"end_location\": {\"name\": \"BEL01\", \"type\": \"TERM\"}, \"start_location\": {\"name\": \"GER01\", \"type\": \"PLANT\"}, \"truck_number\": 1}": {
    "load": []
  },
  "{\"departure_date\": \"2025-08-25\", \"end_location\": {\"name\": \"BEL01\", \"type\": \"TERM\"}, \"start_location\": {\"name\": \"GER01\", \"type\": \"PLANT\"}, \"truck_number\": 1}": {
    "load": []
  },
  "{\"departure_date\": \"2025-08-27\", \"end_location\": {\"name\": \"BEL01\", \"type\": \"TERM\"}, \"start_location\": {\"name\": \"GER01\", \"type\": \"PLANT\"}, \"truck_number\": 1}": {
    "load": []
  },
  "{\"departure_date\": \"2025-08-29\", \"end_location\": {\"name\": \"BEL01\", \"type\": \"TERM\"}, \"start_location\": {\"name\": \"GER01\", \"type\": \"PLANT\"}, \"truck_number\": 1}": {
    "load": []
  },
  "{\"departure_date\": \"2025-09-01\", \"end_location\": {\"name\": \"BEL01\", \"type\": \"TERM\"}, \"start_location\": {\"name\": \"GER01\", \"type\": \"PLANT\"}, \"truck_number\": 1}": {
    "load": []
  },
  "{\"departure_date\": \"2025-07-18\", \"end_location\": {\"name\": \"BEL01\", \"type\": \"TERM\"}, \"start_location\": {\"name\": \"GER01\", \"type\": \"PLANT\"}, \"truck_number\": 11}": {
    "load": []
  },
  "{\"departure_date\": \"2025-07-25\", \"end_location\": {\"name\": \"BEL01\", \"type\": \"TERM\"}, \"start_location\": {\"name\": \"GER01\", \"type\": \"PLANT\"}, \"truck_number\": 11}": {
    "load": []
  },
  "{\"departure_date\": \"2025-08-01\", \"end_location\": {\"name\": \"BEL01\", \"type\": \"TERM\"}, \"start_location\": {\"name\": \"GER01\", \"type\": \"PLANT\"}, \"truck_number\": 11}": {
    "load": []
  },
  "{\"departure_date\": \"2025-08-06\", \"end_location\": {\"name\": \"BEL01\", \"type\": \"TERM\"}, \"start_location\": {\"name\": \"GER01\", \"type\": \"PLANT\"}, \"truck_number\": 11}": {
    "load": []
  },
  "{\"departure_date\": \"2025-08-13\", \"end_location\": {\"name\": \"BEL01\", \"type\": \"TERM\"}, \"start_location\": {\"name\": \"GER01\", \"type\": \"PLANT\"}, \"truck_number\": 11}": {
    "load": []
  },
  "{\"departure_date\": \"2025-08-15\", \"end_location\": {\"name\": \"BEL01\", \"type\": \"TERM\"}, \"start_location\": {\"name\": \"GER01\", \"type\": \"PLANT\"}, \"truck_number\": 11}": {
    "load": []
  },
  "{\"departure_date\": \"2025-08-20\", \"end_location\": {\"name\": \"BEL01\", \"type\": \"TERM\"}, \"start_location\": {\"name\": \"GER01\", \"type\": \"PLANT\"}, \"truck_number\": 11}": {
    "load": []
  },
  "{\"departure_date\": \"2025-08-22\", \"end_location\": {\"name\": \"BEL01\", \"type\": \"TERM\"}, \"start_location\": {\"name\": \"GER01\", \"type\": \"PLANT\"}, \"truck_number\": 11}": {
    "load": []
  },
  "{\"departure_date\": \"2025-08-29\", \"end_location\": {\"name\": \"BEL01\", \"type\": \"TERM\"}, \"start_location\": {\"name\": \"GER01\", \"type\": \"PLANT\"}, \"truck_number\": 11}": {
    "load": []
  },
  "{\"departure_date\": \"2025-06-04\", \"end_location\": {\"name\": \"ITA01\", \"type\": \"DEAL\"}, \"start_location\": {\"name\": \"GER02\", \"type\": \"TERM\"}, \"truck_number\": 1}": {
    "load": []
  },
  "{\"departure_date\": \"2025-07-18\", \"end_location\": {\"name\": \"ITA01\", \"type\": \"DEAL\"}, \"start_location\": {\"name\": \"GER02\", \"type\": \"TERM\"}, \"truck_number\": 1}": {
    "load": []
  },
  "{\"departure_date\": \"2025-07-23\", \"end_location\": {\"name\": \"ITA01\", \"type\": \"DEAL\"}, \"start_location\": {\"name\": \"GER02\", \"type\": \"TERM\"}, \"truck_number\": 1}": {
    "load": []
  },
  "{\"departure_date\": \"2025-07-25\", \"end_location\": {\"name\": \"ITA01\", \"type\": \"DEAL\"}, \"start_location\": {\"name\": \"GER02\", \"type\": \"TERM\"}, \"truck_number\": 1}": {
    "load": []
  },
  "{\"departure_date\": \"2025-07-30\", \"end_location\": {\"name\": \"ITA01\", \"type\": \"DEAL\"}, \"start_location\": {\"name\": \"GER02\", \"type\": \"TERM\"}, \"truck_number\": 1}": {
    "load": []
  },
  "{\"departure_date\": \"2025-08-01\", \"end_location\": {\"name\": \"ITA01\", \"type\": \"DEAL\"}, \"start_location\": {\"name\": \"GER02\", \"type\": \"TERM\"}, \"truck_number\": 1}": {
    "load": []
  },
  "{\"departure_date\": \"2025-08-06\", \"end_location\": {\"name\": \"ITA01\", \"type\": \"DEAL\"}, \"start_location\": {\"name\": \"GER02\", \"type\": \"TERM\"}, \"truck_number\": 1}": {
    "load": []
  },
  "{\"departure_date\": \"2025-08-08\", \"end_location\": {\"name\": \"ITA01\", \"type\": \"DEAL\"}, \"start_location\": {\"name\": \"GER02\", \"type\": \"TERM\"}, \"truck_number\": 1}": {
    "load": []
  },
  "{\"departure_date\": \"2025-08-13\", \"end_location\": {\"name\": \"ITA01\", \"type\": \"DEAL\"}, \"start_location\": {\"name\": \"GER02\", \"type\": \"TERM\"}, \"truck_number\": 1}": {
    "load": []
  },
  "{\"departure_date\": \"2025-08-15\", \"end_location\": {\"name\": \"ITA01\", \"type\": \"DEAL\"}, \"start_location\": {\"name\": \"GER02\", \"type\": \"TERM\"}, \"truck_number\": 1}": {
    "load": []
  },
  "{\"departure_date\": \"2025-08-20\", \"end_location\": {\"name\": \"ITA01\", \"type\": \"DEAL\"}, \"start_location\": {\"name\": \"GER02\", \"type\": \"TERM\"}, \"truck_number\": 1}": {
    "load": []
  },
  "{\"departure_date\": \"2025-08-22\", \"end_location\": {\"name\": \"ITA01\", \"type\": \"DEAL\"}, \"start_location\": {\"name\": \"GER02\", \"type\": \"TERM\"}, \"truck_number\": 1}": {
    "load": []
  },
  "{\"departure_date\": \"2025-08-27\", \"end_location\": {\"name\": \"ITA01\", \"type\": \"DEAL\"}, \"start_location\": {\"name\": \"GER02\", \"type\": \"TERM\"}, \"truck_number\": 1}": {
    "load": []
  },
  "{\"departure_date\": \"2025-08-29\", \"end_location\": {\"name\": \"ITA01\", \"type\": \"DEAL\"}, \"start_location\": {\"name\": \"GER02\", \"type\": \"TERM\"}, \"truck_number\": 1}": {
    "load": []
  },
  "{\"departure_date\": \"2025-06-03\", \"end_location\": {\"name\": \"FRA01\", \"type\": \"DEAL\"}, \"start_location\": {\"name\": \"GER02\", \"type\": \"TERM\"}, \"truck_number\": 1}": {
    "load": []
  },
  "{\"departure_date\": \"2025-06-04\", \"end_location\": {\"name\": \"FRA01\", \"type\": \"DEAL\"}, \"start_location\": {\"name\": \"GER02\", \"type\": \"TERM\"}, \"truck_number\": 1}": {
    "load": []
  },
  "{\"departure_date\": \"2025-06-05\", \"end_location\": {\"name\": \"FRA01\", \"type\": \"DEAL\"}, \"start_location\": {\"name\": \"GER02\", \"type\": \"TERM\"}, \"truck_number\": 1}": {
    "load": []
  },
  "{\"departure_date\": \"2025-06-12\", \"end_location\": {\"name\": \"FRA01\", \"type\": \"DEAL\"}, \"start_location\": {\"name\": \"GER02\", \"type\": \"TERM\"}, \"truck_number\": 1}": {
    "load": []
  },
  "{\"departure_date\": \"2025-06-19\", \"end_location\": {\"name\": \"FRA01\", \"type\": \"DEAL\"}, \"start_location\": {\"name\": \"GER02\", \"type\": \"TERM\"}, \"truck_number\": 1}": {
    "load": []
  },
  "{\"departure_date\": \"2025-06-25\", \"end_location\": {\"name\": \"FRA01\", \"type\": \"DEAL\"}, \"start_location\": {\"name\": \"GER02\", \"type\": \"TERM\"}, \"truck_number\": 1}": {
    "load": []
  },
  "{\"departure_date\": \"2025-06-26\", \"end_location\": {\"name\": \"FRA01\", \"type\": \"DEAL\"}, \"start_location\": {\"name\": \"GER02\", \"type\": \"TERM\"}, \"truck_number\": 1}": {
    "load": []
  },
  "{\"departure_date\": \"2025-07-01\", \"end_location\": {\"name\": \"FRA01\", \"type\": \"DEAL\"}, \"start_location\": {\"name\": \"GER02\", \"type\": \"TERM\"}, \"truck_number\": 1}": {
    "load": []
  },
  "{\"departure_date\": \"2025-07-02\", \"end_location\": {\"name\": \"FRA01\", \"type\": \"DEAL\"}, \"start_location\": {\"name\": \"GER02\", \"type\": \"TERM\"}, \"truck_number\": 1}": {
    "load": []
  },
  "{\"departure_date\": \"2025-07-03\", \"end_location\": {\"name\": \"FRA01\", \"type\": \"DEAL\"}, \"start_location\": {\"name\": \"GER02\", \"type\": \"TERM\"}, \"truck_number\": 1}": {
    "load": []
  },
  "{\"departure_date\": \"2025-07-16\", \"end_location\": {\"name\": \"FRA01\", \"type\": \"DEAL\"}, \"start_location\": {\"name\": \"GER02\", \"type\": \"TERM\"}, \"truck_number\": 1}": {
    "load": []
  },
  "{\"departure_date\": \"2025-07-17\", \"end_location\": {\"name\": \"FRA01\", \"type\": \"DEAL\"}, \"start_location\": {\"name\": \"GER02\", \"type\": \"TERM\"}, \"truck_number\": 1}": {
    "load": []
  },
  "{\"departure_date\": \"2025-07-22\", \"end_location\": {\"name\": \"FRA01\", \"type\": \"DEAL\"}, \"start_location\": {\"name\": \"GER02\", \"type\": \"TERM\"}, \"truck_number\": 1}": {
    "load": []
  },
  "{\"departure_date\": \"2025-07-23\", \"end_location\": {\"name\": \"FRA01\", \"type\": \"DEAL\"}, \"start_location\": {\"name\": \"GER02\", \"type\": \"TERM\"}, \"truck_number\": 1}": {
    "load": []
  },
  "{\"departure_date\": \"2025-07-24\", \"end_location\": {\"name\": \"FRA01\", \"type\": \"DEAL\"}, \"start_location\": {\"name\": \"GER02\", \"type\": \"TERM\"}, \"truck_number\": 1}": {
    "load": []
  },
  "{\"departure_date\": \"2025-07-28\", \"end_location\": {\"name\": \"FRA01\", \"type\": \"DEAL\"}, \"start_location\": {\"name\": \"GER02\", \"type\": \"TERM\"}, \"truck_number\": 1}": {
    "load": []
  },
  "{\"departure_date\": \"2025-07-29\", \"end_location\": {\"name\": \"FRA01\", \"type\": \"DEAL\"}, \"start_location\": {\"name\": \"GER02\", \"type\": \"TERM\"}, \"truck_number\": 1}": {
    "load": []
  },
  "{\"departure_date\": \"2025-07-30\", \"end_location\": {\"name\": \"FRA01\", \"type\": \"DEAL\"}, \"start_location\": {\"name\": \"GER02\", \"type\": \"TERM\"}, \"truck_number\": 1}": {
    "load": []
  },
  "{\"departure_date\": \"2025-07-31\", \"end_location\": {\"name\": \"FRA01\", \"type\": \"DEAL\"}, \"start_location\": {\"name\": \"GER02\", \"type\": \"TERM\"}, \"truck_number\": 1}": {
    "load": []
  },
  "{\"departure_date\": \"2025-08-04\", \"end_location\": {\"name\": \"FRA01\", \"type\": \"DEAL\"}, \"start_location\": {\"name\": \"GER02\", \"type\": \"TERM\"}, \"truck_number\": 1}": {
    "load": []
  },
  "{\"departure_date\": \"2025-08-05\", \"end_location\": {\"name\": \"FRA01\", \"type\": \"DEAL\"}, \"start_location\": {\"name\": \"GER02\", \"type\": \"TERM\"}, \"truck_number\": 1}": {
    "load": []
  },
  "{\"departure_date\": \"2025-08-06\", \"end_location\": {\"name\": \"FRA01\", \"type\": \"DEAL\"}, \"start_location\": {\"name\": \"GER02\", \"type\": \"TERM\"}, \"truck_number\": 1}": {
    "load": []
  },
  "{\"departure_date\": \"2025-08-07\", \"end_location\": {\"name\": \"FRA01\", \"type\": \"DEAL\"}, \"start_location\": {\"name\": \"GER02\", \"type\": \"TERM\"}, \"truck_number\": 1}": {
    "load": []
  },
  "{\"departure_date\": \"2025-08-11\", \"end_location\": {\"name\": \"FRA01\", \"type\": \"DEAL\"}, \"start_location\": {\"name\": \"GER02\", \"type\": \"TERM\"}, \"truck_number\": 1}": {
    "load": []
  },
  "{\"departure_date\": \"2025-08-12\", \"end_location\": {\"name\": \"FRA01\", \"type\": \"DEAL\"}, \"start_location\": {\"name\": \"GER02\", \"type\": \"TERM\"}, \"truck_number\": 1}": {
    "load": []
  },
  "{\"departure_date\": \"2025-08-13\", \"end_location\": {\"name\": \"FRA01\", \"type\": \"DEAL\"}, \"start_location\": {\"name\": \"GER02\", \"type\": \"TERM\"}, \"truck_number\": 1}": {
    "load": []
  },
  "{\"departure_date\": \"2025-08-14\", \"end_location\": {\"name\": \"FRA01\", \"type\": \"DEAL\"}, \"start_location\": {\"name\": \"GER02\", \"type\": \"TERM\"}, \"truck_number\": 1}": {
    "load": []
  },
  "{\"departure_date\": \"2025-08-18\", \"end_location\": {\"name\": \"FRA01\", \"type\": \"DEAL\"}, \"start_location\": {\"name\": \"GER02\", \"type\": \"TERM\"}, \"truck_number\": 1}": {
    "load": []
  },
  "{\"departure_date\": \"2025-08-19\", \"end_location\": {\"name\": \"FRA01\", \"type\": \"DEAL\"}, \"start_location\": {\"name\": \"GER02\", \"type\": \"TERM\"}, \"truck_number\": 1}": {
    "load": []
  },
  "{\"departure_date\": \"2025-08-21\", \"end_location\": {\"name\": \"FRA01\", \"type\": \"DEAL\"}, \"start_location\": {\"name\": \"GER02\", \"type\": \"TERM\"}, \"truck_number\": 1}": {
    "load": []
  },
  "{\"departure_date\": \"2025-08-25\", \"end_location\": {\"name\": \"FRA01\", \"type\": \"DEAL\"}, \"start_location\": {\"name\": \"GER02\", \"type\": \"TERM\"}, \"truck_number\": 1}": {
    "load": []
  },
  "{\"departure_date\": \"2025-08-26\", \"end_location\": {\"name\": \"FRA01\", \"type\": \"DEAL\"}, \"start_location\": {\"name\": \"GER02\", \"type\": \"TERM\"}, \"truck_number\": 1}": {
    "load": []
  },
  "{\"departure_date\": \"2025-08-27\", \"end_location\": {\"name\": \"FRA01\", \"type\": \"DEAL\"}, \"start_location\": {\"name\": \"GER02\", \"type\": \"TERM\"}, \"truck_number\": 1}": {
    "load": []
  },
  "{\"departure_date\": \"2025-08-28\", \"end_location\": {\"name\": \"FRA01\", \"type\": \"DEAL\"}, \"start_location\": {\"name\": \"GER02\", \"type\": \"TERM\"}, \"truck_number\": 1}": {
    "load": []
  },
  "{\"departure_date\": \"2025-09-01\", \"end_location\": {\"name\": \"FRA01\", \"type\": \"DEAL\"}, \"start_location\": {\"name\": \"GER02\", \"type\": \"TERM\"}, \"truck_number\": 1}": {
    "load": []
  },
  "{\"departure_date\": \"2025-06-02\", \"end_location\": {\"name\": \"GER03\", \"type\": \"DEAL\"}, \"start_location\": {\"name\": \"GER02\", \"type\": \"TERM\"}, \"truck_number\": 1}": {
    "load": []
  },
  "{\"departure_date\": \"2025-06-04\", \"end_location\": {\"name\": \"GER03\", \"type\": \"DEAL\"}, \"start_location\": {\"name\": \"GER02\", \"type\": \"TERM\"}, \"truck_number\": 1}": {
    "load": []
  },
  "{\"departure_date\": \"2025-06-09\", \"end_location\": {\"name\": \"GER03\", \"type\": \"DEAL\"}, \"start_location\": {\"name\": \"GER02\", \"type\": \"TERM\"}, \"truck_number\": 1}": {
    "load": []
  },
  "{\"departure_date\": \"2025-06-11\", \"end_location\": {\"name\": \"GER03\", \"type\": \"DEAL\"}, \"start_location\": {\"name\": \"GER02\", \"type\": \"TERM\"}, \"truck_number\": 1}": {
    "load": []
  },
  "{\"departure_date\": \"2025-06-19\", \"end_location\": {\"name\": \"GER03\", \"type\": \"DEAL\"}, \"start_location\": {\"name\": \"GER02\", \"type\": \"TERM\"}, \"truck_number\": 1}": {
    "load": []
  },
  "{\"departure_date\": \"2025-06-23\", \"end_location\": {\"name\": \"GER03\", \"type\": \"DEAL\"}, \"start_location\": {\"name\": \"GER02\", \"type\": \"TERM\"}, \"truck_number\": 1}": {
    "load": []
  },
  "{\"departure_date\": \"2025-06-25\", \"end_location\": {\"name\": \"GER03\", \"type\": \"DEAL\"}, \"start_location\": {\"name\": \"GER02\", \"type\": \"TERM\"}, \"truck_number\": 1}": {
    "load": []
  },
  "{\"departure_date\": \"2025-06-26\", \"end_location\": {\"name\": \"GER03\", \"type\": \"DEAL\"}, \"start_location\": {\"name\": \"GER02\", \"type\": \"TERM\"}, \"truck_number\": 1}": {
    "load": []
  },
  "{\"departure_date\": \"2025-07-11\", \"end_location\": {\"name\": \"GER03\", \"type\": \"DEAL\"}, \"start_location\": {\"name\": \"GER02\", \"type\": \"TERM\"}, \"truck_number\": 1}": {
    "load": []
  },
  "{\"departure_date\": \"2025-07-16\", \"end_location\": {\"name\": \"GER03\", \"type\": \"DEAL\"}, \"start_location\": {\"name\": \"GER02\", \"type\": \"TERM\"}, \"truck_number\": 1}": {
    "load": []
  },
  "{\"departure_date\": \"2025-07-21\", \"end_location\": {\"name\": \"GER03\", \"type\": \"DEAL\"}, \"start_location\": {\"name\": \"GER02\", \"type\": \"TERM\"}, \"truck_number\": 1}": {
    "load": []
  },
  "{\"departure_date\": \"2025-07-23\", \"end_location\": {\"name\": \"GER03\", \"type\": \"DEAL\"}, \"start_location\": {\"name\": \"GER02\", \"type\": \"TERM\"}, \"truck_number\": 1}": {
    "load": []
  },
  "{\"departure_date\": \"2025-07-24\", \"end_location\": {\"name\": \"GER03\", \"type\": \"DEAL\"}, \"start_location\": {\"name\": \"GER02\", \"type\": \"TERM\"}, \"truck_number\": 1}": {
    "load": []
  },
  "{\"departure_date\": \"2025-07-25\", \"end_location\": {\"name\": \"GER03\", \"type\": \"DEAL\"}, \"start_location\": {\"name\": \"GER02\", \"type\": \"TERM\"}, \"truck_number\": 1}": {
    "load": []
  },
  "{\"departure_date\": \"2025-07-28\", \"end_location\": {\"name\": \"GER03\", \"type\": \"DEAL\"}, \"start_location\": {\"name\": \"GER02\", \"type\": \"TERM\"}, \"truck_number\": 1}": {
    "load": []
  },
  "{\"departure_date\": \"2025-07-30\", \"end_location\": {\"name\": \"GER03\", \"type\": \"DEAL\"}, \"start_location\": {\"name\": \"GER02\", \"type\": \"TERM\"}, \"truck_number\": 1}": {
    "load": []
  },
  "{\"departure_date\": \"2025-07-31\", \"end_location\": {\"name\": \"GER03\", \"type\": \"DEAL\"}, \"start_location\": {\"name\": \"GER02\", \"type\": \"TERM\"}, \"truck_number\": 1}": {
    "load": []
  },
  "{\"departure_date\": \"2025-08-01\", \"end_location\": {\"name\": \"GER03\", \"type\": \"DEAL\"}, \"start_location\": {\"name\": \"GER02\", \"type\": \"TERM\"}, \"truck_number\": 1}": {
    "load": []
  },
  "{\"departure_date\": \"2025-08-04\", \"end_location\": {\"name\": \"GER03\", \"type\": \"DEAL\"}, \"start_location\": {\"name\": \"GER02\", \"type\": \"TERM\"}, \"truck_number\": 1}": {
    "load": []
  },
  "{\"departure_date\": \"2025-08-06\", \"end_location\": {\"name\": \"GER03\", \"type\": \"DEAL\"}, \"start_location\": {\"name\": \"GER02\", \"type\": \"TERM\"}, \"truck_number\": 1}": {
    "load": []
  },
  "{\"departure_date\": \"2025-08-07\", \"end_location\": {\"name\": \"GER03\", \"type\": \"DEAL\"}, \"start_location\": {\"name\": \"GER02\", \"type\": \"TERM\"}, \"truck_number\": 1}": {
    "load": []
  },
  "{\"departure_date\": \"2025-08-08\", \"end_location\": {\"name\": \"GER03\", \"type\": \"DEAL\"}, \"start_location\": {\"name\": \"GER02\", \"type\": \"TERM\"}, \"truck_number\": 1}": {
    "load": []
  },
  "{\"departure_date\": \"2025-08-11\", \"end_location\": {\"name\": \"GER03\", \"type\": \"DEAL\"}, \"start_location\": {\"name\": \"GER02\", \"type\": \"TERM\"}, \"truck_number\": 1}": {
    "load": []
  },
  "{\"departure_date\": \"2025-08-14\", \"end_location\": {\"name\": \"GER03\", \"type\": \"DEAL\"}, \"start_location\": {\"name\": \"GER02\", \"type\": \"TERM\"}, \"truck_number\": 1}": {
    "load": []
  },
  "{\"departure_date\": \"2025-08-15\", \"end_location\": {\"name\": \"GER03\", \"type\": \"DEAL\"}, \"start_location\": {\"name\": \"GER02\", \"type\": \"TERM\"}, \"truck_number\": 1}": {
    "load": []
  },
  "{\"departure_date\": \"2025-08-18\", \"end_location\": {\"name\": \"GER03\", \"type\": \"DEAL\"}, \"start_location\": {\"name\": \"GER02\", \"type\": \"TERM\"}, \"truck_number\": 1}": {
    "load": []
  },
  "{\"departure_date\": \"2025-08-21\", \"end_location\": {\"name\": \"GER03\", \"type\": \"DEAL\"}, \"start_location\": {\"name\": \"GER02\", \"type\": \"TERM\"}, \"truck_number\": 1}": {
    "load": []
  },
  "{\"departure_date\": \"2025-08-22\", \"end_location\": {\"name\": \"GER03\", \"type\": \"DEAL\"}, \"start_location\": {\"name\": \"GER02\", \"type\": \"TERM\"}, \"truck_number\": 1}": {
    "load": []
  },
  "{\"departure_date\": \"2025-08-25\", \"end_location\": {\"name\": \"GER03\", \"type\": \"DEAL\"}, \"start_location\": {\"name\": \"GER02\", \"type\": \"TERM\"}, \"truck_number\": 1}": {
    "load": []
  },
  "{\"departure_date\": \"2025-08-27\", \"end_location\": {\"name\": \"GER03\", \"type\": \"DEAL\"}, \"start_location\": {\"name\": \"GER02\", \"type\": \"TERM\"}, \"truck_number\": 1}": {
    "load": []
  },
  "{\"departure_date\": \"2025-08-28\", \"end_location\": {\"name\": \"GER03\", \"type\": \"DEAL\"}, \"start_location\": {\"name\": \"GER02\", \"type\": \"TERM\"}, \"truck_number\": 1}": {
    "load": []
  },
  "{\"departure_date\": \"2025-08-29\", \"end_location\": {\"name\": \"GER03\", \"type\": \"DEAL\"}, \"start_location\": {\"name\": \"GER02\", \"type\": \"TERM\"}, \"truck_number\": 1}": {
    "load": []
  },
  "{\"departure_date\": \"2025-09-01\", \"end_location\": {\"name\": \"GER03\", \"type\": \"DEAL\"}, \"start_location\": {\"name\": \"GER02\", \"type\": \"TERM\"}, \"truck_number\": 1}": {
    "load": []
  },
  "{\"departure_date\": \"2025-06-02\", \"end_location\": {\"name\": \"GER03\", \"type\": \"DEAL\"}, \"start_location\": {\"name\": \"BEL01\", \"type\": \"TERM\"}, \"truck_number\": 1}": {
    "load": []
  },
  "{\"departure_date\": \"2025-06-03\", \"end_location\": {\"name\": \"GER03\", \"type\": \"DEAL\"}, \"start_location\": {\"name\": \"BEL01\", \"type\": \"TERM\"}, \"truck_number\": 1}": {
    "load": []
  },
  "{\"departure_date\": \"2025-07-23\", \"end_location\": {\"name\": \"GER03\", \"type\": \"DEAL\"}, \"start_location\": {\"name\": \"BEL01\", \"type\": \"TERM\"}, \"truck_number\": 1}": {
    "load": []
  },
  "{\"departure_date\": \"2025-07-28\", \"end_location\": {\"name\": \"GER03\", \"type\": \"DEAL\"}, \"start_location\": {\"name\": \"BEL01\", \"type\": \"TERM\"}, \"truck_number\": 1}": {
    "load": []
  },
  "{\"departure_date\": \"2025-07-29\", \"end_location\": {\"name\": \"GER03\", \"type\": \"DEAL\"}, \"start_location\": {\"name\": \"BEL01\", \"type\": \"TERM\"}, \"truck_number\": 1}": {
    "load": []
  },
  "{\"departure_date\": \"2025-07-30\", \"end_location\": {\"name\": \"GER03\", \"type\": \"DEAL\"}, \"start_location\": {\"name\": \"BEL01\", \"type\": \"TERM\"}, \"truck_number\": 1}": {
    "load": []
  },
  "{\"departure_date\": \"2025-08-04\", \"end_location\": {\"name\": \"GER03\", \"type\": \"DEAL\"}, \"start_location\": {\"name\": \"BEL01\", \"type\": \"TERM\"}, \"truck_number\": 1}": {
    "load": []
  },
  "{\"departure_date\": \"2025-08-05\", \"end_location\": {\"name\": \"GER03\", \"type\": \"DEAL\"}, \"start_location\": {\"name\": \"BEL01\", \"type\": \"TERM\"}, \"truck_number\": 1}": {
    "load": []
  },
  "{\"departure_date\": \"2025-08-06\", \"end_location\": {\"name\": \"GER03\", \"type\": \"DEAL\"}, \"start_location\": {\"name\": \"BEL01\", \"type\": \"TERM\"}, \"truck_number\": 1}": {
    "load": []
  },
  "{\"departure_date\": \"2025-08-11\", \"end_location\": {\"name\": \"GER03\", \"type\": \"DEAL\"}, \"start_location\": {\"name\": \"BEL01\", \"type\": \"TERM\"}, \"truck_number\": 1}": {
    "load": []
  },
  "{\"departure_date\": \"2025-08-12\", \"end_location\": {\"name\": \"GER03\", \"type\": \"DEAL\"}, \"start_location\": {\"name\": \"BEL01\", \"type\": \"TERM\"}, \"truck_number\": 1}": {
    "load": []
  },
  "{\"departure_date\": \"2025-08-13\", \"end_location\": {\"name\": \"GER03\", \"type\": \"DEAL\"}, \"start_location\": {\"name\": \"BEL01\", \"type\": \"TERM\"}, \"truck_number\": 1}": {
    "load": []
  },
  "{\"departure_date\": \"2025-08-18\", \"end_location\": {\"name\": \"GER03\", \"type\": \"DEAL\"}, \"start_location\": {\"name\": \"BEL01\", \"type\": \"TERM\"}, \"truck_number\": 1}": {
    "load": []
  },
  "{\"departure_date\": \"2025-08-19\", \"end_location\": {\"name\": \"GER03\", \"type\": \"DEAL\"}, \"start_location\": {\"name\": \"BEL01\", \"type\": \"TERM\"}, \"truck_number\": 1}": {
    "load": []
  },
  "{\"departure_date\": \"2025-08-20\", \"end_location\": {\"name\": \"GER03\", \"type\": \"DEAL\"}, \"start_location\": {\"name\": \"BEL01\", \"type\": \"TERM\"}, \"truck_number\": 1}": {
    "load": []
  },
  "{\"departure_date\": \"2025-08-25\", \"end_location\": {\"name\": \"GER03\", \"type\": \"DEAL\"}, \"start_location\": {\"name\": \"BEL01\", \"type\": \"TERM\"}, \"truck_number\": 1}": {
    "load": []
  },
  "{\"departure_date\": \"2025-08-26\", \"end_location\": {\"name\": \"GER03\", \"type\": \"DEAL\"}, \"start_location\": {\"name\": \"BEL01\", \"type\": \"TERM\"}, \"truck_number\": 1}": {
    "load": []
  },
  "{\"departure_date\": \"2025-08-27\", \"end_location\": {\"name\": \"GER03\", \"type\": \"DEAL\"}, \"start_location\": {\"name\": \"BEL01\", \"type\": \"TERM\"}, \"truck_number\": 1}": {
    "load": []
  },
  "{\"departure_date\": \"2025-09-01\", \"end_location\": {\"name\": \"GER03\", \"type\": \"DEAL\"}, \"start_location\": {\"name\": \"BEL01\", \"type\": \"TERM\"}, \"truck_number\": 1}": {
    "load": []
  },
  "{\"departure_date\": \"2025-06-02\", \"end_location\": {\"name\": \"FRA01\", \"type\": \"DEAL\"}, \"start_location\": {\"name\": \"BEL01\", \"type\": \"TERM\"}, \"truck_number\": 1}": {
    "load": []
  },
  "{\"departure_date\": \"2025-06-04\", \"end_location\": {\"name\": \"FRA01\", \"type\": \"DEAL\"}, \"start_location\": {\"name\": \"BEL01\", \"type\": \"TERM\"}, \"truck_number\": 1}": {
    "load": []
  },
  "{\"departure_date\": \"2025-06-05\", \"end_location\": {\"name\": \"FRA01\", \"type\": \"DEAL\"}, \"start_location\": {\"name\": \"BEL01\", \"type\": \"TERM\"}, \"truck_number\": 1}": {
    "load": []
  },
  "{\"departure_date\": \"2025-06-11\", \"end_location\": {\"name\": \"FRA01\", \"type\": \"DEAL\"}, \"start_location\": {\"name\": \"BEL01\", \"type\": \"TERM\"}, \"truck_number\": 1}": {
    "load": []
  },
  "{\"departure_date\": \"2025-06-17\", \"end_location\": {\"name\": \"FRA01\", \"type\": \"DEAL\"}, \"start_location\": {\"name\": \"BEL01\", \"type\": \"TERM\"}, \"truck_number\": 1}": {
    "load": []
  },
  "{\"departure_date\": \"2025-06-18\", \"end_location\": {\"name\": \"FRA01\", \"type\": \"DEAL\"}, \"start_location\": {\"name\": \"BEL01\", \"type\": \"TERM\"}, \"truck_number\": 1}": {
    "load": []
  },
  "{\"departure_date\": \"2025-06-25\", \"end_location\": {\"name\": \"FRA01\", \"type\": \"DEAL\"}, \"start_location\": {\"name\": \"BEL01\", \"type\": \"TERM\"}, \"truck_number\": 1}": {
    "load": []
  },
  "{\"departure_date\": \"2025-07-09\", \"end_location\": {\"name\": \"FRA01\", \"type\": \"DEAL\"}, \"start_location\": {\"name\": \"BEL01\", \"type\": \"TERM\"}, \"truck_number\": 1}": {
    "load": []
  },
  "{\"departure_date\": \"2025-07-11\", \"end_location\": {\"name\": \"FRA01\", \"type\": \"DEAL\"}, \"start_location\": {\"name\": \"BEL01\", \"type\": \"TERM\"}, \"truck_number\": 1}": {
    "load": []
  },
  "{\"departure_date\": \"2025-07-15\", \"end_location\": {\"name\": \"FRA01\", \"type\": \"DEAL\"}, \"start_location\": {\"name\": \"BEL01\", \"type\": \"TERM\"}, \"truck_number\": 1}": {
    "load": []
  },
  "{\"departure_date\": \"2025-07-16\", \"end_location\": {\"name\": \"FRA01\", \"type\": \"DEAL\"}, \"start_location\": {\"name\": \"BEL01\", \"type\": \"TERM\"}, \"truck_number\": 1}": {
    "load": []
  },
  "{\"departure_date\": \"2025-07-17\", \"end_location\": {\"name\": \"FRA01\", \"type\": \"DEAL\"}, \"start_location\": {\"name\": \"BEL01\", \"type\": \"TERM\"}, \"truck_number\": 1}": {
    "load": []
  },
  "{\"departure_date\": \"2025-07-22\", \"end_location\": {\"name\": \"FRA01\", \"type\": \"DEAL\"}, \"start_location\": {\"name\": \"BEL01\", \"type\": \"TERM\"}, \"truck_number\": 1}": {
    "load": []
  },
  "{\"departure_date\": \"2025-07-23\", \"end_location\": {\"name\": \"FRA01\", \"type\": \"DEAL\"}, \"start_location\": {\"name\": \"BEL01\", \"type\": \"TERM\"}, \"truck_number\": 1}": {
    "load": []
  },
  "{\"departure_date\": \"2025-07-25\", \"end_location\": {\"name\": \"FRA01\", \"type\": \"DEAL\"}, \"start_location\": {\"name\": \"BEL01\", \"type\": \"TERM\"}, \"truck_number\": 1}": {
    "load": []
  },
  "{\"departure_date\": \"2025-07-28\", \"end_location\": {\"name\": \"FRA01\", \"type\": \"DEAL\"}, \"start_location\": {\"name\": \"BEL01\", \"type\": \"TERM\"}, \"truck_number\": 1}": {
    "load": []
  },
  "{\"departure_date\": \"2025-07-29\", \"end_location\": {\"name\": \"FRA01\", \"type\": \"DEAL\"}, \"start_location\": {\"name\": \"BEL01\", \"type\": \"TERM\"}, \"truck_number\": 1}": {
    "load": []
  },
  "{\"departure_date\": \"2025-07-31\", \"end_location\": {\"name\": \"FRA01\", \"type\": \"DEAL\"}, \"start_location\": {\"name\": \"BEL01\", \"type\": \"TERM\"}, \"truck_number\": 1}": {
    "load": []
  },
  "{\"departure_date\": \"2025-08-01\", \"end_location\": {\"name\": \"FRA01\", \"type\": \"DEAL\"}, \"start_location\": {\"name\": \"BEL01\", \"type\": \"TERM\"}, \"truck_number\": 1}": {
    "load": []
  },
  "{\"departure_date\": \"2025-08-04\", \"end_location\": {\"name\": \"FRA01\", \"type\": \"DEAL\"}, \"start_location\": {\"name\": \"BEL01\", \"type\": \"TERM\"}, \"truck_number\": 1}": {
    "load": []
  },
  "{\"departure_date\": \"2025-08-05\", \"end_location\": {\"name\": \"FRA01\", \"type\": \"DEAL\"}, \"start_location\": {\"name\": \"BEL01\", \"type\": \"TERM\"}, \"truck_number\": 1}": {
    "load": []
  },
  "{\"departure_date\": \"2025-08-06\", \"end_location\": {\"name\": \"FRA01\", \"type\": \"DEAL\"}, \"start_location\": {\"name\": \"BEL01\", \"type\": \"TERM\"}, \"truck_number\": 1}": {
    "load": []
  },
  "{\"departure_date\": \"2025-08-07\", \"end_location\": {\"name\": \"FRA01\", \"type\": \"DEAL\"}, \"start_location\": {\"name\": \"BEL01\", \"type\": \"TERM\"}, \"truck_number\": 1}": {
    "load": []
  },
  "{\"departure_date\": \"2025-08-08\", \"end_location\": {\"name\": \"FRA01\", \"type\": \"DEAL\"}, \"start_location\": {\"name\": \"BEL01\", \"type\": \"TERM\"}, \"truck_number\": 1}": {
    "load": []
  },
  "{\"departure_date\": \"2025-08-11\", \"end_location\": {\"name\": \"FRA01\", \"type\": \"DEAL\"}, \"start_location\": {\"name\": \"BEL01\", \"type\": \"TERM\"}, \"truck_number\": 1}": {
    "load": []
  },
  "{\"departure_date\": \"2025-08-12\", \"end_location\": {\"name\": \"FRA01\", \"type\": \"DEAL\"}, \"start_location\": {\"name\": \"BEL01\", \"type\": \"TERM\"}, \"truck_number\": 1}": {
    "load": []
  },
  "{\"departure_date\": \"2025-08-13\", \"end_location\": {\"name\": \"FRA01\", \"type\": \"DEAL\"}, \"start_location\": {\"name\": \"BEL01\", \"type\": \"TERM\"}, \"truck_number\": 1}": {
    "load": []
  },
  "{\"departure_date\": \"2025-08-14\", \"end_location\": {\"name\": \"FRA01\", \"type\": \"DEAL\"}, \"start_location\": {\"name\": \"BEL01\", \"type\": \"TERM\"}, \"truck_number\": 1}": {
    "load": []
  },
  "{\"departure_date\": \"2025-08-15\", \"end_location\": {\"name\": \"FRA01\", \"type\": \"DEAL\"}, \"start_location\": {\"name\": \"BEL01\", \"type\": \"TERM\"}, \"truck_number\": 1}": {
    "load": []
  },
  "{\"departure_date\": \"2025-08-18\", \"end_location\": {\"name\": \"FRA01\", \"type\": \"DEAL\"}, \"start_location\": {\"name\": \"BEL01\", \"type\": \"TERM\"}, \"truck_number\": 1}": {
    "load": []
  },
  "{\"departure_date\": \"2025-08-19\", \"end_location\": {\"name\": \"FRA01\", \"type\": \"DEAL\"}, \"start_location\": {\"name\": \"BEL01\", \"type\": \"TERM\"}, \"truck_number\": 1}": {
    "load": []
  },
  "{\"departure_date\": \"2025-08-20\", \"end_location\": {\"name\": \"FRA01\", \"type\": \"DEAL\"}, \"start_location\": {\"name\": \"BEL01\", \"type\": \"TERM\"}, \"truck_number\": 1}": {
    "load": []
  },
  "{\"departure_date\": \"2025-08-21\", \"end_location\": {\"name\": \"FRA01\", \"type\": \"DEAL\"}, \"start_location\": {\"name\": \"BEL01\", \"type\": \"TERM\"}, \"truck_number\": 1}": {
    "load": []
  },
  "{\"departure_date\": \"2025-08-22\", \"end_location\": {\"name\": \"FRA01\", \"type\": \"DEAL\"}, \"start_location\": {\"name\": \"BEL01\", \"type\": \"TERM\"}, \"truck_number\": 1}": {
    "load": []
  },
  "{\"departure_date\": \"2025-08-25\", \"end_location\": {\"name\": \"FRA01\", \"type\": \"DEAL\"}, \"start_location\": {\"name\": \"BEL01\", \"type\": \"TERM\"}, \"truck_number\": 1}": {
    "load": []
  },
  "{\"departure_date\": \"2025-08-26\", \"end_location\": {\"name\": \"FRA01\", \"type\": \"DEAL\"}, \"start_location\": {\"name\": \"BEL01\", \"type\": \"TERM\"}, \"truck_number\": 1}": {
    "load": []
  },
  "{\"departure_date\": \"2025-08-27\", \"end_location\": {\"name\": \"FRA01\", \"type\": \"DEAL\"}, \"start_location\": {\"name\": \"BEL01\", \"type\": \"TERM\"}, \"truck_number\": 1}": {
    "load": []
  },
  "{\"departure_date\": \"2025-08-28\", \"end_location\": {\"name\": \"FRA01\", \"type\": \"DEAL\"}, \"start_location\": {\"name\": \"BEL01\", \"type\": \"TERM\"}, \"truck_number\": 1}": {
    "load": []
  },
  "{\"departure_date\": \"2025-08-29\", \"end_location\": {\"name\": \"FRA01\", \"type\": \"DEAL\"}, \"start_location\": {\"name\": \"BEL01\", \"type\": \"TERM\"}, \"truck_number\": 1}": {
    "load": []
  },
  "{\"departure_date\": \"2025-06-02\", \"end_location\": {\"name\": \"ITA01\", \"type\": \"DEAL\"}, \"start_location\": {\"name\": \"BEL01\", \"type\": \"TERM\"}, \"truck_number\": 1}": {
    "load": []
  },
  "{\"departure_date\": \"2025-06-04\", \"end_location\": {\"name\": \"ITA01\", \"type\": \"DEAL\"}, \"start_location\": {\"name\": \"BEL01\", \"type\": \"TERM\"}, \"truck_number\": 1}": {
    "load": []
  },
  "{\"departure_date\": \"2025-06-11\", \"end_location\": {\"name\": \"ITA01\", \"type\": \"DEAL\"}, \"start_location\": {\"name\": \"BEL01\", \"type\": \"TERM\"}, \"truck_number\": 1}": {
    "load": []
  },
  "{\"departure_date\": \"2025-06-13\", \"end_location\": {\"name\": \"ITA01\", \"type\": \"DEAL\"}, \"start_location\": {\"name\": \"BEL01\", \"type\": \"TERM\"}, \"truck_number\": 1}": {
    "load": []
  },
  "{\"departure_date\": \"2025-06-27\", \"end_location\": {\"name\": \"ITA01\", \"type\": \"DEAL\"}, \"start_location\": {\"name\": \"BEL01\", \"type\": \"TERM\"}, \"truck_number\": 1}": {
    "load": []
  },
  "{\"departure_date\": \"2025-07-01\", \"end_location\": {\"name\": \"ITA01\", \"type\": \"DEAL\"}, \"start_location\": {\"name\": \"BEL01\", \"type\": \"TERM\"}, \"truck_number\": 1}": {
    "load": []
  },
  "{\"departure_date\": \"2025-07-02\", \"end_location\": {\"name\": \"ITA01\", \"type\": \"DEAL\"}, \"start_location\": {\"name\": \"BEL01\", \"type\": \"TERM\"}, \"truck_number\": 1}": {
    "load": []
  },
  "{\"departure_date\": \"2025-07-09\", \"end_location\": {\"name\": \"ITA01\", \"type\": \"DEAL\"}, \"start_location\": {\"name\": \"BEL01\", \"type\": \"TERM\"}, \"truck_number\": 1}": {
    "load": []
  },
  "{\"departure_date\": \"2025-07-11\", \"end_location\": {\"name\": \"ITA01\", \"type\": \"DEAL\"}, \"start_location\": {\"name\": \"BEL01\", \"type\": \"TERM\"}, \"truck_number\": 1}": {
    "load": []
  },
  "{\"departure_date\": \"2025-07-16\", \"end_location\": {\"name\": \"ITA01\", \"type\": \"DEAL\"}, \"start_location\": {\"name\": \"BEL01\", \"type\": \"TERM\"}, \"truck_number\": 1}": {
    "load": []
  },
  "{\"departure_date\": \"2025-07-18\", \"end_location\": {\"name\": \"ITA01\", \"type\": \"DEAL\"}, \"start_location\": {\"name\": \"BEL01\", \"type\": \"TERM\"}, \"truck_number\": 1}": {
    "load": []
  },
  "{\"departure_date\": \"2025-07-21\", \"end_location\": {\"name\": \"ITA01\", \"type\": \"DEAL\"}, \"start_location\": {\"name\": \"BEL01\", \"type\": \"TERM\"}, \"truck_number\": 1}": {
    "load": []
  },
  "{\"departure_date\": \"2025-07-22\", \"end_location\": {\"name\": \"ITA01\", \"type\": \"DEAL\"}, \"start_location\": {\"name\": \"BEL01\", \"type\": \"TERM\"}, \"truck_number\": 1}": {
    "load": []
  },
  "{\"departure_date\": \"2025-07-25\", \"end_location\": {\"name\": \"ITA01\", \"type\": \"DEAL\"}, \"start_location\": {\"name\": \"BEL01\", \"type\": \"TERM\"}, \"truck_number\": 1}": {
    "load": []
  },
  "{\"departure_date\": \"2025-07-28\", \"end_location\": {\"name\": \"ITA01\", \"type\": \"DEAL\"}, \"start_location\": {\"name\": \"BEL01\", \"type\": \"TERM\"}, \"truck_number\": 1}": {
    "load": []
  },
  "{\"departure_date\": \"2025-07-29\", \"end_location\": {\"name\": \"ITA01\", \"type\": \"DEAL\"}, \"start_location\": {\"name\": \"BEL01\", \"type\": \"TERM\"}, \"truck_number\": 1}": {
    "load": []
  },
  "{\"departure_date\": \"2025-07-30\", \"end_location\": {\"name\": \"ITA01\", \"type\": \"DEAL\"}, \"start_location\": {\"name\": \"BEL01\", \"type\": \"TERM\"}, \"truck_number\": 1}": {
    "load": []
  },
  "{\"departure_date\": \"2025-08-04\", \"end_location\": {\"name\": \"ITA01\", \"type\": \"DEAL\"}, \"start_location\": {\"name\": \"BEL01\", \"type\": \"TERM\"}, \"truck_number\": 1}": {
    "load": []
  },
  "{\"departure_date\": \"2025-08-05\", \"end_location\": {\"name\": \"ITA01\", \"type\": \"DEAL\"}, \"start_location\": {\"name\": \"BEL01\", \"type\": \"TERM\"}, \"truck_number\": 1}": {
    "load": []
  },
  "{\"departure_date\": \"2025-08-08\", \"end_location\": {\"name\": \"ITA01\", \"type\": \"DEAL\"}, \"start_location\": {\"name\": \"BEL01\", \"type\": \"TERM\"}, \"truck_number\": 1}": {
    "load": []
  },
  "{\"departure_date\": \"2025-08-11\", \"end_location\": {\"name\": \"ITA01\", \"type\": \"DEAL\"}, \"start_location\": {\"name\": \"BEL01\", \"type\": \"TERM\"}, \"truck_number\": 1}": {
    "load": []
  },
  "{\"departure_date\": \"2025-08-13\", \"end_location\": {\"name\": \"ITA01\", \"type\": \"DEAL\"}, \"start_location\": {\"name\": \"BEL01\", \"type\": \"TERM\"}, \"truck_number\": 1}": {
    "load": []
  },
  "{\"departure_date\": \"2025-08-15\", \"end_location\": {\"name\": \"ITA01\", \"type\": \"DEAL\"}, \"start_location\": {\"name\": \"BEL01\", \"type\": \"TERM\"}, \"truck_number\": 1}": {
    "load": []
  },
  "{\"departure_date\": \"2025-08-18\", \"end_location\": {\"name\": \"ITA01\", \"type\": \"DEAL\"}, \"start_location\": {\"name\": \"BEL01\", \"type\": \"TERM\"}, \"truck_number\": 1}": {
    "load": []
  },
  "{\"departure_date\": \"2025-08-19\", \"end_location\": {\"name\": \"ITA01\", \"type\": \"DEAL\"}, \"start_location\": {\"name\": \"BEL01\", \"type\": \"TERM\"}, \"truck_number\": 1}": {
    "load": []
  },
  "{\"departure_date\": \"2025-08-20\", \"end_location\": {\"name\": \"ITA01\", \"type\": \"DEAL\"}, \"start_location\": {\"name\": \"BEL01\", \"type\": \"TERM\"}, \"truck_number\": 1}": {
    "load": []
  },
  "{\"departure_date\": \"2025-08-22\", \"end_location\": {\"name\": \"ITA01\", \"type\": \"DEAL\"}, \"start_location\": {\"name\": \"BEL01\", \"type\": \"TERM\"}, \"truck_number\": 1}": {
    "load": []
  },
  "{\"departure_date\": \"2025-08-25\", \"end_location\": {\"name\": \"ITA01\", \"type\": \"DEAL\"}, \"start_location\": {\"name\": \"BEL01\", \"type\": \"TERM\"}, \"truck_number\": 1}": {
    "load": []
  },
  "{\"departure_date\": \"2025-08-26\", \"end_location\": {\"name\": \"ITA01\", \"type\": \"DEAL\"}, \"start_location\": {\"name\": \"BEL01\", \"type\": \"TERM\"}, \"truck_number\": 1}": {
    "load": []
  },
  "{\"departure_date\": \"2025-08-27\", \"end_location\": {\"name\": \"ITA01\", \"type\": \"DEAL\"}, \"start_location\": {\"name\": \"BEL01\", \"type\": \"TERM\"}, \"truck_number\": 1}": {
    "load": []
  },
  "{\"departure_date\": \"2025-08-29\", \"end_location\": {\"name\": \"ITA01\", \"type\": \"DEAL\"}, \"start_location\": {\"name\": \"BEL01\", \"type\": \"TERM\"}, \"truck_number\": 1}": {
    "load": []
  }
}