{
  "{\"departure_date\": \"2025-06-02\", \"end_location\": {\"name\": \"BEL01\", \"type\": \"TERM\"}, \"start_location\": {\"name\": \"GER01\", \"type\": \"PLANT\"}, \"truck_number\": 1}": {
    "load": [
      1,
      3,
      4,
      9,
      12,
      15,
      18
    ]
  },
  "{\"departure_date\": \"2025-06-02\", \"end_location\": {\"name\": \"GER02\", \"type\": \"TERM\"}, \"start_location\": {\"name\": \"GER01\", \"type\": \"PLANT\"}, \"truck_number\": 1}": {
    "load": [
      2,
      6,
      7,
      10,
      11
    ]
  },
  "{\"departure_date\": \"2025-06-03\", \"end_location\": {\"name\": \"GER02\", \"type\": \"TERM\"}, \"start_location\": {\"name\": \"GER01\", \"type\": \"PLANT\"}, \"truck_number\": 1}": {
    "load": [
      32,
      36,
      26,
      28
    ]
  },
  "{\"departure_date\": \"2025-06-04\", \"end_location\": {\"name\": \"BEL01\", \"type\": \"TERM\"}, \"start_location\": {\"name\": \"GER01\", \"type\": \"PLANT\"}, \"truck_number\": 1}": {
    "load": [
      16,
      34,
      38,
      39,
      22,
      25,
      59,
      55,
      43
    ]
  },
  "{\"departure_date\": \"2025-06-04\", \"end_location\": {\"name\": \"GER02\", \"type\": \"TERM\"}, \"start_location\": {\"name\": \"GER01\", \"type\": \"PLANT\"}, \"truck_number\": 1}": {
    "load": [
      35,
      46,
      47,
      48,
      13,
      51,
      20,
      53
    ]
  },
  "{\"departure_date\": \"2025-06-05\", \"end_location\": {\"name\": \"GER02\", \"type\": \"TERM\"}, \"start_location\": {\"name\": \"GER01\", \"type\": \"PLANT\"}, \"truck_number\": 11}": {
    "load": [
      0,
      64,
      67,
      37,
      8,
      41,
      19,
      52,
      33,
      40,
      44,
      63,
      65,
      66,
      45
    ]
  },
  "{\"departure_date\": \"2025-06-05\", \"end_location\": {\"name\": \"FRA01\", \"type\": \"DEAL\"}, \"start_location\": {\"name\": \"BEL01\", \"type\": \"TERM\"}, \"truck_number\": 1}": {
    "load": [
      1,
      3,
      4,
      9,
      12
    ]
  },
  "{\"departure_date\": \"2025-06-05\", \"end_location\": {\"name\": \"BEL01\", \"type\": \"TERM\"}, \"start_location\": {\"name\": \"GER01\", \"type\": \"PLANT\"}, \"truck_number\": 1}": {
    "load": [
      17,
      21,
      58,
      27,
      29,
      30,
      71,
      74,
      78,
      60,
      75,
      61
    ]
  },
  "{\"departure_date\": \"2025-06-05\", \"end_location\": {\"name\": \"FRA01\", \"type\": \"DEAL\"}, \"start_location\": {\"name\": \"GER02\", \"type\": \"TERM\"}, \"truck_number\": 1}": {
    "load": [
      2,
      6,
      7,
      10,
      11
    ]
  },
  "{\"departure_date\": \"2025-06-05\", \"end_location\": {\"name\": \"GER02\", \"type\": \"TERM\"}, \"start_location\": {\"name\": \"GER01\", \"type\": \"PLANT\"}, \"truck_number\": 1}": {
    "load": [
      5,
      14,
      23,
      70,
      68,
      73,
      24
    ]
  },
  "{\"departure_date\": \"2025-06-06\", \"end_location\": {\"name\": \"BEL01\", \"type\": \"TERM\"}, \"start_location\": {\"name\": \"GER01\", \"type\": \"PLANT\"}, \"truck_number\": 11}": {
    "load": [
      54,
      93,
      31,
      42,
      49,
      50,
      83,
      85,
      88,
      95,
      99,
      87
    ]
  },
  "{\"departure_date\": \"2025-06-06\", \"end_location\": {\"name\": \"FRA01\", \"type\": \"DEAL\"}, \"start_location\": {\"name\": \"BEL01\", \"type\": \"TERM\"}, \"truck_number\": 1}": {
    "load": [
      15,
      18
    ]
  },
  "{\"departure_date\": \"2025-06-06\", \"end_location\": {\"name\": \"GER02\", \"type\": \"TERM\"}, \"start_location\": {\"name\": \"GER01\", \"type\": \"PLANT\"}, \"truck_number\": 1}": {
    "load": [
      76,
      79,
      69,
      80,
      96,
      77
    ]
  },
  "{\"departure_date\": \"2025-06-06\", \"end_location\": {\"name\": \"BEL01\", \"type\": \"TERM\"}, \"start_location\": {\"name\": \"GER01\", \"type\": \"PLANT\"}, \"truck_number\": 1}": {
    "load": [
      98,
      86,
      94
    ]
  },
  "{\"departure_date\": \"2025-06-06\", \"end_location\": {\"name\": \"FRA01\", \"type\": \"DEAL\"}, \"start_location\": {\"name\": \"GER02\", \"type\": \"TERM\"}, \"truck_number\": 1}": {
    "load": [
      32,
      36,
      26,
      28
    ]
  },
  "{\"departure_date\": \"2025-06-09\", \"end_location\": {\"name\": \"FRA01\", \"type\": \"DEAL\"}, \"start_location\": {\"name\": \"GER02\", \"type\": \"TERM\"}, \"truck_number\": 1}": {
    "load": [
      0,
      64,
      67,
      37,
      8,
      41,
      19,
      52
    ]
  },
  "{\"departure_date\": \"2025-06-09\", \"end_location\": {\"name\": \"FRA01\", \"type\": \"DEAL\"}, \"start_location\": {\"name\": \"BEL01\", \"type\": \"TERM\"}, \"truck_number\": 1}": {
    "load": [
      16,
      17,
      21,
      58,
      34,
      38,
      39,
      27,
      29,
      30,
      60,
      94
    ]
  },
  "{\"departure_date\": \"2025-06-09\", \"end_location\": {\"name\": \"BEL01\", \"type\": \"TERM\"}, \"start_location\": {\"name\": \"GER01\", \"type\": \"PLANT\"}, \"truck_number\": 1}": {
    "load": [
      100,
      108,
      117,
      89,
      102,
      103,
      112,
      62
    ]
  },
  "{\"departure_date\": \"2025-06-09\", \"end_location\": {\"name\": \"FRA01\", \"type\": \"DEAL\"}, \"start_location\": {\"name\": \"BEL01\", \"type\": \"TERM\"}, \"truck_number\": 2}": {
    "load": [
      98,
      71,
      74,
      78,
      22,
      86,
      25,
      75,
      55,
      61
    ]
  },
  "{\"departure_date\": \"2025-06-09\", \"end_location\": {\"name\": \"FRA01\", \"type\": \"DEAL\"}, \"start_location\": {\"name\": \"GER02\", \"type\": \"TERM\"}, \"truck_number\": 2}": {
    "load": [
      69,
      80
    ]
  },
  "{\"departure_date\": \"2025-06-09\", \"end_location\": {\"name\": \"GER02\", \"type\": \"TERM\"}, \"start_location\": {\"name\": \"GER01\", \"type\": \"PLANT\"}, \"truck_number\": 1}": {
    "load": [
      97,
      101,
      107,
      110,
      113,
      104,
      111
    ]
  },
  "{\"departure_date\": \"2025-06-10\", \"end_location\": {\"name\": \"FRA01\", \"type\": \"DEAL\"}, \"start_location\": {\"name\": \"BEL01\", \"type\": \"TERM\"}, \"truck_number\": 1}": {
    "load": [
      54,
      93,
      31,
      49,
      50,
      42,
      83
    ]
  },
  "{\"departure_date\": \"2025-06-10\", \"end_location\": {\"name\": \"BEL01\", \"type\": \"TERM\"}, \"start_location\": {\"name\": \"GER01\", \"type\": \"PLANT\"}, \"truck_number\": 1}": {
    "load": [
      130,
      129,
      134,
      128,
      136,
      105,
      126,
      132,
      139
    ]
  },
  "{\"departure_date\": \"2025-06-10\", \"end_location\": {\"name\": \"GER02\", \"type\": \"TERM\"}, \"start_location\": {\"name\": \"GER01\", \"type\": \"PLANT\"}, \"truck_number\": 11}": {
    "load": [
      72,
      115,
      116,
      84,
      118,
      119,
      90,
      123,
      133,
      109,
      82,
      122,
      125,
      135,
      137
    ]
  },
  "{\"departure_date\": \"2025-06-10\", \"end_location\": {\"name\": \"GER02\", \"type\": \"TERM\"}, \"start_location\": {\"name\": \"GER01\", \"type\": \"PLANT\"}, \"truck_number\": 1}": {
    "load": [
      131,
      106,
      138
    ]
  },
  "{\"departure_date\": \"2025-06-11\", \"end_location\": {\"name\": \"FRA01\", \"type\": \"DEAL\"}, \"start_location\": {\"name\": \"GER02\", \"type\": \"TERM\"}, \"truck_number\": 1}": {
    "load": [
      5,
      14,
      23,
      33,
      40
    ]
  },
  "{\"departure_date\": \"2025-06-11\", \"end_location\": {\"name\": \"BEL01\", \"type\": \"TERM\"}, \"start_location\": {\"name\": \"GER01\", \"type\": \"PLANT\"}, \"truck_number\": 11}": {
    "load": [
      146,
      157,
      140,
      143,
      124,
      81,
      120,
      57,
      56,
      92,
      152,
      153
    ]
  },
  "{\"departure_date\": \"2025-06-11\", \"end_location\": {\"name\": \"FRA01\", \"type\": \"DEAL\"}, \"start_location\": {\"name\": \"BEL01\", \"type\": \"TERM\"}, \"truck_number\": 1}": {
    "load": [
      85,
      88,
      95,
      99,
      87,
      59,
      43
    ]
  },
  "{\"departure_date\": \"2025-06-11\", \"end_location\": {\"name\": \"FRA01\", \"type\": \"DEAL\"}, \"start_location\": {\"name\": \"GER02\", \"type\": \"TERM\"}, \"truck_number\": 2}": {
    "load": [
      35,
      70
    ]
  },
  "{\"departure_date\": \"2025-06-11\", \"end_location\": {\"name\": \"GER02\", \"type\": \"TERM\"}, \"start_location\": {\"name\": \"GER01\", \"type\": \"PLANT\"}, \"truck_number\": 1}": {
    "load": [
      155,
      156,
      158,
      159,
      147,
      148
    ]
  },
  "{\"departure_date\": \"2025-06-12\", \"end_location\": {\"name\": \"FRA01\", \"type\": \"DEAL\"}, \"start_location\": {\"name\": \"GER02\", \"type\": \"TERM\"}, \"truck_number\": 1}": {
    "load": [
      44,
      63,
      65,
      66,
      76,
      79,
      46
    ]
  },
  "{\"departure_date\": \"2025-06-12\", \"end_location\": {\"name\": \"FRA01\", \"type\": \"DEAL\"}, \"start_location\": {\"name\": \"BEL01\", \"type\": \"TERM\"}, \"truck_number\": 1}": {
    "load": [
      100,
      108,
      117,
      89,
      102,
      103,
      112,
      62
    ]
  },
  "{\"departure_date\": \"2025-06-12\", \"end_location\": {\"name\": \"GER02\", \"type\": \"TERM\"}, \"start_location\": {\"name\": \"GER01\", \"type\": \"PLANT\"}, \"truck_number\": 11}": {
    "load": [
      172,
      170,
      175,
      166,
      141,
      142,
      160,
      162,
      168,
      144,
      150,
      151,
      171,
      173,
      145
    ]
  },
  "{\"departure_date\": \"2025-06-12\", \"end_location\": {\"name\": \"BEL01\", \"type\": \"TERM\"}, \"start_location\": {\"name\": \"GER01\", \"type\": \"PLANT\"}, \"truck_number\": 1}": {
    "load": [
      161,
      163,
      169,
      149,
      164,
      167
    ]
  },
  "{\"departure_date\": \"2025-06-12\", \"end_location\": {\"name\": \"GER02\", \"type\": \"TERM\"}, \"start_location\": {\"name\": \"GER01\", \"type\": \"PLANT\"}, \"truck_number\": 1}": {
    "load": [
      165
    ]
  },
  "{\"departure_date\": \"2025-06-13\", \"end_location\": {\"name\": \"FRA01\", \"type\": \"DEAL\"}, \"start_location\": {\"name\": \"BEL01\", \"type\": \"TERM\"}, \"truck_number\": 1}": {
    "load": [
      130,
      129,
      134,
      128,
      136,
      105,
      126,
      132,
      139
    ]
  },
  "{\"departure_date\": \"2025-06-13\", \"end_location\": {\"name\": \"FRA01\", \"type\": \"DEAL\"}, \"start_location\": {\"name\": \"GER02\", \"type\": \"TERM\"}, \"truck_number\": 1}": {
    "load": [
      47,
      48,
      68,
      73,
      13,
      51,
      20,
      53,
      24,
      96,
      45
    ]
  },
  "{\"departure_date\": \"2025-06-13\", \"end_location\": {\"name\": \"BEL01\", \"type\": \"TERM\"}, \"start_location\": {\"name\": \"GER01\", \"type\": \"PLANT\"}, \"truck_number\": 11}": {
    "load": [
      176,
      177,
      127,
      194,
      182,
      187,
      188,
      114,
      121,
      154,
      91,
      179
    ]
  },
  "{\"departure_date\": \"2025-06-13\", \"end_location\": {\"name\": \"BEL01\", \"type\": \"TERM\"}, \"start_location\": {\"name\": \"GER01\", \"type\": \"PLANT\"}, \"truck_number\": 1}": {
    "load": [
      192,
      193,
      198,
      181,
      191,
      184
    ]
  },
  "{\"departure_date\": \"2025-06-13\", \"end_location\": {\"name\": \"GER02\", \"type\": \"TERM\"}, \"start_location\": {\"name\": \"GER01\", \"type\": \"PLANT\"}, \"truck_number\": 1}": {
    "load": [
      199,
      185
    ]
  },
  "{\"departure_date\": \"2025-06-16\", \"end_location\": {\"name\": \"FRA01\", \"type\": \"DEAL\"}, \"start_location\": {\"name\": \"BEL01\", \"type\": \"TERM\"}, \"truck_number\": 1}": {
    "load": [
      146,
      157,
      140,
      143,
      124
    ]
  },
  "{\"departure_date\": \"2025-06-16\", \"end_location\": {\"name\": \"FRA01\", \"type\": \"DEAL\"}, \"start_location\": {\"name\": \"GER02\", \"type\": \"TERM\"}, \"truck_number\": 1}": {
    "load": [
      77,
      172,
      72,
      115,
      116,
      84
    ]
  },
  "{\"departure_date\": \"2025-06-16\", \"end_location\": {\"name\": \"FRA01\", \"type\": \"DEAL\"}, \"start_location\": {\"name\": \"BEL01\", \"type\": \"TERM\"}, \"truck_number\": 2}": {
    "load": [
      57,
      56,
      92,
      152,
      164
    ]
  },
  "{\"departure_date\": \"2025-06-16\", \"end_location\": {\"name\": \"BEL01\", \"type\": \"TERM\"}, \"start_location\": {\"name\": \"GER01\", \"type\": \"PLANT\"}, \"truck_number\": 1}": {
    "load": [
      200,
      202,
      210,
      209,
      197,
      203,
      211,
      212,
      183,
      213,
      218,
      190,
      217,
      206
    ]
  },
  "{\"departure_date\": \"2025-06-17\", \"end_location\": {\"name\": \"FRA01\", \"type\": \"DEAL\"}, \"start_location\": {\"name\": \"BEL01\", \"type\": \"TERM\"}, \"truck_number\": 1}": {
    "load": [
      81,
      120,
      176,
      177,
      153,
      127,
      194,
      182
    ]
  },
  "{\"departure_date\": \"2025-06-17\", \"end_location\": {\"name\": \"GER02\", \"type\": \"TERM\"}, \"start_location\": {\"name\": \"GER01\", \"type\": \"PLANT\"}, \"truck_number\": 11}": {
    "load": [
      195,
      196,
      208,
      178,
      224,
      228,
      201,
      205,
      174,
      227,
      215,
      189,
      230,
      204,
      207
    ]
  },
  "{\"departure_date\": \"2025-06-17\", \"end_location\": {\"name\": \"FRA01\", \"type\": \"DEAL\"}, \"start_location\": {\"name\": \"BEL01\", \"type\": \"TERM\"}, \"truck_number\": 2}": {
    "load": [
      167
    ]
  },
  "{\"departure_date\": \"2025-06-18\", \"end_location\": {\"name\": \"FRA01\", \"type\": \"DEAL\"}, \"start_location\": {\"name\": \"GER02\", \"type\": \"TERM\"}, \"truck_number\": 1}": {
    "load": [
      118,
      119,
      90,
      123,
      133,
      170,
      109,
      175
    ]
  },
  "{\"departure_date\": \"2025-06-18\", \"end_location\": {\"name\": \"FRA01\", \"type\": \"DEAL\"}, \"start_location\": {\"name\": \"BEL01\", \"type\": \"TERM\"}, \"truck_number\": 1}": {
    "load": [
      187,
      188,
      192
    ]
  },
  "{\"departure_date\": \"2025-06-18\", \"end_location\": {\"name\": \"FRA01\", \"type\": \"DEAL\"}, \"start_location\": {\"name\": \"GER02\", \"type\": \"TERM\"}, \"truck_number\": 2}": {
    "load": [
      97,
      101,
      166,
      135,
      137,
      165,
      199,
      171
    ]
  },
  "{\"departure_date\": \"2025-06-18\", \"end_location\": {\"name\": \"BEL01\", \"type\": \"TERM\"}, \"start_location\": {\"name\": \"GER01\", \"type\": \"PLANT\"}, \"truck_number\": 11}": {
    "load": [
      236,
      243,
      180,
      214,
      251,
      186,
      255,
      225,
      226,
      231,
      223,
      247
    ]
  },
  "{\"departure_date\": \"2025-06-18\", \"end_location\": {\"name\": \"GER02\", \"type\": \"TERM\"}, \"start_location\": {\"name\": \"GER01\", \"type\": \"PLANT\"}, \"truck_number\": 1}": {
    "load": [
      221,
      222,
      229,
      232,
      234,
      238,
      240,
      241,
      242
    ]
  },
  "{\"departure_date\": \"2025-06-19\", \"end_location\": {\"name\": \"FRA01\", \"type\": \"DEAL\"}, \"start_location\": {\"name\": \"GER02\", \"type\": \"TERM\"}, \"truck_number\": 1}": {
    "load": [
      82,
      122,
      125,
      107,
      141,
      110,
      142,
      113,
      160
    ]
  },
  "{\"departure_date\": \"2025-06-19\", \"end_location\": {\"name\": \"FRA01\", \"type\": \"DEAL\"}, \"start_location\": {\"name\": \"BEL01\", \"type\": \"TERM\"}, \"truck_number\": 1}": {
    "load": [
      114,
      121,
      154,
      91,
      193,
      198,
      200,
      202,
      181,
      191
    ]
  },
  "{\"departure_date\": \"2025-06-19\", \"end_location\": {\"name\": \"FRA01\", \"type\": \"DEAL\"}, \"start_location\": {\"name\": \"BEL01\", \"type\": \"TERM\"}, \"truck_number\": 2}": {
    "load": [
      149,
      184,
      209,
      197,
      203,
      211,
      212,
      183,
      213,
      218
    ]
  },
  "{\"departure_date\": \"2025-06-19\", \"end_location\": {\"name\": \"FRA01\", \"type\": \"DEAL\"}, \"start_location\": {\"name\": \"GER02\", \"type\": \"TERM\"}, \"truck_number\": 2}": {
    "load": [
      173,
      185,
      159,
      147,
      148
    ]
  },
  "{\"departure_date\": \"2025-06-19\", \"end_location\": {\"name\": \"BEL01\", \"type\": \"TERM\"}, \"start_location\": {\"name\": \"GER01\", \"type\": \"PLANT\"}, \"truck_number\": 1}": {
    "load": [
      219,
      233,
      250,
      235,
      237,
      239,
      246,
      249,
      245,
      252,
      253,
      277
    ]
  },
  "{\"departure_date\": \"2025-06-20\", \"end_location\": {\"name\": \"FRA01\", \"type\": \"DEAL\"}, \"start_location\": {\"name\": \"GER02\", \"type\": \"TERM\"}, \"truck_number\": 1}": {
    "load": [
      162,
      131,
      104,
      168,
      111,
      144,
      150,
      151,
      106
    ]
  },
  "{\"departure_date\": \"2025-06-20\", \"end_location\": {\"name\": \"FRA01\", \"type\": \"DEAL\"}, \"start_location\": {\"name\": \"BEL01\", \"type\": \"TERM\"}, \"truck_number\": 1}": {
    "load": [
      161,
      163,
      169,
      210,
      179,
      190,
      217
    ]
  },
  "{\"departure_date\": \"2025-06-20\", \"end_location\": {\"name\": \"GER02\", \"type\": \"TERM\"}, \"start_location\": {\"name\": \"GER01\", \"type\": \"PLANT\"}, \"truck_number\": 1}": {
    "load": [
      256,
      258,
      292,
      262,
      291,
      261,
      264,
      282,
      269,
      270,
      273,
      280,
      299
    ]
  },
  "{\"departure_date\": \"2025-06-20\", \"end_location\": {\"name\": \"BEL01\", \"type\": \"TERM\"}, \"start_location\": {\"name\": \"GER01\", \"type\": \"PLANT\"}, \"truck_number\": 1}": {
    "load": [
      259,
      244,
      278,
      279,
      216,
      220,
      254,
      289
    ]
  },
  "{\"departure_date\": \"2025-06-20\", \"end_location\": {\"name\": \"FRA01\", \"type\": \"DEAL\"}, \"start_location\": {\"name\": \"BEL01\", \"type\": \"TERM\"}, \"truck_number\": 2}": {
    "load": [
      206
    ]
  },
  "{\"departure_date\": \"2025-06-23\", \"end_location\": {\"name\": \"FRA01\", \"type\": \"DEAL\"}, \"start_location\": {\"name\": \"GER02\", \"type\": \"TERM\"}, \"truck_number\": 1}": {
    "load": [
      138,
      155,
      156,
      158,
      195,
      196,
      208,
      145,
      178
    ]
  },
  "{\"departure_date\": \"2025-06-23\", \"end_location\": {\"name\": \"FRA01\", \"type\": \"DEAL\"}, \"start_location\": {\"name\": \"BEL01\", \"type\": \"TERM\"}, \"truck_number\": 1}": {
    "load": [
      236,
      243,
      180,
      214,
      251,
      186,
      255,
      259,
      244
    ]
  },
  "{\"departure_date\": \"2025-06-23\", \"end_location\": {\"name\": \"BEL01\", \"type\": \"TERM\"}, \"start_location\": {\"name\": \"GER01\", \"type\": \"PLANT\"}, \"truck_number\": 1}": {
    "load": [
      295,
      263,
      266,
      271,
      272,
      283,
      260,
      265,
      267,
      275,
      284,
      308,
      294,
      296,
      297,
      301,
      303,
      281,
      307,
      314,
      319
    ]
  },
  "{\"departure_date\": \"2025-06-23\", \"end_location\": {\"name\": \"FRA01\", \"type\": \"DEAL\"}, \"start_location\": {\"name\": \"BEL01\", \"type\": \"TERM\"}, \"truck_number\": 2}": {
    "load": [
      225,
      226,
      231,
      223,
      245,
      252,
      289,
      277
    ]
  },
  "{\"departure_date\": \"2025-06-23\", \"end_location\": {\"name\": \"GER02\", \"type\": \"TERM\"}, \"start_location\": {\"name\": \"GER01\", \"type\": \"PLANT\"}, \"truck_number\": 1}": {
    "load": [
      286,
      306,
      310,
      302,
      309,
      316,
      311
    ]
  },
  "{\"departure_date\": \"2025-06-23\", \"end_location\": {\"name\": \"FRA01\", \"type\": \"DEAL\"}, \"start_location\": {\"name\": \"GER02\", \"type\": \"TERM\"}, \"truck_number\": 2}": {
    "load": [
      269
    ]
  },
  "{\"departure_date\": \"2025-06-24\", \"end_location\": {\"name\": \"FRA01\", \"type\": \"DEAL\"}, \"start_location\": {\"name\": \"GER02\", \"type\": \"TERM\"}, \"truck_number\": 1}": {
    "load": [
      224,
      256,
      258,
      228,
      292,
      262,
      201,
      205,
      174,
      227,
      215
    ]
  },
  "{\"departure_date\": \"2025-06-24\", \"end_location\": {\"name\": \"BEL01\", \"type\": \"TERM\"}, \"start_location\": {\"name\": \"GER01\", \"type\": \"PLANT\"}, \"truck_number\": 1}": {
    "load": [
      320,
      328,
      337,
      326,
      339,
      323
    ]
  },
  "{\"departure_date\": \"2025-06-24\", \"end_location\": {\"name\": \"GER02\", \"type\": \"TERM\"}, \"start_location\": {\"name\": \"GER01\", \"type\": \"PLANT\"}, \"truck_number\": 11}": {
    "load": [
      257,
      300,
      332,
      288,
      321,
      290,
      293,
      268,
      334,
      304,
      317,
      287,
      285,
      298,
      335
    ]
  },
  "{\"departure_date\": \"2025-06-24\", \"end_location\": {\"name\": \"GER02\", \"type\": \"TERM\"}, \"start_location\": {\"name\": \"GER01\", \"type\": \"PLANT\"}, \"truck_number\": 1}": {
    "load": [
      325,
      324,
      330,
      331,
      333,
      336,
      338
    ]
  },
  "{\"departure_date\": \"2025-06-25\", \"end_location\": {\"name\": \"FRA01\", \"type\": \"DEAL\"}, \"start_location\": {\"name\": \"BEL01\", \"type\": \"TERM\"}, \"truck_number\": 1}": {
    "load": [
      247,
      278,
      279,
      216,
      219,
      220,
      254,
      233,
      250,
      235
    ]
  },
  "{\"departure_date\": \"2025-06-25\", \"end_location\": {\"name\": \"FRA01\", \"type\": \"DEAL\"}, \"start_location\": {\"name\": \"GER02\", \"type\": \"TERM\"}, \"truck_number\": 1}": {
    "load": [
      189,
      291,
      261,
      230,
      264,
      204,
      207
    ]
  },
  "{\"departure_date\": \"2025-06-25\", \"end_location\": {\"name\": \"BEL01\", \"type\": \"TERM\"}, \"start_location\": {\"name\": \"GER01\", \"type\": \"PLANT\"}, \"truck_number\": 11}": {
    "load": [
      340,
      344,
      354,
      358,
      274,
      276,
      248,
      356,
      359,
      348,
      345,
      341
    ]
  },
  "{\"departure_date\": \"2025-06-25\", \"end_location\": {\"name\": \"FRA01\", \"type\": \"DEAL\"}, \"start_location\": {\"name\": \"BEL01\", \"type\": \"TERM\"}, \"truck_number\": 2}": {
    "load": [
      253
    ]
  },
  "{\"departure_date\": \"2025-06-25\", \"end_location\": {\"name\": \"GER02\", \"type\": \"TERM\"}, \"start_location\": {\"name\": \"GER01\", \"type\": \"PLANT\"}, \"truck_number\": 1}": {
    "load": [
      342
    ]
  },
  "{\"departure_date\": \"2025-06-26\", \"end_location\": {\"name\": \"FRA01\", \"type\": \"DEAL\"}, \"start_location\": {\"name\": \"BEL01\", \"type\": \"TERM\"}, \"truck_number\": 1}": {
    "load": [
      295,
      263,
      266,
      271,
      272
    ]
  },
  "{\"departure_date\": \"2025-06-26\", \"end_location\": {\"name\": \"FRA01\", \"type\": \"DEAL\"}, \"start_location\": {\"name\": \"BEL01\", \"type\": \"TERM\"}, \"truck_number\": 2}": {
    "load": [
      265,
      267,
      275,
      284,
      308
    ]
  },
  "{\"departure_date\": \"2025-06-26\", \"end_location\": {\"name\": \"FRA01\", \"type\": \"DEAL\"}, \"start_location\": {\"name\": \"GER02\", \"type\": \"TERM\"}, \"truck_number\": 1}": {
    "load": [
      286,
      306,
      310,
      282,
      270,
      273,
      280,
      299,
      221,
      222
    ]
  },
  "{\"departure_date\": \"2025-06-26\", \"end_location\": {\"name\": \"GER02\", \"type\": \"TERM\"}, \"start_location\": {\"name\": \"GER01\", \"type\": \"PLANT\"}, \"truck_number\": 11}": {
    "load": [
      367,
      374,
      361,
      357,
      366,
      305,
      370,
      350,
      322,
      327,
      329,
      363,
      368,
      376,
      373
    ]
  },
  "{\"departure_date\": \"2025-06-26\", \"end_location\": {\"name\": \"GER02\", \"type\": \"TERM\"}, \"start_location\": {\"name\": \"GER01\", \"type\": \"PLANT\"}, \"truck_number\": 1}": {
    "load": [
      362,
      364,
      369
    ]
  },
  "{\"departure_date\": \"2025-06-27\", \"end_location\": {\"name\": \"FRA01\", \"type\": \"DEAL\"}, \"start_location\": {\"name\": \"BEL01\", \"type\": \"TERM\"}, \"truck_number\": 1}": {
    "load": [
      283,
      260,
      237,
      239,
      246,
      249,
      320,
      303,
      339,
      281
    ]
  },
  "{\"departure_date\": \"2025-06-27\", \"end_location\": {\"name\": \"FRA01\", \"type\": \"DEAL\"}, \"start_location\": {\"name\": \"BEL01\", \"type\": \"TERM\"}, \"truck_number\": 2}": {
    "load": [
      328,
      337,
      294,
      326,
      296,
      297,
      301,
      323
    ]
  },
  "{\"departure_date\": \"2025-06-27\", \"end_location\": {\"name\": \"FRA01\", \"type\": \"DEAL\"}, \"start_location\": {\"name\": \"GER02\", \"type\": \"TERM\"}, \"truck_number\": 1}": {
    "load": [
      229,
      232,
      234,
      238,
      240,
      241,
      242,
      325,
      302,
      309
    ]
  },
  "{\"departure_date\": \"2025-06-27\", \"end_location\": {\"name\": \"BEL01\", \"type\": \"TERM\"}, \"start_location\": {\"name\": \"GER01\", \"type\": \"PLANT\"}, \"truck_number\": 11}": {
    "load": [
      388,
      380,
      347,
      351,
      389,
      394,
      312,
      313,
      378,
      315,
      349,
      383
    ]
  },
  "{\"departure_date\": \"2025-06-27\", \"end_location\": {\"name\": \"BEL01\", \"type\": \"TERM\"}, \"start_location\": {\"name\": \"GER01\", \"type\": \"PLANT\"}, \"truck_number\": 1}": {
    "load": [
      352,
      353,
      371,
      318,
      398,
      381,
      382
    ]
  },
  "{\"departure_date\": \"2025-06-27\", \"end_location\": {\"name\": \"GER02\", \"type\": \"TERM\"}, \"start_location\": {\"name\": \"GER01\", \"type\": \"PLANT\"}, \"truck_number\": 1}": {
    "load": [
      396
    ]
  },
  "{\"departure_date\": \"2025-06-30\", \"end_location\": {\"name\": \"FRA01\", \"type\": \"DEAL\"}, \"start_location\": {\"name\": \"BEL01\", \"type\": \"TERM\"}, \"truck_number\": 1}": {
    "load": [
      340,
      344,
      354,
      358,
      274,
      276,
      248,
      356,
      359,
      348,
      345,
      341
    ]
  },
  "{\"departure_date\": \"2025-06-30\", \"end_location\": {\"name\": \"FRA01\", \"type\": \"DEAL\"}, \"start_location\": {\"name\": \"GER02\", \"type\": \"TERM\"}, \"truck_number\": 1}": {
    "load": [
      257,
      300,
      332,
      367,
      374,
      288,
      321,
      290,
      293,
      361,
      268
    ]
  },
  "{\"departure_date\": \"2025-06-30\", \"end_location\": {\"name\": \"FRA01\", \"type\": \"DEAL\"}, \"start_location\": {\"name\": \"BEL01\", \"type\": \"TERM\"}, \"truck_number\": 2}": {
    "load": [
      352,
      353,
      371
    ]
  },
  "{\"departure_date\": \"2025-06-30\", \"end_location\": {\"name\": \"BEL01\", \"type\": \"TERM\"}, \"start_location\": {\"name\": \"GER01\", \"type\": \"PLANT\"}, \"truck_number\": 1}": {
    "load": [
      403,
      387,
      392,
      377,
      391,
      393,
      401,
      408,
      412,
      417,
      355,
      411,
      384,
      399,
      400,
      406,
      414,
      415,
      407
    ]
  },
  "{\"departure_date\": \"2025-06-30\", \"end_location\": {\"name\": \"GER02\", \"type\": \"TERM\"}, \"start_location\": {\"name\": \"GER01\", \"type\": \"PLANT\"}, \"truck_number\": 1}": {
    "load": [
      385,
      419,
      409,
      410,
      413
    ]
  },
  "{\"departure_date\": \"2025-07-01\", \"end_location\": {\"name\": \"FRA01\", \"type\": \"DEAL\"}, \"start_location\": {\"name\": \"BEL01\", \"type\": \"TERM\"}, \"truck_number\": 1}": {
    "load": [
      388,
      380,
      347,
      351,
      389
    ]
  },
  "{\"departure_date\": \"2025-07-01\", \"end_location\": {\"name\": \"FRA01\", \"type\": \"DEAL\"}, \"start_location\": {\"name\": \"GER02\", \"type\": \"TERM\"}, \"truck_number\": 1}": {
    "load": [
      334,
      304,
      317,
      287,
      285,
      357,
      298,
      366,
      335
    ]
  },
  "{\"departure_date\": \"2025-07-01\", \"end_location\": {\"name\": \"BEL01\", \"type\": \"TERM\"}, \"start_location\": {\"name\": \"GER01\", \"type\": \"PLANT\"}, \"truck_number\": 1}": {
    "load": [
      433,
      439,
      420,
      424,
      437,
      434
    ]
  },
  "{\"departure_date\": \"2025-07-01\", \"end_location\": {\"name\": \"GER02\", \"type\": \"TERM\"}, \"start_location\": {\"name\": \"GER01\", \"type\": \"PLANT\"}, \"truck_number\": 11}": {
    "load": [
      386,
      421,
      423,
      395,
      375,
      343,
      422,
      390,
      360,
      426,
      365,
      397,
      402,
      425,
      427
    ]
  },
  "{\"departure_date\": \"2025-07-02\", \"end_location\": {\"name\": \"FRA01\", \"type\": \"DEAL\"}, \"start_location\": {\"name\": \"BEL01\", \"type\": \"TERM\"}, \"truck_number\": 1}": {
    "load": [
      394,
      312,
      313,
      378,
      315,
      349,
      318,
      398,
      381,
      382,
      383
    ]
  },
  "{\"departure_date\": \"2025-07-02\", \"end_location\": {\"name\": \"FRA01\", \"type\": \"DEAL\"}, \"start_location\": {\"name\": \"GER02\", \"type\": \"TERM\"}, \"truck_number\": 1}": {
    "load": [
      305,
      370
    ]
  },
  "{\"departure_date\": \"2025-07-02\", \"end_location\": {\"name\": \"BEL01\", \"type\": \"TERM\"}, \"start_location\": {\"name\": \"GER01\", \"type\": \"PLANT\"}, \"truck_number\": 11}": {
    "load": [
      448,
      438,
      459,
      428,
      435,
      372,
      404,
      405,
      436,
      379,
      346,
      442
    ]
  },
  "{\"departure_date\": \"2025-07-02\", \"end_location\": {\"name\": \"BEL01\", \"type\": \"TERM\"}, \"start_location\": {\"name\": \"GER01\", \"type\": \"PLANT\"}, \"truck_number\": 1}": {
    "load": [
      451,
      449,
      418,
      455
    ]
  },
  "{\"departure_date\": \"2025-07-02\", \"end_location\": {\"name\": \"GER02\", \"type\": \"TERM\"}, \"start_location\": {\"name\": \"GER01\", \"type\": \"PLANT\"}, \"truck_number\": 1}": {
    "load": [
      416,
      430
    ]
  },
  "{\"departure_date\": \"2025-07-03\", \"end_location\": {\"name\": \"FRA01\", \"type\": \"DEAL\"}, \"start_location\": {\"name\": \"GER02\", \"type\": \"TERM\"}, \"truck_number\": 1}": {
    "load": [
      350,
      322,
      327,
      329,
      363,
      396,
      368,
      316,
      342
    ]
  },
  "{\"departure_date\": \"2025-07-03\", \"end_location\": {\"name\": \"FRA01\", \"type\": \"DEAL\"}, \"start_location\": {\"name\": \"BEL01\", \"type\": \"TERM\"}, \"truck_number\": 1}": {
    "load": [
      403,
      387,
      392,
      307,
      377,
      314,
      319,
      391
    ]
  },
  "{\"departure_date\": \"2025-07-03\", \"end_location\": {\"name\": \"FRA01\", \"type\": \"DEAL\"}, \"start_location\": {\"name\": \"BEL01\", \"type\": \"TERM\"}, \"truck_number\": 2}": {
    "load": [
      417,
      355
    ]
  },
  "{\"departure_date\": \"2025-07-03\", \"end_location\": {\"name\": \"BEL01\", \"type\": \"TERM\"}, \"start_location\": {\"name\": \"GER01\", \"type\": \"PLANT\"}, \"truck_number\": 1}": {
    "load": [
      464,
      479,
      471,
      461,
      452,
      462,
      478
    ]
  },
  "{\"departure_date\": \"2025-07-03\", \"end_location\": {\"name\": \"GER02\", \"type\": \"TERM\"}, \"start_location\": {\"name\": \"GER01\", \"type\": \"PLANT\"}, \"truck_number\": 11}": {
    "load": [
      450,
      469,
      441,
      453,
      454,
      460,
      440,
      457,
      431,
      463,
      467,
      472,
      475,
      468,
      456
    ]
  },
  "{\"departure_date\": \"2025-07-03\", \"end_location\": {\"name\": \"GER02\", \"type\": \"TERM\"}, \"start_location\": {\"name\": \"GER01\", \"type\": \"PLANT\"}, \"truck_number\": 1}": {
    "load": [
      466
    ]
  },
  "{\"departure_date\": \"2025-07-04\", \"end_location\": {\"name\": \"FRA01\", \"type\": \"DEAL\"}, \"start_location\": {\"name\": \"BEL01\", \"type\": \"TERM\"}, \"truck_number\": 1}": {
    "load": [
      433,
      393,
      401,
      408,
      412,
      411,
      384,
      399,
      400
    ]
  },
  "{\"departure_date\": \"2025-07-04\", \"end_location\": {\"name\": \"FRA01\", \"type\": \"DEAL\"}, \"start_location\": {\"name\": \"GER02\", \"type\": \"TERM\"}, \"truck_number\": 1}": {
    "load": [
      376,
      385,
      419,
      324,
      330,
      331,
      362,
      333,
      364,
      336
    ]
  },
  "{\"departure_date\": \"2025-07-04\", \"end_location\": {\"name\": \"BEL01\", \"type\": \"TERM\"}, \"start_location\": {\"name\": \"GER01\", \"type\": \"PLANT\"}, \"truck_number\": 11}": {
    "load": [
      458,
      473,
      494,
      474,
      476,
      445,
      488,
      429,
      493,
      432,
      443,
      495
    ]
  },
  "{\"departure_date\": \"2025-07-04\", \"end_location\": {\"name\": \"BEL01\", \"type\": \"TERM\"}, \"start_location\": {\"name\": \"GER01\", \"type\": \"PLANT\"}, \"truck_number\": 1}": {
    "load": [
      499,
      497,
      481
    ]
  },
  "{\"departure_date\": \"2025-07-04\", \"end_location\": {\"name\": \"GER02\", \"type\": \"TERM\"}, \"start_location\": {\"name\": \"GER01\", \"type\": \"PLANT\"}, \"truck_number\": 1}": {
    "load": [
      486,
      487,
      482,
      484
    ]
  },
  "{\"departure_date\": \"2025-07-04\", \"end_location\": {\"name\": \"FRA01\", \"type\": \"DEAL\"}, \"start_location\": {\"name\": \"BEL01\", \"type\": \"TERM\"}, \"truck_number\": 2}": {
    "load": [
      420,
      424,
      437,
      434
    ]
  },
  "{\"departure_date\": \"2025-07-07\", \"end_location\": {\"name\": \"FRA01\", \"type\": \"DEAL\"}, \"start_location\": {\"name\": \"BEL01\", \"type\": \"TERM\"}, \"truck_number\": 1}": {
    "load": [
      448,
      438,
      451,
      459
    ]
  },
  "{\"departure_date\": \"2025-07-07\", \"end_location\": {\"name\": \"FRA01\", \"type\": \"DEAL\"}, \"start_location\": {\"name\": \"GER02\", \"type\": \"TERM\"}, \"truck_number\": 1}": {
    "load": [
      369,
      338,
      311,
      450,
      386,
      421,
      423,
      395,
      373
    ]
  },
  "{\"departure_date\": \"2025-07-07\", \"end_location\": {\"name\": \"FRA01\", \"type\": \"DEAL\"}, \"start_location\": {\"name\": \"BEL01\", \"type\": \"TERM\"}, \"truck_number\": 2}": {
    "load": [
      372,
      404,
      405,
      436
    ]
  },
  "{\"departure_date\": \"2025-07-07\", \"end_location\": {\"name\": \"GER02\", \"type\": \"TERM\"}, \"start_location\": {\"name\": \"GER01\", \"type\": \"PLANT\"}, \"truck_number\": 1}": {
    "load": [
      515,
      514,
      517
    ]
  },
  "{\"departure_date\": \"2025-07-07\", \"end_location\": {\"name\": \"BEL01\", \"type\": \"TERM\"}, \"start_location\": {\"name\": \"GER01\", \"type\": \"PLANT\"}, \"truck_number\": 1}": {
    "load": [
      500,
      502,
      509,
      513,
      480,
      512,
      485,
      490,
      503,
      516,
      507,
      508,
      505,
      506,
      511
    ]
  },
  "{\"departure_date\": \"2025-07-08\", \"end_location\": {\"name\": \"FRA01\", \"type\": \"DEAL\"}, \"start_location\": {\"name\": \"GER02\", \"type\": \"TERM\"}, \"truck_number\": 1}": {
    "load": [
      375,
      343,
      422,
      390,
      360,
      426,
      365,
      397,
      402,
      469,
      441,
      453
    ]
  },
  "{\"departure_date\": \"2025-07-08\", \"end_location\": {\"name\": \"GER02\", \"type\": \"TERM\"}, \"start_location\": {\"name\": \"GER01\", \"type\": \"PLANT\"}, \"truck_number\": 1}": {
    "load": [
      525,
      531,
      539,
      532
    ]
  },
  "{\"departure_date\": \"2025-07-08\", \"end_location\": {\"name\": \"FRA01\", \"type\": \"DEAL\"}, \"start_location\": {\"name\": \"GER02\", \"type\": \"TERM\"}, \"truck_number\": 2}": {
    "load": [
      482,
      484
    ]
  },
  "{\"departure_date\": \"2025-07-08\", \"end_location\": {\"name\": \"GER02\", \"type\": \"TERM\"}, \"start_location\": {\"name\": \"GER01\", \"type\": \"PLANT\"}, \"truck_number\": 11}": {
    "load": [
      483,
      519,
      489,
      491,
      504,
      538,
      444,
      523,
      492,
      528,
      465,
      498,
      534,
      535,
      510
    ]
  },
  "{\"departure_date\": \"2025-07-09\", \"end_location\": {\"name\": \"FRA01\", \"type\": \"DEAL\"}, \"start_location\": {\"name\": \"BEL01\", \"type\": \"TERM\"}, \"truck_number\": 1}": {
    "load": [
      428,
      464,
      435,
      346,
      379,
      479,
      442,
      488,
      429,
      493,
      432,
      443,
      449,
      418,
      499
    ]
  },
  "{\"departure_date\": \"2025-07-09\", \"end_location\": {\"name\": \"FRA01\", \"type\": \"DEAL\"}, \"start_location\": {\"name\": \"BEL01\", \"type\": \"TERM\"}, \"truck_number\": 2}": {
    "load": [
      473,
      458,
      494,
      474,
      476,
      445,
      471,
      407,
      452,
      462,
      497,
      481,
      455,
      495
    ]
  },
  "{\"departure_date\": \"2025-07-09\", \"end_location\": {\"name\": \"FRA01\", \"type\": \"DEAL\"}, \"start_location\": {\"name\": \"GER02\", \"type\": \"TERM\"}, \"truck_number\": 1}": {
    "load": [
      454,
      425,
      427
    ]
  },
  "{\"departure_date\": \"2025-07-09\", \"end_location\": {\"name\": \"BEL01\", \"type\": \"TERM\"}, \"start_location\": {\"name\": \"GER01\", \"type\": \"PLANT\"}, \"truck_number\": 11}": {
    "load": [
      529,
      518,
      521,
      522,
      554,
      496,
      533,
      470,
      541,
      542,
      447,
      550
    ]
  },
  "{\"departure_date\": \"2025-07-10\", \"end_location\": {\"name\": \"FRA01\", \"type\": \"DEAL\"}, \"start_location\": {\"name\": \"GER02\", \"type\": \"TERM\"}, \"truck_number\": 1}": {
    "load": [
      460,
      416,
      440,
      457,
      431,
      463
    ]
  },
  "{\"departure_date\": \"2025-07-10\", \"end_location\": {\"name\": \"FRA01\", \"type\": \"DEAL\"}, \"start_location\": {\"name\": \"BEL01\", \"type\": \"TERM\"}, \"truck_number\": 1}": {
    "load": [
      406,
      439,
      414,
      415,
      461,
      500,
      502,
      509,
      513,
      480,
      512
    ]
  },
  "{\"departure_date\": \"2025-07-10\", \"end_location\": {\"name\": \"BEL01\", \"type\": \"TERM\"}, \"start_location\": {\"name\": \"GER01\", \"type\": \"PLANT\"}, \"truck_number\": 1}": {
    "load": [
      576,
      546,
      571,
      544,
      547,
      549,
      552,
      524,
      564,
      566,
      537,
      570,
      573,
      558,
      559,
      562
    ]
  },
  "{\"departure_date\": \"2025-07-10\", \"end_location\": {\"name\": \"FRA01\", \"type\": \"DEAL\"}, \"start_location\": {\"name\": \"BEL01\", \"type\": \"TERM\"}, \"truck_number\": 2}": {
    "load": [
      505,
      506,
      511
    ]
  },
  "{\"departure_date\": \"2025-07-11\", \"end_location\": {\"name\": \"FRA01\", \"type\": \"DEAL\"}, \"start_location\": {\"name\": \"GER02\", \"type\": \"TERM\"}, \"truck_number\": 1}": {
    "load": [
      467,
      472,
      475,
      515,
      486,
      487,
      430,
      525,
      531,
      468,
      539,
      466
    ]
  },
  "{\"departure_date\": \"2025-07-11\", \"end_location\": {\"name\": \"FRA01\", \"type\": \"DEAL\"}, \"start_location\": {\"name\": \"GER02\", \"type\": \"TERM\"}, \"truck_number\": 2}": {
    "load": [
      410,
      413
    ]
  },
  "{\"departure_date\": \"2025-07-11\", \"end_location\": {\"name\": \"FRA01\", \"type\": \"DEAL\"}, \"start_location\": {\"name\": \"BEL01\", \"type\": \"TERM\"}, \"truck_number\": 1}": {
    "load": [
      485,
      478,
      490,
      503,
      516,
      507,
      508
    ]
  },
  "{\"departure_date\": \"2025-07-11\", \"end_location\": {\"name\": \"GER02\", \"type\": \"TERM\"}, \"start_location\": {\"name\": \"GER01\", \"type\": \"PLANT\"}, \"truck_number\": 1}": {
    "load": [
      583,
      582,
      551,
      520,
      585,
      587
    ]
  },
  "{\"departure_date\": \"2025-07-11\", \"end_location\": {\"name\": \"BEL01\", \"type\": \"TERM\"}, \"start_location\": {\"name\": \"GER01\", \"type\": \"PLANT\"}, \"truck_number\": 1}": {
    "load": [
      553,
      556,
      589
    ]
  },
  "{\"departure_date\": \"2025-07-14\", \"end_location\": {\"name\": \"FRA01\", \"type\": \"DEAL\"}, \"start_location\": {\"name\": \"BEL01\", \"type\": \"TERM\"}, \"truck_number\": 1}": {
    "load": [
      529,
      518,
      521,
      522,
      554,
      496,
      533,
      550,
      553,
      576,
      556,
      589
    ]
  },
  "{\"departure_date\": \"2025-07-14\", \"end_location\": {\"name\": \"FRA01\", \"type\": \"DEAL\"}, \"start_location\": {\"name\": \"GER02\", \"type\": \"TERM\"}, \"truck_number\": 1}": {
    "load": [
      409,
      483,
      519,
      456,
      489,
      491
    ]
  },
  "{\"departure_date\": \"2025-07-14\", \"end_location\": {\"name\": \"FRA01\", \"type\": \"DEAL\"}, \"start_location\": {\"name\": \"BEL01\", \"type\": \"TERM\"}, \"truck_number\": 2}": {
    "load": [
      470,
      541,
      542,
      447,
      537,
      570,
      573,
      558,
      559,
      562
    ]
  },
  "{\"departure_date\": \"2025-07-14\", \"end_location\": {\"name\": \"BEL01\", \"type\": \"TERM\"}, \"start_location\": {\"name\": \"GER01\", \"type\": \"PLANT\"}, \"truck_number\": 1}": {
    "load": [
      545,
      555,
      591,
      563,
      595,
      569,
      477,
      446,
      543,
      586,
      594,
      561,
      530,
      501,
      565,
      536,
      540,
      575,
      598
    ]
  },
  "{\"departure_date\": \"2025-07-14\", \"end_location\": {\"name\": \"GER02\", \"type\": \"TERM\"}, \"start_location\": {\"name\": \"GER01\", \"type\": \"PLANT\"}, \"truck_number\": 1}": {
    "load": [
      526,
      560,
      592,
      593,
      599,
      588,
      596,
      597
    ]
  },
  "{\"departure_date\": \"2025-07-15\", \"end_location\": {\"name\": \"FRA01\", \"type\": \"DEAL\"}, \"start_location\": {\"name\": \"GER02\", \"type\": \"TERM\"}, \"truck_number\": 1}": {
    "load": [
      504,
      538,
      444,
      583,
      523,
      492,
      528
    ]
  },
  "{\"departure_date\": \"2025-07-15\", \"end_location\": {\"name\": \"FRA01\", \"type\": \"DEAL\"}, \"start_location\": {\"name\": \"GER02\", \"type\": \"TERM\"}, \"truck_number\": 2}": {
    "load": [
      534,
      535,
      510
    ]
  },
  "{\"departure_date\": \"2025-07-15\", \"end_location\": {\"name\": \"FRA01\", \"type\": \"DEAL\"}, \"start_location\": {\"name\": \"BEL01\", \"type\": \"TERM\"}, \"truck_number\": 1}": {
    "load": [
      546,
      571,
      544,
      547,
      549,
      552,
      524,
      564,
      566
    ]
  },
  "{\"departure_date\": \"2025-07-16\", \"end_location\": {\"name\": \"FRA01\", \"type\": \"DEAL\"}, \"start_location\": {\"name\": \"GER02\", \"type\": \"TERM\"}, \"truck_number\": 1}": {
    "load": [
      465,
      498,
      582,
      551,
      520,
      585,
      587
    ]
  },
  "{\"departure_date\": \"2025-07-17\", \"end_location\": {\"name\": \"FRA01\", \"type\": \"DEAL\"}, \"start_location\": {\"name\": \"GER02\", \"type\": \"TERM\"}, \"truck_number\": 1}": {
    "load": [
      526,
      560,
      592,
      593,
      599,
      588,
      596,
      597,
      514,
      517
    ]
  },
  "{\"departure_date\": \"2025-07-17\", \"end_location\": {\"name\": \"BEL01\", \"type\": \"TERM\"}, \"start_location\": {\"name\": \"GER01\", \"type\": \"PLANT\"}, \"truck_number\": 1}": {
    "load": [
      579,
      580,
      557,
      527
    ]
  },
  "{\"departure_date\": \"2025-07-17\", \"end_location\": {\"name\": \"GER02\", \"type\": \"TERM\"}, \"start_location\": {\"name\": \"GER01\", \"type\": \"PLANT\"}, \"truck_number\": 11}": {
    "load": [
      578,
      548,
      584,
      590,
      567,
      568,
      577,
      572
    ]
  },
  "{\"departure_date\": \"2025-07-18\", \"end_location\": {\"name\": \"FRA01\", \"type\": \"DEAL\"}, \"start_location\": {\"name\": \"BEL01\", \"type\": \"TERM\"}, \"truck_number\": 1}": {
    "load": [
      591,
      595,
      477,
      543,
      545,
      555,
      563,
      561,
      501,
      565,
      575,
      598
    ]
  },
  "{\"departure_date\": \"2025-07-18\", \"end_location\": {\"name\": \"FRA01\", \"type\": \"DEAL\"}, \"start_location\": {\"name\": \"BEL01\", \"type\": \"TERM\"}, \"truck_number\": 2}": {
    "load": [
      569,
      446,
      586,
      594,
      530,
      536,
      540
    ]
  },
  "{\"departure_date\": \"2025-07-18\", \"end_location\": {\"name\": \"FRA01\", \"type\": \"DEAL\"}, \"start_location\": {\"name\": \"GER02\", \"type\": \"TERM\"}, \"truck_number\": 1}": {
    "load": [
      532
    ]
  },
  "{\"departure_date\": \"2025-07-18\", \"end_location\": {\"name\": \"BEL01\", \"type\": \"TERM\"}, \"start_location\": {\"name\": \"GER01\", \"type\": \"PLANT\"}, \"truck_number\": 11}": {
    "load": [
      581,
      574
    ]
  },
  "{\"departure_date\": \"2025-07-21\", \"end_location\": {\"name\": \"FRA01\", \"type\": \"DEAL\"}, \"start_location\": {\"name\": \"BEL01\", \"type\": \"TERM\"}, \"truck_number\": 1}": {
    "load": [
      579,
      580,
      557,
      527
    ]
  },
  "{\"departure_date\": \"2025-07-21\", \"end_location\": {\"name\": \"FRA01\", \"type\": \"DEAL\"}, \"start_location\": {\"name\": \"GER02\", \"type\": \"TERM\"}, \"truck_number\": 1}": {
    "load": [
      578,
      548,
      584,
      590,
      567,
      568,
      577,
      572
    ]
  },
  "{\"departure_date\": \"2025-07-22\", \"end_location\": {\"name\": \"FRA01\", \"type\": \"DEAL\"}, \"start_location\": {\"name\": \"BEL01\", \"type\": \"TERM\"}, \"truck_number\": 1}": {
    "load": [
      581,
      574
    ]
  },
  "{\"departure_date\": \"2025-06-16\", \"end_location\": {\"name\": \"GER02\", \"type\": \"TERM\"}, \"start_location\": {\"name\": \"GER01\", \"type\": \"PLANT\"}, \"truck_number\": 1}": {
    "load": []
  },
  "{\"departure_date\": \"2025-06-17\", \"end_location\": {\"name\": \"GER02\", \"type\": \"TERM\"}, \"start_location\": {\"name\": \"GER01\", \"type\": \"PLANT\"}, \"truck_number\": 1}": {
    "load": []
  },
  "{\"departure_date\": \"2025-06-19\", \"end_location\": {\"name\": \"GER02\", \"type\": \"TERM\"}, \"start_location\": {\"name\": \"GER01\", \"type\": \"PLANT\"}, \"truck_number\": 1}": {
    "load": []
  },
  "{\"departure_date\": \"2025-07-09\", \"end_location\": {\"name\": \"GER02\", \"type\": \"TERM\"}, \"start_location\": {\"name\": \"GER01\", \"type\": \"PLANT\"}, \"truck_number\": 1}": {
    "load": []
  },
  "{\"departure_date\": \"2025-07-10\", \"end_location\": {\"name\": \"GER02\", \"type\": \"TERM\"}, \"start_location\": {\"name\": \"GER01\", \"type\": \"PLANT\"}, \"truck_number\": 1}": {
    "load": []
  },
  "{\"departure_date\": \"2025-07-15\", \"end_location\": {\"name\": \"GER02\", \"type\": \"TERM\"}, \"start_location\": {\"name\": \"GER01\", \"type\": \"PLANT\"}, \"truck_number\": 1}": {
    "load": []
  },
  "{\"departure_date\": \"2025-07-16\", \"end_location\": {\"name\": \"GER02\", \"type\": \"TERM\"}, \"start_location\": {\"name\": \"GER01\", \"type\": \"PLANT\"}, \"truck_number\": 1}": {
    "load": []
  },
  "{\"departure_date\": \"2025-07-17\", \"end_location\": {\"name\": \"GER02\", \"type\": \"TERM\"}, \"start_location\": {\"name\": \"GER01\", \"type\": \"PLANT\"}, \"truck_number\": 1}": {
    "load": []
  },
  "{\"departure_date\": \"2025-07-18\", \"end_location\": {\"name\": \"GER02\", \"type\": \"TERM\"}, \"start_location\": {\"name\": \"GER01\", \"type\": \"PLANT\"}, \"truck_number\": 1}": {
    "load": []
  },
  "{\"departure_date\": \"2025-07-21\", \"end_location\": {\"name\": \"GER02\", \"type\": \"TERM\"}, \"start_location\": {\"name\": \"GER01\", \"type\": \"PLANT\"}, \"truck_number\": 1}": {
    "load": []
  },
  "{\"departure_date\": \"2025-07-22\", \"end_location\": {\"name\": \"GER02\", \"type\": \"TERM\"}, \"start_location\": {\"name\": \"GER01\", \"type\": \"PLANT\"}, \"truck_number\": 1}": {
    "load": []
  },
  "{\"departure_date\": \"2025-07-23\", \"end_location\": {\"name\": \"GER02\", \"type\": \"TERM\"}, \"start_location\": {\"name\": \"GER01\", \"type\": \"PLANT\"}, \"truck_number\": 1}": {
    "load": []
  },
  "{\"departure_date\": \"2025-07-24\", \"end_location\": {\"name\": \"GER02\", \"type\": \"TERM\"}, \"start_location\": {\"name\": \"GER01\", \"type\": \"PLANT\"}, \"truck_number\": 1}": {
    "load": []
  },
  "{\"departure_date\": \"2025-07-25\", \"end_location\": {\"name\": \"GER02\", \"type\": \"TERM\"}, \"start_location\": {\"name\": \"GER01\", \"type\": \"PLANT\"}, \"truck_number\": 1}": {
    "load": []
  },
  "{\"departure_date\": \"2025-07-28\", \"end_location\": {\"name\": \"GER02\", \"type\": \"TERM\"}, \"start_location\": {\"name\": \"GER01\", \"type\": \"PLANT\"}, \"truck_number\": 1}": {
    "load": []
  },
  "{\"departure_date\": \"2025-07-29\", \"end_location\": {\"name\": \"GER02\", \"type\": \"TERM\"}, \"start_location\": {\"name\": \"GER01\", \"type\": \"PLANT\"}, \"truck_number\": 1}": {
    "load": []
  },
  "{\"departure_date\": \"2025-07-30\", \"end_location\": {\"name\": \"GER02\", \"type\": \"TERM\"}, \"start_location\": {\"name\": \"GER01\", \"type\": \"PLANT\"}, \"truck_number\": 1}": {
    "load": []
  },
  "{\"departure_date\": \"2025-07-31\", \"end_location\": {\"name\": \"GER02\", \"type\": \"TERM\"}, \"start_location\": {\"name\": \"GER01\", \"type\": \"PLANT\"}, \"truck_number\": 1}": {
    "load": []
  },
  "{\"departure_date\": \"2025-08-01\", \"end_location\": {\"name\": \"GER02\", \"type\": \"TERM\"}, \"start_location\": {\"name\": \"GER01\", \"type\": \"PLANT\"}, \"truck_number\": 1}": {
    "load": []
  },
  "{\"departure_date\": \"2025-07-22\", \"end_location\": {\"name\": \"GER02\", \"type\": \"TERM\"}, \"start_location\": {\"name\": \"GER01\", \"type\": \"PLANT\"}, \"truck_number\": 11}": {
    "load": []
  },
  "{\"departure_date\": \"2025-07-24\", \"end_location\": {\"name\": \"GER02\", \"type\": \"TERM\"}, \"start_location\": {\"name\": \"GER01\", \"type\": \"PLANT\"}, \"truck_number\": 11}": {
    "load": []
  },
  "{\"departure_date\": \"2025-07-29\", \"end_location\": {\"name\": \"GER02\", \"type\": \"TERM\"}, \"start_location\": {\"name\": \"GER01\", \"type\": \"PLANT\"}, \"truck_number\": 11}": {
    "load": []
  },
  "{\"departure_date\": \"2025-07-31\", \"end_location\": {\"name\": \"GER02\", \"type\": \"TERM\"}, \"start_location\": {\"name\": \"GER01\", \"type\": \"PLANT\"}, \"truck_number\": 11}": {
    "load": []
  },
  "{\"departure_date\": \"2025-07-15\", \"end_location\": {\"name\": \"BEL01\", \"type\": \"TERM\"}, \"start_location\": {\"name\": \"GER01\", \"type\": \"PLANT\"}, \"truck_number\": 1}": {
    "load": []
  },
  "{\"departure_date\": \"2025-07-21\", \"end_location\": {\"name\": \"BEL01\", \"type\": \"TERM\"}, \"start_location\": {\"name\": \"GER01\", \"type\": \"PLANT\"}, \"truck_number\": 1}": {
    "load": []
  },
  "{\"departure_date\": \"2025-07-22\", \"end_location\": {\"name\": \"BEL01\", \"type\": \"TERM\"}, \"start_location\": {\"name\": \"GER01\", \"type\": \"PLANT\"}, \"truck_number\": 1}": {
    "load": []
  },
  "{\"departure_date\": \"2025-07-23\", \"end_location\": {\"name\": \"BEL01\", \"type\": \"TERM\"}, \"start_location\": {\"name\": \"GER01\", \"type\": \"PLANT\"}, \"truck_number\": 1}": {
    "load": []
  },
  "{\"departure_date\": \"2025-07-24\", \"end_location\": {\"name\": \"BEL01\", \"type\": \"TERM\"}, \"start_location\": {\"name\": \"GER01\", \"type\": \"PLANT\"}, \"truck_number\": 1}": {
    "load": []
  },
  "{\"departure_date\": \"2025-07-25\", \"end_location\": {\"name\": \"BEL01\", \"type\": \"TERM\"}, \"start_location\": {\"name\": \"GER01\", \"type\": \"PLANT\"}, \"truck_number\": 1}": {
    "load": []
  },
  "{\"departure_date\": \"2025-07-28\", \"end_location\": {\"name\": \"BEL01\", \"type\": \"TERM\"}, \"start_location\": {\"name\": \"GER01\", \"type\": \"PLANT\"}, \"truck_number\": 1}": {
    "load": []
  },
  "{\"departure_date\": \"2025-07-29\", \"end_location\": {\"name\": \"BEL01\", \"type\": \"TERM\"}, \"start_location\": {\"name\": \"GER01\", \"type\": \"PLANT\"}, \"truck_number\": 1}": {
    "load": []
  },
  "{\"departure_date\": \"2025-07-30\", \"end_location\": {\"name\": \"BEL01\", \"type\": \"TERM\"}, \"start_location\": {\"name\": \"GER01\", \"type\": \"PLANT\"}, \"truck_number\": 1}": {
    "load": []
  },
  "{\"departure_date\": \"2025-07-31\", \"end_location\": {\"name\": \"BEL01\", \"type\": \"TERM\"}, \"start_location\": {\"name\": \"GER01\", \"type\": \"PLANT\"}, \"truck_number\": 1}": {
    "load": []
  },
  "{\"departure_date\": \"2025-08-01\", \"end_location\": {\"name\": \"BEL01\", \"type\": \"TERM\"}, \"start_location\": {\"name\": \"GER01\", \"type\": \"PLANT\"}, \"truck_number\": 1}": {
    "load": []
  },
  "{\"departure_date\": \"2025-07-23\", \"end_location\": {\"name\": \"BEL01\", \"type\": \"TERM\"}, \"start_location\": {\"name\": \"GER01\", \"type\": \"PLANT\"}, \"truck_number\": 11}": {
    "load": []
  },
  "{\"departure_date\": \"2025-07-25\", \"end_location\": {\"name\": \"BEL01\", \"type\": \"TERM\"}, \"start_location\": {\"name\": \"GER01\", \"type\": \"PLANT\"}, \"truck_number\": 11}": {
    "load": []
  },
  "{\"departure_date\": \"2025-07-30\", \"end_location\": {\"name\": \"BEL01\", \"type\": \"TERM\"}, \"start_location\": {\"name\": \"GER01\", \"type\": \"PLANT\"}, \"truck_number\": 11}": {
    "load": []
  },
  "{\"departure_date\": \"2025-08-01\", \"end_location\": {\"name\": \"BEL01\", \"type\": \"TERM\"}, \"start_location\": {\"name\": \"GER01\", \"type\": \"PLANT\"}, \"truck_number\": 11}": {
    "load": []
  },
  "{\"departure_date\": \"2025-06-02\", \"end_location\": {\"name\": \"FRA01\", \"type\": \"DEAL\"}, \"start_location\": {\"name\": \"GER02\", \"type\": \"TERM\"}, \"truck_number\": 1}": {
    "load": []
  },
  "{\"departure_date\": \"2025-06-03\", \"end_location\": {\"name\": \"FRA01\", \"type\": \"DEAL\"}, \"start_location\": {\"name\": \"GER02\", \"type\": \"TERM\"}, \"truck_number\": 1}": {
    "load": []
  },
  "{\"departure_date\": \"2025-07-22\", \"end_location\": {\"name\": \"FRA01\", \"type\": \"DEAL\"}, \"start_location\": {\"name\": \"GER02\", \"type\": \"TERM\"}, \"truck_number\": 1}": {
    "load": []
  },
  "{\"departure_date\": \"2025-07-23\", \"end_location\": {\"name\": \"FRA01\", \"type\": \"DEAL\"}, \"start_location\": {\"name\": \"GER02\", \"type\": \"TERM\"}, \"truck_number\": 1}": {
    "load": []
  },
  "{\"departure_date\": \"2025-07-24\", \"end_location\": {\"name\": \"FRA01\", \"type\": \"DEAL\"}, \"start_location\": {\"name\": \"GER02\", \"type\": \"TERM\"}, \"truck_number\": 1}": {
    "load": []
  },
  "{\"departure_date\": \"2025-07-25\", \"end_location\": {\"name\": \"FRA01\", \"type\": \"DEAL\"}, \"start_location\": {\"name\": \"GER02\", \"type\": \"TERM\"}, \"truck_number\": 1}": {
    "load": []
  },
  "{\"departure_date\": \"2025-07-28\", \"end_location\": {\"name\": \"FRA01\", \"type\": \"DEAL\"}, \"start_location\": {\"name\": \"GER02\", \"type\": \"TERM\"}, \"truck_number\": 1}": {
    "load": []
  },
  "{\"departure_date\": \"2025-07-29\", \"end_location\": {\"name\": \"FRA01\", \"type\": \"DEAL\"}, \"start_location\": {\"name\": \"GER02\", \"type\": \"TERM\"}, \"truck_number\": 1}": {
    "load": []
  },
  "{\"departure_date\": \"2025-08-01\", \"end_location\": {\"name\": \"FRA01\", \"type\": \"DEAL\"}, \"start_location\": {\"name\": \"GER02\", \"type\": \"TERM\"}, \"truck_number\": 1}": {
    "load": []
  },
  "{\"departure_date\": \"2025-06-02\", \"end_location\": {\"name\": \"FRA01\", \"type\": \"DEAL\"}, \"start_location\": {\"name\": \"GER02\", \"type\": \"TERM\"}, \"truck_number\": 2}": {
    "load": []
  },
  "{\"departure_date\": \"2025-06-03\", \"end_location\": {\"name\": \"FRA01\", \"type\": \"DEAL\"}, \"start_location\": {\"name\": \"GER02\", \"type\": \"TERM\"}, \"truck_number\": 2}": {
    "load": []
  },
  "{\"departure_date\": \"2025-06-05\", \"end_location\": {\"name\": \"FRA01\", \"type\": \"DEAL\"}, \"start_location\": {\"name\": \"GER02\", \"type\": \"TERM\"}, \"truck_number\": 2}": {
    "load": []
  },
  "{\"departure_date\": \"2025-06-06\", \"end_location\": {\"name\": \"FRA01\", \"type\": \"DEAL\"}, \"start_location\": {\"name\": \"GER02\", \"type\": \"TERM\"}, \"truck_number\": 2}": {
    "load": []
  },
  "{\"departure_date\": \"2025-06-12\", \"end_location\": {\"name\": \"FRA01\", \"type\": \"DEAL\"}, \"start_location\": {\"name\": \"GER02\", \"type\": \"TERM\"}, \"truck_number\": 2}": {
    "load": []
  },
  "{\"departure_date\": \"2025-06-13\", \"end_location\": {\"name\": \"FRA01\", \"type\": \"DEAL\"}, \"start_location\": {\"name\": \"GER02\", \"type\": \"TERM\"}, \"truck_number\": 2}": {
    "load": []
  },
  "{\"departure_date\": \"2025-06-16\", \"end_location\": {\"name\": \"FRA01\", \"type\": \"DEAL\"}, \"start_location\": {\"name\": \"GER02\", \"type\": \"TERM\"}, \"truck_number\": 2}": {
    "load": []
  },
  "{\"departure_date\": \"2025-06-20\", \"end_location\": {\"name\": \"FRA01\", \"type\": \"DEAL\"}, \"start_location\": {\"name\": \"GER02\", \"type\": \"TERM\"}, \"truck_number\": 2}": {
    "load": []
  },
  "{\"departure_date\": \"2025-06-24\", \"end_location\": {\"name\": \"FRA01\", \"type\": \"DEAL\"}, \"start_location\": {\"name\": \"GER02\", \"type\": \"TERM\"}, \"truck_number\": 2}": {
    "load": []
  },
  "{\"departure_date\": \"2025-06-25\", \"end_location\": {\"name\": \"FRA01\", \"type\": \"DEAL\"}, \"start_location\": {\"name\": \"GER02\", \"type\": \"TERM\"}, \"truck_number\": 2}": {
    "load": []
  },
  "{\"departure_date\": \"2025-06-26\", \"end_location\": {\"name\": \"FRA01\", \"type\": \"DEAL\"}, \"start_location\": {\"name\": \"GER02\", \"type\": \"TERM\"}, \"truck_number\": 2}": {
    "load": []
  },
  "{\"departure_date\": \"2025-06-27\", \"end_location\": {\"name\": \"FRA01\", \"type\": \"DEAL\"}, \"start_location\": {\"name\": \"GER02\", \"type\": \"TERM\"}, \"truck_number\": 2}": {
    "load": []
  },
  "{\"departure_date\": \"2025-06-30\", \"end_location\": {\"name\": \"FRA01\", \"type\": \"DEAL\"}, \"start_location\": {\"name\": \"GER02\", \"type\": \"TERM\"}, \"truck_number\": 2}": {
    "load": []
  },
  "{\"departure_date\": \"2025-07-01\", \"end_location\": {\"name\": \"FRA01\", \"type\": \"DEAL\"}, \"start_location\": {\"name\": \"GER02\", \"type\": \"TERM\"}, \"truck_number\": 2}": {
    "load": []
  },
  "{\"departure_date\": \"2025-07-02\", \"end_location\": {\"name\": \"FRA01\", \"type\": \"DEAL\"}, \"start_location\": {\"name\": \"GER02\", \"type\": \"TERM\"}, \"truck_number\": 2}": {
    "load": []
  },
  "{\"departure_date\": \"2025-07-03\", \"end_location\": {\"name\": \"FRA01\", \"type\": \"DEAL\"}, \"start_location\": {\"name\": \"GER02\", \"type\": \"TERM\"}, \"truck_number\": 2}": {
    "load": []
  },
  "{\"departure_date\": \"2025-07-04\", \"end_location\": {\"name\": \"FRA01\", \"type\": \"DEAL\"}, \"start_location\": {\"name\": \"GER02\", \"type\": \"TERM\"}, \"truck_number\": 2}": {
    "load": []
  },
  "{\"departure_date\": \"2025-07-07\", \"end_location\": {\"name\": \"FRA01\", \"type\": \"DEAL\"}, \"start_location\": {\"name\": \"GER02\", \"type\": \"TERM\"}, \"truck_number\": 2}": {
    "load": []
  },
  "{\"departure_date\": \"2025-07-09\", \"end_location\": {\"name\": \"FRA01\", \"type\": \"DEAL\"}, \"start_location\": {\"name\": \"GER02\", \"type\": \"TERM\"}, \"truck_number\": 2}": {
    "load": []
  },
  "{\"departure_date\": \"2025-07-10\", \"end_location\": {\"name\": \"FRA01\", \"type\": \"DEAL\"}, \"start_location\": {\"name\": \"GER02\", \"type\": \"TERM\"}, \"truck_number\": 2}": {
    "load": []
  },
  "{\"departure_date\": \"2025-07-14\", \"end_location\": {\"name\": \"FRA01\", \"type\": \"DEAL\"}, \"start_location\": {\"name\": \"GER02\", \"type\": \"TERM\"}, \"truck_number\": 2}": {
    "load": []
  },
  "{\"departure_date\": \"2025-07-16\", \"end_location\": {\"name\": \"FRA01\", \"type\": \"DEAL\"}, \"start_location\": {\"name\": \"GER02\", \"type\": \"TERM\"}, \"truck_number\": 2}": {
    "load": []
  },
  "{\"departure_date\": \"2025-07-17\", \"end_location\": {\"name\": \"FRA01\", \"type\": \"DEAL\"}, \"start_location\": {\"name\": \"GER02\", \"type\": \"TERM\"}, \"truck_number\": 2}": {
    "load": []
  },
  "{\"departure_date\": \"2025-07-18\", \"end_location\": {\"name\": \"FRA01\", \"type\": \"DEAL\"}, \"start_location\": {\"name\": \"GER02\", \"type\": \"TERM\"}, \"truck_number\": 2}": {
    "load": []
  },
  "{\"departure_date\": \"2025-07-21\", \"end_location\": {\"name\": \"FRA01\", \"type\": \"DEAL\"}, \"start_location\": {\"name\": \"GER02\", \"type\": \"TERM\"}, \"truck_number\": 2}": {
    "load": []
  },
  "{\"departure_date\": \"2025-07-22\", \"end_location\": {\"name\": \"FRA01\", \"type\": \"DEAL\"}, \"start_location\": {\"name\": \"GER02\", \"type\": \"TERM\"}, \"truck_number\": 2}": {
    "load": []
  },
  "{\"departure_date\": \"2025-07-23\", \"end_location\": {\"name\": \"FRA01\", \"type\": \"DEAL\"}, \"start_location\": {\"name\": \"GER02\", \"type\": \"TERM\"}, \"truck_number\": 2}": {
    "load": []
  },
  "{\"departure_date\": \"2025-07-24\", \"end_location\": {\"name\": \"FRA01\", \"type\": \"DEAL\"}, \"start_location\": {\"name\": \"GER02\", \"type\": \"TERM\"}, \"truck_number\": 2}": {
    "load": []
  },
  "{\"departure_date\": \"2025-07-25\", \"end_location\": {\"name\": \"FRA01\", \"type\": \"DEAL\"}, \"start_location\": {\"name\": \"GER02\", \"type\": \"TERM\"}, \"truck_number\": 2}": {
    "load": []
  },
  "{\"departure_date\": \"2025-07-28\", \"end_location\": {\"name\": \"FRA01\", \"type\": \"DEAL\"}, \"start_location\": {\"name\": \"GER02\", \"type\": \"TERM\"}, \"truck_number\": 2}": {
    "load": []
  },
  "{\"departure_date\": \"2025-07-29\", \"end_location\": {\"name\": \"FRA01\", \"type\": \"DEAL\"}, \"start_location\": {\"name\": \"GER02\", \"type\": \"TERM\"}, \"truck_number\": 2}": {
    "load": []
  },
  "{\"departure_date\": \"2025-08-01\", \"end_location\": {\"name\": \"FRA01\", \"type\": \"DEAL\"}, \"start_location\": {\"name\": \"GER02\", \"type\": \"TERM\"}, \"truck_number\": 2}": {
    "load": []
  },
  "{\"departure_date\": \"2025-06-02\", \"end_location\": {\"name\": \"FRA01\", \"type\": \"DEAL\"}, \"start_location\": {\"name\": \"BEL01\", \"type\": \"TERM\"}, \"truck_number\": 1}": {
    "load": []
  },
  "{\"departure_date\": \"2025-06-03\", \"end_location\": {\"name\": \"FRA01\", \"type\": \"DEAL\"}, \"start_location\": {\"name\": \"BEL01\", \"type\": \"TERM\"}, \"truck_number\": 1}": {
    "load": []
  },
  "{\"departure_date\": \"2025-06-04\", \"end_location\": {\"name\": \"FRA01\", \"type\": \"DEAL\"}, \"start_location\": {\"name\": \"BEL01\", \"type\": \"TERM\"}, \"truck_number\": 1}": {
    "load": []
  },
  "{\"departure_date\": \"2025-07-16\", \"end_location\": {\"name\": \"FRA01\", \"type\": \"DEAL\"}, \"start_location\": {\"name\": \"BEL01\", \"type\": \"TERM\"}, \"truck_number\": 1}": {
    "load": []
  },
  "{\"departure_date\": \"2025-07-24\", \"end_location\": {\"name\": \"FRA01\", \"type\": \"DEAL\"}, \"start_location\": {\"name\": \"BEL01\", \"type\": \"TERM\"}, \"truck_number\": 1}": {
    "load": []
  },
  "{\"departure_date\": \"2025-07-25\", \"end_location\": {\"name\": \"FRA01\", \"type\": \"DEAL\"}, \"start_location\": {\"name\": \"BEL01\", \"type\": \"TERM\"}, \"truck_number\": 1}": {
    "load": []
  },
  "{\"departure_date\": \"2025-07-28\", \"end_location\": {\"name\": \"FRA01\", \"type\": \"DEAL\"}, \"start_location\": {\"name\": \"BEL01\", \"type\": \"TERM\"}, \"truck_number\": 1}": {
    "load": []
  },
  "{\"departure_date\": \"2025-07-29\", \"end_location\": {\"name\": \"FRA01\", \"type\": \"DEAL\"}, \"start_location\": {\"name\": \"BEL01\", \"type\": \"TERM\"}, \"truck_number\": 1}": {
    "load": []
  },
  "{\"departure_date\": \"2025-07-30\", \"end_location\": {\"name\": \"FRA01\", \"type\": \"DEAL\"}, \"start_location\": {\"name\": \"BEL01\", \"type\": \"TERM\"}, \"truck_number\": 1}": {
    "load": []
  },
  "{\"departure_date\": \"2025-07-31\", \"end_location\": {\"name\": \"FRA01\", \"type\": \"DEAL\"}, \"start_location\": {\"name\": \"BEL01\", \"type\": \"TERM\"}, \"truck_number\": 1}": {
    "load": []
  },
  "{\"departure_date\": \"2025-08-01\", \"end_location\": {\"name\": \"FRA01\", \"type\": \"DEAL\"}, \"start_location\": {\"name\": \"BEL01\", \"type\": \"TERM\"}, \"truck_number\": 1}": {
    "load": []
  },
  "{\"departure_date\": \"2025-06-02\", \"end_location\": {\"name\": \"FRA01\", \"type\": \"DEAL\"}, \"start_location\": {\"name\": \"BEL01\", \"type\": \"TERM\"}, \"truck_number\": 2}": {
    "load": []
  },
  "{\"departure_date\": \"2025-06-03\", \"end_location\": {\"name\": \"FRA01\", \"type\": \"DEAL\"}, \"start_location\": {\"name\": \"BEL01\", \"type\": \"TERM\"}, \"truck_number\": 2}": {
    "load": []
  },
  "{\"departure_date\": \"2025-06-04\", \"end_location\": {\"name\": \"FRA01\", \"type\": \"DEAL\"}, \"start_location\": {\"name\": \"BEL01\", \"type\": \"TERM\"}, \"truck_number\": 2}": {
    "load": []
  },
  "{\"departure_date\": \"2025-06-05\", \"end_location\": {\"name\": \"FRA01\", \"type\": \"DEAL\"}, \"start_location\": {\"name\": \"BEL01\", \"type\": \"TERM\"}, \"truck_number\": 2}": {
    "load": []
  },
  "{\"departure_date\": \"2025-06-06\", \"end_location\": {\"name\": \"FRA01\", \"type\": \"DEAL\"}, \"start_location\": {\"name\": \"BEL01\", \"type\": \"TERM\"}, \"truck_number\": 2}": {
    "load": []
  },
  "{\"departure_date\": \"2025-06-10\", \"end_location\": {\"name\": \"FRA01\", \"type\": \"DEAL\"}, \"start_location\": {\"name\": \"BEL01\", \"type\": \"TERM\"}, \"truck_number\": 2}": {
    "load": []
  },
  "{\"departure_date\": \"2025-06-11\", \"end_location\": {\"name\": \"FRA01\", \"type\": \"DEAL\"}, \"start_location\": {\"name\": \"BEL01\", \"type\": \"TERM\"}, \"truck_number\": 2}": {
    "load": []
  },
  "{\"departure_date\": \"2025-06-12\", \"end_location\": {\"name\": \"FRA01\", \"type\": \"DEAL\"}, \"start_location\": {\"name\": \"BEL01\", \"type\": \"TERM\"}, \"truck_number\": 2}": {
    "load": []
  },
  "{\"departure_date\": \"2025-06-13\", \"end_location\": {\"name\": \"FRA01\", \"type\": \"DEAL\"}, \"start_location\": {\"name\": \"BEL01\", \"type\": \"TERM\"}, \"truck_number\": 2}": {
    "load": []
  },
  "{\"departure_date\": \"2025-06-18\", \"end_location\": {\"name\": \"FRA01\", \"type\": \"DEAL\"}, \"start_location\": {\"name\": \"BEL01\", \"type\": \"TERM\"}, \"truck_number\": 2}": {
    "load": []
  },
  "{\"departure_date\": \"2025-07-01\", \"end_location\": {\"name\": \"FRA01\", \"type\": \"DEAL\"}, \"start_location\": {\"name\": \"BEL01\", \"type\": \"TERM\"}, \"truck_number\": 2}": {
    "load": []
  },
  "{\"departure_date\": \"2025-07-02\", \"end_location\": {\"name\": \"FRA01\", \"type\": \"DEAL\"}, \"start_location\": {\"name\": \"BEL01\", \"type\": \"TERM\"}, \"truck_number\": 2}": {
    "load": []
  },
  "{\"departure_date\": \"2025-07-11\", \"end_location\": {\"name\": \"FRA01\", \"type\": \"DEAL\"}, \"start_location\": {\"name\": \"BEL01\", \"type\": \"TERM\"}, \"truck_number\": 2}": {
    "load": []
  },
  "{\"departure_date\": \"2025-07-15\", \"end_location\": {\"name\": \"FRA01\", \"type\": \"DEAL\"}, \"start_location\": {\"name\": \"BEL01\", \"type\": \"TERM\"}, \"truck_number\": 2}": {
    "load": []
  },
  "{\"departure_date\": \"2025-07-16\", \"end_location\": {\"name\": \"FRA01\", \"type\": \"DEAL\"}, \"start_location\": {\"name\": \"BEL01\", \"type\": \"TERM\"}, \"truck_number\": 2}": {
    "load": []
  },
  "{\"departure_date\": \"2025-07-21\", \"end_location\": {\"name\": \"FRA01\", \"type\": \"DEAL\"}, \"start_location\": {\"name\": \"BEL01\", \"type\": \"TERM\"}, \"truck_number\": 2}": {
    "load": []
  },
  "{\"departure_date\": \"2025-07-22\", \"end_location\": {\"name\": \"FRA01\", \"type\": \"DEAL\"}, \"start_location\": {\"name\": \"BEL01\", \"type\": \"TERM\"}, \"truck_number\": 2}": {
    "load": []
  },
  "{\"departure_date\": \"2025-07-24\", \"end_location\": {\"name\": \"FRA01\", \"type\": \"DEAL\"}, \"start_location\": {\"name\": \"BEL01\", \"type\": \"TERM\"}, \"truck_number\": 2}": {
    "load": []
  },
  "{\"departure_date\": \"2025-07-25\", \"end_location\": {\"name\": \"FRA01\", \"type\": \"DEAL\"}, \"start_location\": {\"name\": \"BEL01\", \"type\": \"TERM\"}, \"truck_number\": 2}": {
    "load": []
  },
  "{\"departure_date\": \"2025-07-28\", \"end_location\": {\"name\": \"FRA01\", \"type\": \"DEAL\"}, \"start_location\": {\"name\": \"BEL01\", \"type\": \"TERM\"}, \"truck_number\": 2}": {
    "load": []
  },
  "{\"departure_date\": \"2025-07-29\", \"end_location\": {\"name\": \"FRA01\", \"type\": \"DEAL\"}, \"start_location\": {\"name\": \"BEL01\", \"type\": \"TERM\"}, \"truck_number\": 2}": {
    "load": []
  },
  "{\"departure_date\": \"2025-07-30\", \"end_location\": {\"name\": \"FRA01\", \"type\": \"DEAL\"}, \"start_location\": {\"name\": \"BEL01\", \"type\": \"TERM\"}, \"truck_number\": 2}": {
    "load": []
  },
  "{\"departure_date\": \"2025-07-31\", \"end_location\": {\"name\": \"FRA01\", \"type\": \"DEAL\"}, \"start_location\": {\"name\": \"BEL01\", \"type\": \"TERM\"}, \"truck_number\": 2}": {
    "load": []
  },
  "{\"departure_date\": \"2025-08-01\", \"end_location\": {\"name\": \"FRA01\", \"type\": \"DEAL\"}, \"start_location\": {\"name\": \"BEL01\", \"type\": \"TERM\"}, \"truck_number\": 2}": {
    "load": []
  }
}