{
  "{\"departure_date\": \"2025-06-03\", \"end_location\": {\"name\": \"GER02\", \"type\": \"TERM\"}, \"start_location\": {\"name\": \"GER01\", \"type\": \"PLANT\"}, \"truck_number\": 1}": {
    "load": [
      0,
      7,
      8,
      10,
      15,
      17,
      18,
      19,
      21,
      22,
      25,
      26,
      34,
      36,
      37,
      38,
      39
    ]
  },
  "{\"departure_date\": \"2025-06-06\", \"end_location\": {\"name\": \"FRA01\", \"type\": \"DEAL\"}, \"start_location\": {\"name\": \"GER02\", \"type\": \"TERM\"}, \"truck_number\": 1}": {
    "load": [
      0,
      7,
      8,
      10,
      15,
      17,
      18,
      19,
      21,
      22,
      25,
      26,
      34,
      36,
      37,
      38,
      39
    ]
  },
  "{\"departure_date\": \"2025-06-02\", \"end_location\": {\"name\": \"BEL01\", \"type\": \"TERM\"}, \"start_location\": {\"name\": \"GER01\", \"type\": \"PLANT\"}, \"truck_number\": 1}": {
    "load": [
      1,
      2,
      3,
      4,
      6,
      9,
      12,
      16
    ]
  },
  "{\"departure_date\": \"2025-06-06\", \"end_location\": {\"name\": \"FRA01\", \"type\": \"DEAL\"}, \"start_location\": {\"name\": \"BEL01\", \"type\": \"TERM\"}, \"truck_number\": 1}": {
    "load": [
      1,
      3,
      4,
      16
    ]
  },
  "{\"departure_date\": \"2025-06-05\", \"end_location\": {\"name\": \"FRA01\", \"type\": \"DEAL\"}, \"start_location\": {\"name\": \"BEL01\", \"type\": \"TERM\"}, \"truck_number\": 1}": {
    "load": [
      2,
      6,
      9,
      12
    ]
  },
  "{\"departure_date\": \"2025-06-03\", \"end_location\": {\"name\": \"GER02\", \"type\": \"TERM\"}, \"start_location\": {\"name\": \"GER01\", \"type\": \"PLANT\"}, \"truck_number\": 11}": {
    "load": [
      5,
      11,
      13,
      14,
      20,
      23,
      24,
      27,
      28,
      29,
      30,
      31,
      32,
      33,
      35
    ]
  },
  "{\"departure_date\": \"2025-06-10\", \"end_location\": {\"name\": \"FRA01\", \"type\": \"DEAL\"}, \"start_location\": {\"name\": \"GER02\", \"type\": \"TERM\"}, \"truck_number\": 1}": {
    "load": [
      5,
      11,
      14,
      23,
      27,
      35,
      46,
      47,
      48,
      70
    ]
  },
  "{\"departure_date\": \"2025-06-13\", \"end_location\": {\"name\": \"FRA01\", \"type\": \"DEAL\"}, \"start_location\": {\"name\": \"GER02\", \"type\": \"TERM\"}, \"truck_number\": 1}": {
    "load": [
      13,
      20,
      24,
      62,
      72,
      84,
      102,
      103,
      110,
      112,
      113,
      114,
      115,
      116,
      120,
      124,
      128,
      129,
      130,
      134,
      135,
      136,
      137
    ]
  },
  "{\"departure_date\": \"2025-06-09\", \"end_location\": {\"name\": \"FRA01\", \"type\": \"DEAL\"}, \"start_location\": {\"name\": \"GER02\", \"type\": \"TERM\"}, \"truck_number\": 1}": {
    "load": [
      28,
      43,
      45,
      56,
      57,
      61,
      69,
      75,
      77
    ]
  },
  "{\"departure_date\": \"2025-06-12\", \"end_location\": {\"name\": \"FRA01\", \"type\": \"DEAL\"}, \"start_location\": {\"name\": \"GER02\", \"type\": \"TERM\"}, \"truck_number\": 1}": {
    "load": [
      29,
      30,
      31,
      33,
      64,
      67,
      88,
      93,
      95,
      97,
      99,
      100,
      101,
      105,
      107,
      108,
      117
    ]
  },
  "{\"departure_date\": \"2025-06-11\", \"end_location\": {\"name\": \"FRA01\", \"type\": \"DEAL\"}, \"start_location\": {\"name\": \"GER02\", \"type\": \"TERM\"}, \"truck_number\": 1}": {
    "load": [
      32,
      68,
      73
    ]
  },
  "{\"departure_date\": \"2025-06-04\", \"end_location\": {\"name\": \"BEL01\", \"type\": \"TERM\"}, \"start_location\": {\"name\": \"GER01\", \"type\": \"PLANT\"}, \"truck_number\": 11}": {
    "load": [
      40,
      41,
      42,
      44,
      49,
      50,
      51,
      52,
      53,
      54,
      55,
      59
    ]
  },
  "{\"departure_date\": \"2025-06-12\", \"end_location\": {\"name\": \"FRA01\", \"type\": \"DEAL\"}, \"start_location\": {\"name\": \"BEL01\", \"type\": \"TERM\"}, \"truck_number\": 1}": {
    "load": [
      40,
      44,
      63,
      65,
      66
    ]
  },
  "{\"departure_date\": \"2025-06-13\", \"end_location\": {\"name\": \"FRA01\", \"type\": \"DEAL\"}, \"start_location\": {\"name\": \"BEL01\", \"type\": \"TERM\"}, \"truck_number\": 1}": {
    "load": [
      41,
      52,
      54,
      76,
      79,
      81,
      83,
      85,
      92,
      96
    ]
  },
  "{\"departure_date\": \"2025-06-09\", \"end_location\": {\"name\": \"FRA01\", \"type\": \"DEAL\"}, \"start_location\": {\"name\": \"BEL01\", \"type\": \"TERM\"}, \"truck_number\": 1}": {
    "load": [
      42,
      49,
      50,
      55,
      58,
      80
    ]
  },
  "{\"departure_date\": \"2025-06-05\", \"end_location\": {\"name\": \"GER02\", \"type\": \"TERM\"}, \"start_location\": {\"name\": \"GER01\", \"type\": \"PLANT\"}, \"truck_number\": 11}": {
    "load": [
      43,
      45,
      46,
      47,
      48,
      56,
      57,
      61,
      62,
      68,
      69,
      70,
      73,
      75,
      77
    ]
  },
  "{\"departure_date\": \"2025-06-11\", \"end_location\": {\"name\": \"FRA01\", \"type\": \"DEAL\"}, \"start_location\": {\"name\": \"BEL01\", \"type\": \"TERM\"}, \"truck_number\": 1}": {
    "load": [
      51,
      53,
      59,
      87,
      89,
      94
    ]
  },
  "{\"departure_date\": \"2025-06-05\", \"end_location\": {\"name\": \"BEL01\", \"type\": \"TERM\"}, \"start_location\": {\"name\": \"GER01\", \"type\": \"PLANT\"}, \"truck_number\": 1}": {
    "load": [
      58
    ]
  },
  "{\"departure_date\": \"2025-06-06\", \"end_location\": {\"name\": \"BEL01\", \"type\": \"TERM\"}, \"start_location\": {\"name\": \"GER01\", \"type\": \"PLANT\"}, \"truck_number\": 1}": {
    "load": [
      60,
      71,
      74,
      78,
      80,
      86,
      94,
      98
    ]
  },
  "{\"departure_date\": \"2025-06-10\", \"end_location\": {\"name\": \"FRA01\", \"type\": \"DEAL\"}, \"start_location\": {\"name\": \"BEL01\", \"type\": \"TERM\"}, \"truck_number\": 1}": {
    "load": [
      60,
      71,
      74,
      78,
      86,
      98
    ]
  },
  "{\"departure_date\": \"2025-06-06\", \"end_location\": {\"name\": \"BEL01\", \"type\": \"TERM\"}, \"start_location\": {\"name\": \"GER01\", \"type\": \"PLANT\"}, \"truck_number\": 11}": {
    "load": [
      63,
      65,
      66,
      76,
      79,
      81,
      83,
      85,
      87,
      89,
      92,
      96
    ]
  },
  "{\"departure_date\": \"2025-06-09\", \"end_location\": {\"name\": \"GER02\", \"type\": \"TERM\"}, \"start_location\": {\"name\": \"GER01\", \"type\": \"PLANT\"}, \"truck_number\": 1}": {
    "load": [
      64,
      67,
      88,
      93,
      95,
      97,
      99,
      100,
      101,
      102,
      103,
      105,
      107,
      108,
      117
    ]
  },
  "{\"departure_date\": \"2025-06-10\", \"end_location\": {\"name\": \"GER02\", \"type\": \"TERM\"}, \"start_location\": {\"name\": \"GER01\", \"type\": \"PLANT\"}, \"truck_number\": 1}": {
    "load": [
      72,
      84,
      91,
      106,
      110,
      112,
      113,
      114,
      115,
      116,
      120,
      121,
      124,
      126,
      128,
      129,
      130,
      134,
      135,
      136,
      137,
      138
    ]
  },
  "{\"departure_date\": \"2025-06-10\", \"end_location\": {\"name\": \"GER02\", \"type\": \"TERM\"}, \"start_location\": {\"name\": \"GER01\", \"type\": \"PLANT\"}, \"truck_number\": 11}": {
    "load": [
      82,
      90,
      104,
      109,
      111,
      118,
      119,
      122,
      123,
      125,
      127,
      131,
      132,
      133,
      139
    ]
  },
  "{\"departure_date\": \"2025-06-17\", \"end_location\": {\"name\": \"FRA01\", \"type\": \"DEAL\"}, \"start_location\": {\"name\": \"GER02\", \"type\": \"TERM\"}, \"truck_number\": 1}": {
    "load": [
      82,
      106,
      109,
      122,
      125,
      126,
      133,
      138,
      145,
      149,
      169,
      170,
      175,
      178,
      179
    ]
  },
  "{\"departure_date\": \"2025-06-16\", \"end_location\": {\"name\": \"FRA01\", \"type\": \"DEAL\"}, \"start_location\": {\"name\": \"GER02\", \"type\": \"TERM\"}, \"truck_number\": 1}": {
    "load": [
      90,
      91,
      118,
      119,
      121,
      123,
      127,
      132,
      160,
      161,
      163,
      164,
      165,
      166,
      176,
      177
    ]
  },
  "{\"departure_date\": \"2025-06-19\", \"end_location\": {\"name\": \"FRA01\", \"type\": \"DEAL\"}, \"start_location\": {\"name\": \"GER02\", \"type\": \"TERM\"}, \"truck_number\": 1}": {
    "load": [
      104,
      111,
      131,
      144,
      150,
      151,
      162,
      168
    ]
  },
  "{\"departure_date\": \"2025-06-20\", \"end_location\": {\"name\": \"FRA01\", \"type\": \"DEAL\"}, \"start_location\": {\"name\": \"GER02\", \"type\": \"TERM\"}, \"truck_number\": 1}": {
    "load": [
      139,
      148,
      159,
      171,
      173,
      174,
      183,
      185,
      190,
      203,
      209,
      211,
      212,
      213,
      218,
      223,
      225,
      226,
      231,
      233,
      235,
      236,
      237
    ]
  },
  "{\"departure_date\": \"2025-06-11\", \"end_location\": {\"name\": \"BEL01\", \"type\": \"TERM\"}, \"start_location\": {\"name\": \"GER01\", \"type\": \"PLANT\"}, \"truck_number\": 11}": {
    "load": [
      140,
      141,
      142,
      143,
      146,
      152,
      153,
      154,
      155,
      156,
      157,
      158
    ]
  },
  "{\"departure_date\": \"2025-06-16\", \"end_location\": {\"name\": \"FRA01\", \"type\": \"DEAL\"}, \"start_location\": {\"name\": \"BEL01\", \"type\": \"TERM\"}, \"truck_number\": 1}": {
    "load": [
      140,
      143,
      146,
      152,
      172
    ]
  },
  "{\"departure_date\": \"2025-06-17\", \"end_location\": {\"name\": \"FRA01\", \"type\": \"DEAL\"}, \"start_location\": {\"name\": \"BEL01\", \"type\": \"TERM\"}, \"truck_number\": 1}": {
    "load": [
      141,
      142,
      147,
      153,
      157,
      167,
      192,
      197
    ]
  },
  "{\"departure_date\": \"2025-06-12\", \"end_location\": {\"name\": \"GER02\", \"type\": \"TERM\"}, \"start_location\": {\"name\": \"GER01\", \"type\": \"PLANT\"}, \"truck_number\": 1}": {
    "load": [
      144,
      145,
      150,
      160,
      162,
      168,
      178,
      179
    ]
  },
  "{\"departure_date\": \"2025-06-13\", \"end_location\": {\"name\": \"BEL01\", \"type\": \"TERM\"}, \"start_location\": {\"name\": \"GER01\", \"type\": \"PLANT\"}, \"truck_number\": 11}": {
    "load": [
      147,
      167,
      180,
      182,
      186,
      187,
      188,
      192,
      194,
      195,
      196,
      197
    ]
  },
  "{\"departure_date\": \"2025-06-17\", \"end_location\": {\"name\": \"GER02\", \"type\": \"TERM\"}, \"start_location\": {\"name\": \"GER01\", \"type\": \"PLANT\"}, \"truck_number\": 1}": {
    "load": [
      148,
      159,
      183,
      185,
      190,
      203,
      209,
      211,
      212,
      213,
      218,
      223,
      225,
      226,
      231,
      233,
      235,
      236,
      237
    ]
  },
  "{\"departure_date\": \"2025-06-12\", \"end_location\": {\"name\": \"GER02\", \"type\": \"TERM\"}, \"start_location\": {\"name\": \"GER01\", \"type\": \"PLANT\"}, \"truck_number\": 11}": {
    "load": [
      149,
      151,
      161,
      163,
      164,
      165,
      166,
      169,
      170,
      171,
      173,
      174,
      175,
      176,
      177
    ]
  },
  "{\"departure_date\": \"2025-06-18\", \"end_location\": {\"name\": \"FRA01\", \"type\": \"DEAL\"}, \"start_location\": {\"name\": \"BEL01\", \"type\": \"TERM\"}, \"truck_number\": 1}": {
    "load": [
      154,
      155,
      156,
      158,
      182,
      187,
      188,
      194
    ]
  },
  "{\"departure_date\": \"2025-06-13\", \"end_location\": {\"name\": \"BEL01\", \"type\": \"TERM\"}, \"start_location\": {\"name\": \"GER01\", \"type\": \"PLANT\"}, \"truck_number\": 1}": {
    "load": [
      172
    ]
  },
  "{\"departure_date\": \"2025-06-20\", \"end_location\": {\"name\": \"FRA01\", \"type\": \"DEAL\"}, \"start_location\": {\"name\": \"BEL01\", \"type\": \"TERM\"}, \"truck_number\": 1}": {
    "load": [
      180,
      184,
      186,
      196,
      204,
      207,
      208,
      210,
      214,
      216,
      219
    ]
  },
  "{\"departure_date\": \"2025-06-16\", \"end_location\": {\"name\": \"BEL01\", \"type\": \"TERM\"}, \"start_location\": {\"name\": \"GER01\", \"type\": \"PLANT\"}, \"truck_number\": 1}": {
    "load": [
      181,
      184,
      191,
      193,
      198,
      199,
      200,
      202,
      204,
      207,
      208,
      210,
      214,
      216,
      219
    ]
  },
  "{\"departure_date\": \"2025-06-19\", \"end_location\": {\"name\": \"FRA01\", \"type\": \"DEAL\"}, \"start_location\": {\"name\": \"BEL01\", \"type\": \"TERM\"}, \"truck_number\": 1}": {
    "load": [
      181,
      191,
      193,
      195,
      198,
      199,
      200,
      202
    ]
  },
  "{\"departure_date\": \"2025-06-18\", \"end_location\": {\"name\": \"BEL01\", \"type\": \"TERM\"}, \"start_location\": {\"name\": \"GER01\", \"type\": \"PLANT\"}, \"truck_number\": 11}": {
    "load": [
      189,
      215,
      241,
      242,
      243,
      245,
      250,
      252,
      253,
      254,
      256,
      258
    ]
  },
  "{\"departure_date\": \"2025-06-24\", \"end_location\": {\"name\": \"FRA01\", \"type\": \"DEAL\"}, \"start_location\": {\"name\": \"BEL01\", \"type\": \"TERM\"}, \"truck_number\": 1}": {
    "load": [
      189,
      215,
      241,
      268,
      293
    ]
  },
  "{\"departure_date\": \"2025-06-17\", \"end_location\": {\"name\": \"GER02\", \"type\": \"TERM\"}, \"start_location\": {\"name\": \"GER01\", \"type\": \"PLANT\"}, \"truck_number\": 11}": {
    "load": [
      201,
      205,
      206,
      217,
      220,
      221,
      222,
      224,
      228,
      229,
      230,
      232,
      234,
      238,
      239
    ]
  },
  "{\"departure_date\": \"2025-06-24\", \"end_location\": {\"name\": \"FRA01\", \"type\": \"DEAL\"}, \"start_location\": {\"name\": \"GER02\", \"type\": \"TERM\"}, \"truck_number\": 1}": {
    "load": [
      201,
      205,
      220,
      224,
      227,
      228,
      230,
      244,
      247,
      259,
      262,
      265,
      267,
      278,
      279,
      286,
      291
    ]
  },
  "{\"departure_date\": \"2025-06-23\", \"end_location\": {\"name\": \"FRA01\", \"type\": \"DEAL\"}, \"start_location\": {\"name\": \"GER02\", \"type\": \"TERM\"}, \"truck_number\": 1}": {
    "load": [
      206,
      249,
      251,
      255,
      263,
      266,
      271,
      272,
      283,
      295
    ]
  },
  "{\"departure_date\": \"2025-06-25\", \"end_location\": {\"name\": \"FRA01\", \"type\": \"DEAL\"}, \"start_location\": {\"name\": \"GER02\", \"type\": \"TERM\"}, \"truck_number\": 1}": {
    "load": [
      217,
      239,
      246,
      269,
      270,
      273,
      280,
      299
    ]
  },
  "{\"departure_date\": \"2025-06-26\", \"end_location\": {\"name\": \"FRA01\", \"type\": \"DEAL\"}, \"start_location\": {\"name\": \"GER02\", \"type\": \"TERM\"}, \"truck_number\": 1}": {
    "load": [
      221,
      222,
      229,
      232,
      248,
      257,
      274,
      276,
      277,
      281,
      289,
      294,
      296,
      297
    ]
  },
  "{\"departure_date\": \"2025-06-18\", \"end_location\": {\"name\": \"GER02\", \"type\": \"TERM\"}, \"start_location\": {\"name\": \"GER01\", \"type\": \"PLANT\"}, \"truck_number\": 1}": {
    "load": [
      227,
      240,
      244,
      246,
      247,
      248,
      249,
      251,
      255,
      257,
      259
    ]
  },
  "{\"departure_date\": \"2025-06-27\", \"end_location\": {\"name\": \"FRA01\", \"type\": \"DEAL\"}, \"start_location\": {\"name\": \"GER02\", \"type\": \"TERM\"}, \"truck_number\": 1}": {
    "load": [
      234,
      238,
      240,
      288,
      290,
      320,
      321,
      324,
      325,
      326,
      328,
      330,
      331,
      333,
      334,
      336,
      337,
      338,
      339
    ]
  },
  "{\"departure_date\": \"2025-06-25\", \"end_location\": {\"name\": \"FRA01\", \"type\": \"DEAL\"}, \"start_location\": {\"name\": \"BEL01\", \"type\": \"TERM\"}, \"truck_number\": 1}": {
    "load": [
      242,
      245,
      252,
      253,
      254,
      256,
      258,
      261,
      264,
      275,
      284,
      292
    ]
  },
  "{\"departure_date\": \"2025-06-23\", \"end_location\": {\"name\": \"FRA01\", \"type\": \"DEAL\"}, \"start_location\": {\"name\": \"BEL01\", \"type\": \"TERM\"}, \"truck_number\": 1}": {
    "load": [
      243,
      250,
      260
    ]
  },
  "{\"departure_date\": \"2025-06-19\", \"end_location\": {\"name\": \"BEL01\", \"type\": \"TERM\"}, \"start_location\": {\"name\": \"GER01\", \"type\": \"PLANT\"}, \"truck_number\": 1}": {
    "load": [
      260,
      261,
      264
    ]
  },
  "{\"departure_date\": \"2025-06-19\", \"end_location\": {\"name\": \"GER02\", \"type\": \"TERM\"}, \"start_location\": {\"name\": \"GER01\", \"type\": \"PLANT\"}, \"truck_number\": 1}": {
    "load": [
      262,
      263,
      265,
      266,
      267,
      269,
      270,
      271,
      272,
      273,
      274,
      276
    ]
  },
  "{\"departure_date\": \"2025-06-20\", \"end_location\": {\"name\": \"BEL01\", \"type\": \"TERM\"}, \"start_location\": {\"name\": \"GER01\", \"type\": \"PLANT\"}, \"truck_number\": 1}": {
    "load": [
      268,
      275,
      284,
      292,
      293
    ]
  },
  "{\"departure_date\": \"2025-06-20\", \"end_location\": {\"name\": \"GER02\", \"type\": \"TERM\"}, \"start_location\": {\"name\": \"GER01\", \"type\": \"PLANT\"}, \"truck_number\": 1}": {
    "load": [
      277,
      278,
      279,
      280,
      281,
      283,
      286,
      288,
      289,
      290,
      291,
      294,
      295,
      296,
      297,
      299
    ]
  },
  "{\"departure_date\": \"2025-06-23\", \"end_location\": {\"name\": \"BEL01\", \"type\": \"TERM\"}, \"start_location\": {\"name\": \"GER01\", \"type\": \"PLANT\"}, \"truck_number\": 1}": {
    "load": [
      282,
      285,
      298,
      301,
      303,
      305,
      306,
      307,
      308,
      310,
      312,
      313,
      314,
      315,
      319
    ]
  },
  "{\"departure_date\": \"2025-06-26\", \"end_location\": {\"name\": \"FRA01\", \"type\": \"DEAL\"}, \"start_location\": {\"name\": \"BEL01\", \"type\": \"TERM\"}, \"truck_number\": 1}": {
    "load": [
      282,
      306,
      308,
      310
    ]
  },
  "{\"departure_date\": \"2025-07-03\", \"end_location\": {\"name\": \"FRA01\", \"type\": \"DEAL\"}, \"start_location\": {\"name\": \"BEL01\", \"type\": \"TERM\"}, \"truck_number\": 1}": {
    "load": [
      285,
      307,
      313,
      315,
      349,
      381,
      382,
      383,
      393,
      396,
      398
    ]
  },
  "{\"departure_date\": \"2025-06-24\", \"end_location\": {\"name\": \"GER02\", \"type\": \"TERM\"}, \"start_location\": {\"name\": \"GER01\", \"type\": \"PLANT\"}, \"truck_number\": 11}": {
    "load": [
      287,
      300,
      302,
      304,
      309,
      311,
      316,
      317,
      318,
      322,
      323,
      327,
      329,
      332,
      335
    ]
  },
  "{\"departure_date\": \"2025-07-01\", \"end_location\": {\"name\": \"FRA01\", \"type\": \"DEAL\"}, \"start_location\": {\"name\": \"GER02\", \"type\": \"TERM\"}, \"truck_number\": 1}": {
    "load": [
      287,
      304,
      317,
      318,
      335,
      345,
      348,
      359,
      361,
      366,
      370,
      378
    ]
  },
  "{\"departure_date\": \"2025-06-27\", \"end_location\": {\"name\": \"FRA01\", \"type\": \"DEAL\"}, \"start_location\": {\"name\": \"BEL01\", \"type\": \"TERM\"}, \"truck_number\": 1}": {
    "load": [
      298,
      301,
      303,
      305
    ]
  },
  "{\"departure_date\": \"2025-06-30\", \"end_location\": {\"name\": \"FRA01\", \"type\": \"DEAL\"}, \"start_location\": {\"name\": \"GER02\", \"type\": \"TERM\"}, \"truck_number\": 1}": {
    "load": [
      300,
      332,
      342,
      356,
      367,
      374,
      376,
      377
    ]
  },
  "{\"departure_date\": \"2025-07-03\", \"end_location\": {\"name\": \"FRA01\", \"type\": \"DEAL\"}, \"start_location\": {\"name\": \"GER02\", \"type\": \"TERM\"}, \"truck_number\": 1}": {
    "load": [
      302,
      322,
      327,
      329,
      363,
      368,
      387,
      392
    ]
  },
  "{\"departure_date\": \"2025-07-04\", \"end_location\": {\"name\": \"FRA01\", \"type\": \"DEAL\"}, \"start_location\": {\"name\": \"GER02\", \"type\": \"TERM\"}, \"truck_number\": 1}": {
    "load": [
      309,
      311,
      316,
      323,
      346,
      350,
      355,
      362,
      364,
      369,
      372,
      373,
      375,
      379,
      401,
      403,
      404,
      405,
      408,
      411,
      412,
      417,
      419
    ]
  },
  "{\"departure_date\": \"2025-07-01\", \"end_location\": {\"name\": \"FRA01\", \"type\": \"DEAL\"}, \"start_location\": {\"name\": \"BEL01\", \"type\": \"TERM\"}, \"truck_number\": 1}": {
    "load": [
      312,
      341,
      357,
      358,
      389,
      394
    ]
  },
  "{\"departure_date\": \"2025-07-04\", \"end_location\": {\"name\": \"FRA01\", \"type\": \"DEAL\"}, \"start_location\": {\"name\": \"BEL01\", \"type\": \"TERM\"}, \"truck_number\": 1}": {
    "load": [
      314,
      319,
      428,
      433,
      435,
      436,
      438
    ]
  },
  "{\"departure_date\": \"2025-06-24\", \"end_location\": {\"name\": \"GER02\", \"type\": \"TERM\"}, \"start_location\": {\"name\": \"GER01\", \"type\": \"PLANT\"}, \"truck_number\": 1}": {
    "load": [
      320,
      321,
      324,
      325,
      326,
      328,
      330,
      331,
      333,
      334,
      336,
      337,
      338,
      339
    ]
  },
  "{\"departure_date\": \"2025-06-25\", \"end_location\": {\"name\": \"BEL01\", \"type\": \"TERM\"}, \"start_location\": {\"name\": \"GER01\", \"type\": \"PLANT\"}, \"truck_number\": 11}": {
    "load": [
      340,
      341,
      343,
      344,
      347,
      349,
      351,
      352,
      353,
      354,
      357,
      358
    ]
  },
  "{\"departure_date\": \"2025-06-30\", \"end_location\": {\"name\": \"FRA01\", \"type\": \"DEAL\"}, \"start_location\": {\"name\": \"BEL01\", \"type\": \"TERM\"}, \"truck_number\": 1}": {
    "load": [
      340,
      344,
      352,
      354
    ]
  },
  "{\"departure_date\": \"2025-06-26\", \"end_location\": {\"name\": \"GER02\", \"type\": \"TERM\"}, \"start_location\": {\"name\": \"GER01\", \"type\": \"PLANT\"}, \"truck_number\": 11}": {
    "load": [
      342,
      345,
      346,
      348,
      355,
      356,
      359,
      361,
      369,
      372,
      373,
      375,
      376,
      377,
      379
    ]
  },
  "{\"departure_date\": \"2025-07-08\", \"end_location\": {\"name\": \"FRA01\", \"type\": \"DEAL\"}, \"start_location\": {\"name\": \"BEL01\", \"type\": \"TERM\"}, \"truck_number\": 1}": {
    "load": [
      343,
      399,
      400,
      429,
      448,
      451,
      453,
      454,
      459,
      460,
      464,
      479,
      488,
      493
    ]
  },
  "{\"departure_date\": \"2025-06-30\", \"end_location\": {\"name\": \"FRA01\", \"type\": \"DEAL\"}, \"start_location\": {\"name\": \"BEL01\", \"type\": \"TERM\"}, \"truck_number\": 2}": {
    "load": [
      347,
      351,
      353,
      371
    ]
  },
  "{\"departure_date\": \"2025-06-26\", \"end_location\": {\"name\": \"GER02\", \"type\": \"TERM\"}, \"start_location\": {\"name\": \"GER01\", \"type\": \"PLANT\"}, \"truck_number\": 1}": {
    "load": [
      350,
      360,
      362,
      363,
      364,
      365,
      366,
      367,
      368,
      370,
      374,
      378
    ]
  },
  "{\"departure_date\": \"2025-07-08\", \"end_location\": {\"name\": \"FRA01\", \"type\": \"DEAL\"}, \"start_location\": {\"name\": \"GER02\", \"type\": \"TERM\"}, \"truck_number\": 1}": {
    "load": [
      360,
      365,
      390,
      397,
      402,
      422,
      424,
      426,
      441,
      445,
      469,
      474,
      476,
      494
    ]
  },
  "{\"departure_date\": \"2025-06-27\", \"end_location\": {\"name\": \"BEL01\", \"type\": \"TERM\"}, \"start_location\": {\"name\": \"GER01\", \"type\": \"PLANT\"}, \"truck_number\": 1}": {
    "load": [
      371
    ]
  },
  "{\"departure_date\": \"2025-06-27\", \"end_location\": {\"name\": \"BEL01\", \"type\": \"TERM\"}, \"start_location\": {\"name\": \"GER01\", \"type\": \"PLANT\"}, \"truck_number\": 11}": {
    "load": [
      380,
      381,
      382,
      383,
      385,
      388,
      389,
      391,
      393,
      394,
      396,
      398
    ]
  },
  "{\"departure_date\": \"2025-07-02\", \"end_location\": {\"name\": \"FRA01\", \"type\": \"DEAL\"}, \"start_location\": {\"name\": \"BEL01\", \"type\": \"TERM\"}, \"truck_number\": 1}": {
    "load": [
      380,
      385,
      388,
      391
    ]
  },
  "{\"departure_date\": \"2025-07-01\", \"end_location\": {\"name\": \"GER02\", \"type\": \"TERM\"}, \"start_location\": {\"name\": \"GER01\", \"type\": \"PLANT\"}, \"truck_number\": 11}": {
    "load": [
      384,
      390,
      397,
      402,
      406,
      414,
      415,
      416,
      418,
      422,
      425,
      426,
      427,
      431,
      439
    ]
  },
  "{\"departure_date\": \"2025-07-07\", \"end_location\": {\"name\": \"FRA01\", \"type\": \"DEAL\"}, \"start_location\": {\"name\": \"GER02\", \"type\": \"TERM\"}, \"truck_number\": 1}": {
    "load": [
      384,
      386,
      395,
      420,
      421,
      423,
      425,
      427,
      442,
      450,
      452,
      458,
      473
    ]
  },
  "{\"departure_date\": \"2025-07-03\", \"end_location\": {\"name\": \"GER02\", \"type\": \"TERM\"}, \"start_location\": {\"name\": \"GER01\", \"type\": \"PLANT\"}, \"truck_number\": 11}": {
    "load": [
      386,
      421,
      423,
      444,
      446,
      450,
      461,
      462,
      463,
      466,
      467,
      468,
      471,
      472,
      477
    ]
  },
  "{\"departure_date\": \"2025-06-30\", \"end_location\": {\"name\": \"GER02\", \"type\": \"TERM\"}, \"start_location\": {\"name\": \"GER01\", \"type\": \"PLANT\"}, \"truck_number\": 1}": {
    "load": [
      387,
      392,
      401,
      403,
      404,
      405,
      408,
      411,
      412,
      417,
      419
    ]
  },
  "{\"departure_date\": \"2025-07-04\", \"end_location\": {\"name\": \"GER02\", \"type\": \"TERM\"}, \"start_location\": {\"name\": \"GER01\", \"type\": \"PLANT\"}, \"truck_number\": 1}": {
    "load": [
      395,
      441,
      442,
      445,
      458,
      465,
      469,
      473,
      474,
      476,
      480,
      485,
      486,
      490,
      492,
      494
    ]
  },
  "{\"departure_date\": \"2025-07-02\", \"end_location\": {\"name\": \"BEL01\", \"type\": \"TERM\"}, \"start_location\": {\"name\": \"GER01\", \"type\": \"PLANT\"}, \"truck_number\": 11}": {
    "load": [
      399,
      400,
      429,
      432,
      443,
      448,
      449,
      451,
      453,
      454,
      457,
      459
    ]
  },
  "{\"departure_date\": \"2025-07-10\", \"end_location\": {\"name\": \"FRA01\", \"type\": \"DEAL\"}, \"start_location\": {\"name\": \"GER02\", \"type\": \"TERM\"}, \"truck_number\": 1}": {
    "load": [
      406,
      407,
      414,
      415,
      430,
      439,
      461,
      468,
      471,
      486
    ]
  },
  "{\"departure_date\": \"2025-07-02\", \"end_location\": {\"name\": \"GER02\", \"type\": \"TERM\"}, \"start_location\": {\"name\": \"GER01\", \"type\": \"PLANT\"}, \"truck_number\": 1}": {
    "load": [
      407,
      409,
      410,
      413,
      420,
      424,
      430,
      434,
      437,
      447,
      452,
      455,
      456
    ]
  },
  "{\"departure_date\": \"2025-07-11\", \"end_location\": {\"name\": \"FRA01\", \"type\": \"DEAL\"}, \"start_location\": {\"name\": \"GER02\", \"type\": \"TERM\"}, \"truck_number\": 1}": {
    "load": [
      409,
      410,
      413,
      434,
      437,
      444,
      446,
      447,
      455,
      456,
      462,
      466,
      477
    ]
  },
  "{\"departure_date\": \"2025-07-09\", \"end_location\": {\"name\": \"FRA01\", \"type\": \"DEAL\"}, \"start_location\": {\"name\": \"GER02\", \"type\": \"TERM\"}, \"truck_number\": 1}": {
    "load": [
      416,
      418,
      431,
      463,
      467,
      472
    ]
  },
  "{\"departure_date\": \"2025-07-01\", \"end_location\": {\"name\": \"BEL01\", \"type\": \"TERM\"}, \"start_location\": {\"name\": \"GER01\", \"type\": \"PLANT\"}, \"truck_number\": 1}": {
    "load": [
      428,
      433,
      435,
      436,
      438
    ]
  },
  "{\"departure_date\": \"2025-07-10\", \"end_location\": {\"name\": \"FRA01\", \"type\": \"DEAL\"}, \"start_location\": {\"name\": \"BEL01\", \"type\": \"TERM\"}, \"truck_number\": 1}": {
    "load": [
      432,
      443,
      487,
      500,
      515
    ]
  },
  "{\"departure_date\": \"2025-07-04\", \"end_location\": {\"name\": \"BEL01\", \"type\": \"TERM\"}, \"start_location\": {\"name\": \"GER01\", \"type\": \"PLANT\"}, \"truck_number\": 11}": {
    "load": [
      440,
      464,
      470,
      475,
      479,
      481,
      483,
      489,
      491,
      495,
      496,
      499
    ]
  },
  "{\"departure_date\": \"2025-07-11\", \"end_location\": {\"name\": \"FRA01\", \"type\": \"DEAL\"}, \"start_location\": {\"name\": \"BEL01\", \"type\": \"TERM\"}, \"truck_number\": 1}": {
    "load": [
      440,
      449,
      457,
      470,
      475,
      481,
      482,
      484,
      495,
      496,
      497,
      499,
      502,
      505,
      509,
      512,
      513,
      518,
      525,
      529,
      531,
      539
    ]
  },
  "{\"departure_date\": \"2025-07-04\", \"end_location\": {\"name\": \"BEL01\", \"type\": \"TERM\"}, \"start_location\": {\"name\": \"GER01\", \"type\": \"PLANT\"}, \"truck_number\": 1}": {
    "load": [
      460,
      478,
      482,
      484,
      488,
      493,
      497,
      498
    ]
  },
  "{\"departure_date\": \"2025-07-15\", \"end_location\": {\"name\": \"FRA01\", \"type\": \"DEAL\"}, \"start_location\": {\"name\": \"GER02\", \"type\": \"TERM\"}, \"truck_number\": 1}": {
    "load": [
      465,
      480,
      485,
      490,
      492,
      506,
      511,
      523,
      528,
      534,
      535,
      553,
      566,
      570,
      573
    ]
  },
  "{\"departure_date\": \"2025-07-16\", \"end_location\": {\"name\": \"FRA01\", \"type\": \"DEAL\"}, \"start_location\": {\"name\": \"BEL01\", \"type\": \"TERM\"}, \"truck_number\": 1}": {
    "load": [
      478,
      498,
      583,
      586,
      594
    ]
  },
  "{\"departure_date\": \"2025-07-15\", \"end_location\": {\"name\": \"FRA01\", \"type\": \"DEAL\"}, \"start_location\": {\"name\": \"BEL01\", \"type\": \"TERM\"}, \"truck_number\": 1}": {
    "load": [
      483,
      489,
      491,
      504,
      519,
      544,
      545,
      547,
      549,
      591,
      595
    ]
  },
  "{\"departure_date\": \"2025-07-07\", \"end_location\": {\"name\": \"BEL01\", \"type\": \"TERM\"}, \"start_location\": {\"name\": \"GER01\", \"type\": \"PLANT\"}, \"truck_number\": 1}": {
    "load": [
      487,
      500,
      502,
      503,
      504,
      505,
      507,
      508,
      509,
      510,
      512,
      513,
      514,
      515,
      516,
      517,
      518,
      519
    ]
  },
  "{\"departure_date\": \"2025-07-08\", \"end_location\": {\"name\": \"GER02\", \"type\": \"TERM\"}, \"start_location\": {\"name\": \"GER01\", \"type\": \"PLANT\"}, \"truck_number\": 11}": {
    "load": [
      501,
      506,
      511,
      520,
      523,
      524,
      526,
      528,
      530,
      532,
      534,
      535,
      536,
      537,
      538
    ]
  },
  "{\"departure_date\": \"2025-07-17\", \"end_location\": {\"name\": \"FRA01\", \"type\": \"DEAL\"}, \"start_location\": {\"name\": \"GER02\", \"type\": \"TERM\"}, \"truck_number\": 1}": {
    "load": [
      501,
      520,
      526,
      530,
      532,
      536,
      546,
      556,
      560,
      571,
      576
    ]
  },
  "{\"departure_date\": \"2025-07-18\", \"end_location\": {\"name\": \"FRA01\", \"type\": \"DEAL\"}, \"start_location\": {\"name\": \"BEL01\", \"type\": \"TERM\"}, \"truck_number\": 1}": {
    "load": [
      503,
      507,
      508,
      514,
      516,
      517,
      551,
      592,
      593,
      599
    ]
  },
  "{\"departure_date\": \"2025-07-14\", \"end_location\": {\"name\": \"FRA01\", \"type\": \"DEAL\"}, \"start_location\": {\"name\": \"BEL01\", \"type\": \"TERM\"}, \"truck_number\": 1}": {
    "load": [
      510,
      521,
      522,
      533,
      541,
      542,
      554
    ]
  },
  "{\"departure_date\": \"2025-07-09\", \"end_location\": {\"name\": \"BEL01\", \"type\": \"TERM\"}, \"start_location\": {\"name\": \"GER01\", \"type\": \"PLANT\"}, \"truck_number\": 11}": {
    "load": [
      521,
      522,
      533,
      541,
      542,
      544,
      545,
      547,
      549,
      551,
      552,
      554
    ]
  },
  "{\"departure_date\": \"2025-07-14\", \"end_location\": {\"name\": \"FRA01\", \"type\": \"DEAL\"}, \"start_location\": {\"name\": \"GER02\", \"type\": \"TERM\"}, \"truck_number\": 1}": {
    "load": [
      524,
      537,
      538,
      543,
      550,
      555,
      563,
      564,
      569
    ]
  },
  "{\"departure_date\": \"2025-07-08\", \"end_location\": {\"name\": \"BEL01\", \"type\": \"TERM\"}, \"start_location\": {\"name\": \"GER01\", \"type\": \"PLANT\"}, \"truck_number\": 1}": {
    "load": [
      525,
      529,
      531,
      539
    ]
  },
  "{\"departure_date\": \"2025-07-16\", \"end_location\": {\"name\": \"BEL01\", \"type\": \"TERM\"}, \"start_location\": {\"name\": \"GER01\", \"type\": \"PLANT\"}, \"truck_number\": 11}": {
    "load": [
      527,
      557,
      567,
      568,
      579,
      580
    ]
  },
  "{\"departure_date\": \"2025-07-21\", \"end_location\": {\"name\": \"FRA01\", \"type\": \"DEAL\"}, \"start_location\": {\"name\": \"BEL01\", \"type\": \"TERM\"}, \"truck_number\": 1}": {
    "load": [
      527,
      557,
      567,
      568,
      579,
      580
    ]
  },
  "{\"departure_date\": \"2025-07-15\", \"end_location\": {\"name\": \"GER02\", \"type\": \"TERM\"}, \"start_location\": {\"name\": \"GER01\", \"type\": \"PLANT\"}, \"truck_number\": 1}": {
    "load": [
      540,
      558,
      559,
      561,
      562,
      565,
      575,
      582,
      585,
      587,
      589
    ]
  },
  "{\"departure_date\": \"2025-07-18\", \"end_location\": {\"name\": \"FRA01\", \"type\": \"DEAL\"}, \"start_location\": {\"name\": \"GER02\", \"type\": \"TERM\"}, \"truck_number\": 1}": {
    "load": [
      540,
      558,
      559,
      561,
      562,
      565,
      575,
      582,
      585,
      587,
      589
    ]
  },
  "{\"departure_date\": \"2025-07-10\", \"end_location\": {\"name\": \"GER02\", \"type\": \"TERM\"}, \"start_location\": {\"name\": \"GER01\", \"type\": \"PLANT\"}, \"truck_number\": 11}": {
    "load": [
      543,
      546,
      550,
      553,
      555,
      556,
      560,
      563,
      564,
      566,
      569,
      570,
      571,
      573,
      576
    ]
  },
  "{\"departure_date\": \"2025-07-15\", \"end_location\": {\"name\": \"GER02\", \"type\": \"TERM\"}, \"start_location\": {\"name\": \"GER01\", \"type\": \"PLANT\"}, \"truck_number\": 11}": {
    "load": [
      548,
      572,
      574,
      577,
      578,
      581,
      584,
      590
    ]
  },
  "{\"departure_date\": \"2025-07-21\", \"end_location\": {\"name\": \"FRA01\", \"type\": \"DEAL\"}, \"start_location\": {\"name\": \"GER02\", \"type\": \"TERM\"}, \"truck_number\": 1}": {
    "load": [
      548,
      572,
      574,
      577,
      578,
      581,
      584,
      590
    ]
  },
  "{\"departure_date\": \"2025-07-17\", \"end_location\": {\"name\": \"FRA01\", \"type\": \"DEAL\"}, \"start_location\": {\"name\": \"BEL01\", \"type\": \"TERM\"}, \"truck_number\": 1}": {
    "load": [
      552,
      588,
      596,
      597,
      598
    ]
  },
  "{\"departure_date\": \"2025-07-11\", \"end_location\": {\"name\": \"BEL01\", \"type\": \"TERM\"}, \"start_location\": {\"name\": \"GER01\", \"type\": \"PLANT\"}, \"truck_number\": 11}": {
    "load": [
      583,
      586,
      588,
      591,
      592,
      593,
      594,
      595,
      596,
      597,
      598,
      599
    ]
  },
  "{\"departure_date\": \"2025-06-02\", \"end_location\": {\"name\": \"GER02\", \"type\": \"TERM\"}, \"start_location\": {\"name\": \"GER01\", \"type\": \"PLANT\"}, \"truck_number\": 1}": {
    "load": []
  },
  "{\"departure_date\": \"2025-06-04\", \"end_location\": {\"name\": \"GER02\", \"type\": \"TERM\"}, \"start_location\": {\"name\": \"GER01\", \"type\": \"PLANT\"}, \"truck_number\": 1}": {
    "load": []
  },
  "{\"departure_date\": \"2025-06-05\", \"end_location\": {\"name\": \"GER02\", \"type\": \"TERM\"}, \"start_location\": {\"name\": \"GER01\", \"type\": \"PLANT\"}, \"truck_number\": 1}": {
    "load": []
  },
  "{\"departure_date\": \"2025-06-06\", \"end_location\": {\"name\": \"GER02\", \"type\": \"TERM\"}, \"start_location\": {\"name\": \"GER01\", \"type\": \"PLANT\"}, \"truck_number\": 1}": {
    "load": []
  },
  "{\"departure_date\": \"2025-06-11\", \"end_location\": {\"name\": \"GER02\", \"type\": \"TERM\"}, \"start_location\": {\"name\": \"GER01\", \"type\": \"PLANT\"}, \"truck_number\": 1}": {
    "load": []
  },
  "{\"departure_date\": \"2025-06-13\", \"end_location\": {\"name\": \"GER02\", \"type\": \"TERM\"}, \"start_location\": {\"name\": \"GER01\", \"type\": \"PLANT\"}, \"truck_number\": 1}": {
    "load": []
  },
  "{\"departure_date\": \"2025-06-16\", \"end_location\": {\"name\": \"GER02\", \"type\": \"TERM\"}, \"start_location\": {\"name\": \"GER01\", \"type\": \"PLANT\"}, \"truck_number\": 1}": {
    "load": []
  },
  "{\"departure_date\": \"2025-06-23\", \"end_location\": {\"name\": \"GER02\", \"type\": \"TERM\"}, \"start_location\": {\"name\": \"GER01\", \"type\": \"PLANT\"}, \"truck_number\": 1}": {
    "load": []
  },
  "{\"departure_date\": \"2025-06-25\", \"end_location\": {\"name\": \"GER02\", \"type\": \"TERM\"}, \"start_location\": {\"name\": \"GER01\", \"type\": \"PLANT\"}, \"truck_number\": 1}": {
    "load": []
  },
  "{\"departure_date\": \"2025-06-27\", \"end_location\": {\"name\": \"GER02\", \"type\": \"TERM\"}, \"start_location\": {\"name\": \"GER01\", \"type\": \"PLANT\"}, \"truck_number\": 1}": {
    "load": []
  },
  "{\"departure_date\": \"2025-07-03\", \"end_location\": {\"name\": \"GER02\", \"type\": \"TERM\"}, \"start_location\": {\"name\": \"GER01\", \"type\": \"PLANT\"}, \"truck_number\": 1}": {
    "load": []
  },
  "{\"departure_date\": \"2025-07-07\", \"end_location\": {\"name\": \"GER02\", \"type\": \"TERM\"}, \"start_location\": {\"name\": \"GER01\", \"type\": \"PLANT\"}, \"truck_number\": 1}": {
    "load": []
  },
  "{\"departure_date\": \"2025-07-08\", \"end_location\": {\"name\": \"GER02\", \"type\": \"TERM\"}, \"start_location\": {\"name\": \"GER01\", \"type\": \"PLANT\"}, \"truck_number\": 1}": {
    "load": []
  },
  "{\"departure_date\": \"2025-07-09\", \"end_location\": {\"name\": \"GER02\", \"type\": \"TERM\"}, \"start_location\": {\"name\": \"GER01\", \"type\": \"PLANT\"}, \"truck_number\": 1}": {
    "load": []
  },
  "{\"departure_date\": \"2025-07-10\", \"end_location\": {\"name\": \"GER02\", \"type\": \"TERM\"}, \"start_location\": {\"name\": \"GER01\", \"type\": \"PLANT\"}, \"truck_number\": 1}": {
    "load": []
  },
  "{\"departure_date\": \"2025-07-11\", \"end_location\": {\"name\": \"GER02\", \"type\": \"TERM\"}, \"start_location\": {\"name\": \"GER01\", \"type\": \"PLANT\"}, \"truck_number\": 1}": {
    "load": []
  },
  "{\"departure_date\": \"2025-07-14\", \"end_location\": {\"name\": \"GER02\", \"type\": \"TERM\"}, \"start_location\": {\"name\": \"GER01\", \"type\": \"PLANT\"}, \"truck_number\": 1}": {
    "load": []
  },
  "{\"departure_date\": \"2025-07-16\", \"end_location\": {\"name\": \"GER02\", \"type\": \"TERM\"}, \"start_location\": {\"name\": \"GER01\", \"type\": \"PLANT\"}, \"truck_number\": 1}": {
    "load": []
  },
  "{\"departure_date\": \"2025-07-17\", \"end_location\": {\"name\": \"GER02\", \"type\": \"TERM\"}, \"start_location\": {\"name\": \"GER01\", \"type\": \"PLANT\"}, \"truck_number\": 1}": {
    "load": []
  },
  "{\"departure_date\": \"2025-07-18\", \"end_location\": {\"name\": \"GER02\", \"type\": \"TERM\"}, \"start_location\": {\"name\": \"GER01\", \"type\": \"PLANT\"}, \"truck_number\": 1}": {
    "load": []
  },
  "{\"departure_date\": \"2025-07-21\", \"end_location\": {\"name\": \"GER02\", \"type\": \"TERM\"}, \"start_location\": {\"name\": \"GER01\", \"type\": \"PLANT\"}, \"truck_number\": 1}": {
    "load": []
  },
  "{\"departure_date\": \"2025-07-22\", \"end_location\": {\"name\": \"GER02\", \"type\": \"TERM\"}, \"start_location\": {\"name\": \"GER01\", \"type\": \"PLANT\"}, \"truck_number\": 1}": {
    "load": []
  },
  "{\"departure_date\": \"2025-07-23\", \"end_location\": {\"name\": \"GER02\", \"type\": \"TERM\"}, \"start_location\": {\"name\": \"GER01\", \"type\": \"PLANT\"}, \"truck_number\": 1}": {
    "load": []
  },
  "{\"departure_date\": \"2025-07-24\", \"end_location\": {\"name\": \"GER02\", \"type\": \"TERM\"}, \"start_location\": {\"name\": \"GER01\", \"type\": \"PLANT\"}, \"truck_number\": 1}": {
    "load": []
  },
  "{\"departure_date\": \"2025-07-25\", \"end_location\": {\"name\": \"GER02\", \"type\": \"TERM\"}, \"start_location\": {\"name\": \"GER01\", \"type\": \"PLANT\"}, \"truck_number\": 1}": {
    "load": []
  },
  "{\"departure_date\": \"2025-07-28\", \"end_location\": {\"name\": \"GER02\", \"type\": \"TERM\"}, \"start_location\": {\"name\": \"GER01\", \"type\": \"PLANT\"}, \"truck_number\": 1}": {
    "load": []
  },
  "{\"departure_date\": \"2025-07-29\", \"end_location\": {\"name\": \"GER02\", \"type\": \"TERM\"}, \"start_location\": {\"name\": \"GER01\", \"type\": \"PLANT\"}, \"truck_number\": 1}": {
    "load": []
  },
  "{\"departure_date\": \"2025-07-30\", \"end_location\": {\"name\": \"GER02\", \"type\": \"TERM\"}, \"start_location\": {\"name\": \"GER01\", \"type\": \"PLANT\"}, \"truck_number\": 1}": {
    "load": []
  },
  "{\"departure_date\": \"2025-07-31\", \"end_location\": {\"name\": \"GER02\", \"type\": \"TERM\"}, \"start_location\": {\"name\": \"GER01\", \"type\": \"PLANT\"}, \"truck_number\": 1}": {
    "load": []
  },
  "{\"departure_date\": \"2025-08-01\", \"end_location\": {\"name\": \"GER02\", \"type\": \"TERM\"}, \"start_location\": {\"name\": \"GER01\", \"type\": \"PLANT\"}, \"truck_number\": 1}": {
    "load": []
  },
  "{\"departure_date\": \"2025-07-24\", \"end_location\": {\"name\": \"GER02\", \"type\": \"TERM\"}, \"start_location\": {\"name\": \"GER01\", \"type\": \"PLANT\"}, \"truck_number\": 11}": {
    "load": []
  },
  "{\"departure_date\": \"2025-07-29\", \"end_location\": {\"name\": \"GER02\", \"type\": \"TERM\"}, \"start_location\": {\"name\": \"GER01\", \"type\": \"PLANT\"}, \"truck_number\": 11}": {
    "load": []
  },
  "{\"departure_date\": \"2025-06-12\", \"end_location\": {\"name\": \"BEL01\", \"type\": \"TERM\"}, \"start_location\": {\"name\": \"GER01\", \"type\": \"PLANT\"}, \"truck_number\": 1}": {
    "load": []
  },
  "{\"departure_date\": \"2025-06-17\", \"end_location\": {\"name\": \"BEL01\", \"type\": \"TERM\"}, \"start_location\": {\"name\": \"GER01\", \"type\": \"PLANT\"}, \"truck_number\": 1}": {
    "load": []
  },
  "{\"departure_date\": \"2025-06-18\", \"end_location\": {\"name\": \"BEL01\", \"type\": \"TERM\"}, \"start_location\": {\"name\": \"GER01\", \"type\": \"PLANT\"}, \"truck_number\": 1}": {
    "load": []
  },
  "{\"departure_date\": \"2025-06-24\", \"end_location\": {\"name\": \"BEL01\", \"type\": \"TERM\"}, \"start_location\": {\"name\": \"GER01\", \"type\": \"PLANT\"}, \"truck_number\": 1}": {
    "load": []
  },
  "{\"departure_date\": \"2025-06-25\", \"end_location\": {\"name\": \"BEL01\", \"type\": \"TERM\"}, \"start_location\": {\"name\": \"GER01\", \"type\": \"PLANT\"}, \"truck_number\": 1}": {
    "load": []
  },
  "{\"departure_date\": \"2025-06-26\", \"end_location\": {\"name\": \"BEL01\", \"type\": \"TERM\"}, \"start_location\": {\"name\": \"GER01\", \"type\": \"PLANT\"}, \"truck_number\": 1}": {
    "load": []
  },
  "{\"departure_date\": \"2025-06-30\", \"end_location\": {\"name\": \"BEL01\", \"type\": \"TERM\"}, \"start_location\": {\"name\": \"GER01\", \"type\": \"PLANT\"}, \"truck_number\": 1}": {
    "load": []
  },
  "{\"departure_date\": \"2025-07-03\", \"end_location\": {\"name\": \"BEL01\", \"type\": \"TERM\"}, \"start_location\": {\"name\": \"GER01\", \"type\": \"PLANT\"}, \"truck_number\": 1}": {
    "load": []
  },
  "{\"departure_date\": \"2025-07-11\", \"end_location\": {\"name\": \"BEL01\", \"type\": \"TERM\"}, \"start_location\": {\"name\": \"GER01\", \"type\": \"PLANT\"}, \"truck_number\": 1}": {
    "load": []
  },
  "{\"departure_date\": \"2025-07-14\", \"end_location\": {\"name\": \"BEL01\", \"type\": \"TERM\"}, \"start_location\": {\"name\": \"GER01\", \"type\": \"PLANT\"}, \"truck_number\": 1}": {
    "load": []
  },
  "{\"departure_date\": \"2025-07-15\", \"end_location\": {\"name\": \"BEL01\", \"type\": \"TERM\"}, \"start_location\": {\"name\": \"GER01\", \"type\": \"PLANT\"}, \"truck_number\": 1}": {
    "load": []
  },
  "{\"departure_date\": \"2025-07-17\", \"end_location\": {\"name\": \"BEL01\", \"type\": \"TERM\"}, \"start_location\": {\"name\": \"GER01\", \"type\": \"PLANT\"}, \"truck_number\": 1}": {
    "load": []
  },
  "{\"departure_date\": \"2025-07-18\", \"end_location\": {\"name\": \"BEL01\", \"type\": \"TERM\"}, \"start_location\": {\"name\": \"GER01\", \"type\": \"PLANT\"}, \"truck_number\": 1}": {
    "load": []
  },
  "{\"departure_date\": \"2025-07-21\", \"end_location\": {\"name\": \"BEL01\", \"type\": \"TERM\"}, \"start_location\": {\"name\": \"GER01\", \"type\": \"PLANT\"}, \"truck_number\": 1}": {
    "load": []
  },
  "{\"departure_date\": \"2025-07-22\", \"end_location\": {\"name\": \"BEL01\", \"type\": \"TERM\"}, \"start_location\": {\"name\": \"GER01\", \"type\": \"PLANT\"}, \"truck_number\": 1}": {
    "load": []
  },
  "{\"departure_date\": \"2025-07-24\", \"end_location\": {\"name\": \"BEL01\", \"type\": \"TERM\"}, \"start_location\": {\"name\": \"GER01\", \"type\": \"PLANT\"}, \"truck_number\": 1}": {
    "load": []
  },
  "{\"departure_date\": \"2025-07-25\", \"end_location\": {\"name\": \"BEL01\", \"type\": \"TERM\"}, \"start_location\": {\"name\": \"GER01\", \"type\": \"PLANT\"}, \"truck_number\": 1}": {
    "load": []
  },
  "{\"departure_date\": \"2025-07-29\", \"end_location\": {\"name\": \"BEL01\", \"type\": \"TERM\"}, \"start_location\": {\"name\": \"GER01\", \"type\": \"PLANT\"}, \"truck_number\": 1}": {
    "load": []
  },
  "{\"departure_date\": \"2025-07-31\", \"end_location\": {\"name\": \"BEL01\", \"type\": \"TERM\"}, \"start_location\": {\"name\": \"GER01\", \"type\": \"PLANT\"}, \"truck_number\": 1}": {
    "load": []
  },
  "{\"departure_date\": \"2025-08-01\", \"end_location\": {\"name\": \"BEL01\", \"type\": \"TERM\"}, \"start_location\": {\"name\": \"GER01\", \"type\": \"PLANT\"}, \"truck_number\": 1}": {
    "load": []
  },
  "{\"departure_date\": \"2025-07-25\", \"end_location\": {\"name\": \"BEL01\", \"type\": \"TERM\"}, \"start_location\": {\"name\": \"GER01\", \"type\": \"PLANT\"}, \"truck_number\": 11}": {
    "load": []
  },
  "{\"departure_date\": \"2025-07-30\", \"end_location\": {\"name\": \"BEL01\", \"type\": \"TERM\"}, \"start_location\": {\"name\": \"GER01\", \"type\": \"PLANT\"}, \"truck_number\": 11}": {
    "load": []
  },
  "{\"departure_date\": \"2025-06-02\", \"end_location\": {\"name\": \"FRA01\", \"type\": \"DEAL\"}, \"start_location\": {\"name\": \"GER02\", \"type\": \"TERM\"}, \"truck_number\": 1}": {
    "load": []
  },
  "{\"departure_date\": \"2025-06-03\", \"end_location\": {\"name\": \"FRA01\", \"type\": \"DEAL\"}, \"start_location\": {\"name\": \"GER02\", \"type\": \"TERM\"}, \"truck_number\": 1}": {
    "load": []
  },
  "{\"departure_date\": \"2025-06-04\", \"end_location\": {\"name\": \"FRA01\", \"type\": \"DEAL\"}, \"start_location\": {\"name\": \"GER02\", \"type\": \"TERM\"}, \"truck_number\": 1}": {
    "load": []
  },
  "{\"departure_date\": \"2025-06-05\", \"end_location\": {\"name\": \"FRA01\", \"type\": \"DEAL\"}, \"start_location\": {\"name\": \"GER02\", \"type\": \"TERM\"}, \"truck_number\": 1}": {
    "load": []
  },
  "{\"departure_date\": \"2025-07-22\", \"end_location\": {\"name\": \"FRA01\", \"type\": \"DEAL\"}, \"start_location\": {\"name\": \"GER02\", \"type\": \"TERM\"}, \"truck_number\": 1}": {
    "load": []
  },
  "{\"departure_date\": \"2025-07-23\", \"end_location\": {\"name\": \"FRA01\", \"type\": \"DEAL\"}, \"start_location\": {\"name\": \"GER02\", \"type\": \"TERM\"}, \"truck_number\": 1}": {
    "load": []
  },
  "{\"departure_date\": \"2025-07-24\", \"end_location\": {\"name\": \"FRA01\", \"type\": \"DEAL\"}, \"start_location\": {\"name\": \"GER02\", \"type\": \"TERM\"}, \"truck_number\": 1}": {
    "load": []
  },
  "{\"departure_date\": \"2025-07-25\", \"end_location\": {\"name\": \"FRA01\", \"type\": \"DEAL\"}, \"start_location\": {\"name\": \"GER02\", \"type\": \"TERM\"}, \"truck_number\": 1}": {
    "load": []
  },
  "{\"departure_date\": \"2025-07-28\", \"end_location\": {\"name\": \"FRA01\", \"type\": \"DEAL\"}, \"start_location\": {\"name\": \"GER02\", \"type\": \"TERM\"}, \"truck_number\": 1}": {
    "load": []
  },
  "{\"departure_date\": \"2025-07-29\", \"end_location\": {\"name\": \"FRA01\", \"type\": \"DEAL\"}, \"start_location\": {\"name\": \"GER02\", \"type\": \"TERM\"}, \"truck_number\": 1}": {
    "load": []
  },
  "{\"departure_date\": \"2025-07-31\", \"end_location\": {\"name\": \"FRA01\", \"type\": \"DEAL\"}, \"start_location\": {\"name\": \"GER02\", \"type\": \"TERM\"}, \"truck_number\": 1}": {
    "load": []
  },
  "{\"departure_date\": \"2025-08-01\", \"end_location\": {\"name\": \"FRA01\", \"type\": \"DEAL\"}, \"start_location\": {\"name\": \"GER02\", \"type\": \"TERM\"}, \"truck_number\": 1}": {
    "load": []
  },
  "{\"departure_date\": \"2025-06-02\", \"end_location\": {\"name\": \"FRA01\", \"type\": \"DEAL\"}, \"start_location\": {\"name\": \"GER02\", \"type\": \"TERM\"}, \"truck_number\": 2}": {
    "load": []
  },
  "{\"departure_date\": \"2025-06-03\", \"end_location\": {\"name\": \"FRA01\", \"type\": \"DEAL\"}, \"start_location\": {\"name\": \"GER02\", \"type\": \"TERM\"}, \"truck_number\": 2}": {
    "load": []
  },
  "{\"departure_date\": \"2025-06-04\", \"end_location\": {\"name\": \"FRA01\", \"type\": \"DEAL\"}, \"start_location\": {\"name\": \"GER02\", \"type\": \"TERM\"}, \"truck_number\": 2}": {
    "load": []
  },
  "{\"departure_date\": \"2025-06-05\", \"end_location\": {\"name\": \"FRA01\", \"type\": \"DEAL\"}, \"start_location\": {\"name\": \"GER02\", \"type\": \"TERM\"}, \"truck_number\": 2}": {
    "load": []
  },
  "{\"departure_date\": \"2025-06-06\", \"end_location\": {\"name\": \"FRA01\", \"type\": \"DEAL\"}, \"start_location\": {\"name\": \"GER02\", \"type\": \"TERM\"}, \"truck_number\": 2}": {
    "load": []
  },
  "{\"departure_date\": \"2025-06-09\", \"end_location\": {\"name\": \"FRA01\", \"type\": \"DEAL\"}, \"start_location\": {\"name\": \"GER02\", \"type\": \"TERM\"}, \"truck_number\": 2}": {
    "load": []
  },
  "{\"departure_date\": \"2025-06-10\", \"end_location\": {\"name\": \"FRA01\", \"type\": \"DEAL\"}, \"start_location\": {\"name\": \"GER02\", \"type\": \"TERM\"}, \"truck_number\": 2}": {
    "load": []
  },
  "{\"departure_date\": \"2025-06-11\", \"end_location\": {\"name\": \"FRA01\", \"type\": \"DEAL\"}, \"start_location\": {\"name\": \"GER02\", \"type\": \"TERM\"}, \"truck_number\": 2}": {
    "load": []
  },
  "{\"departure_date\": \"2025-06-12\", \"end_location\": {\"name\": \"FRA01\", \"type\": \"DEAL\"}, \"start_location\": {\"name\": \"GER02\", \"type\": \"TERM\"}, \"truck_number\": 2}": {
    "load": []
  },
  "{\"departure_date\": \"2025-06-13\", \"end_location\": {\"name\": \"FRA01\", \"type\": \"DEAL\"}, \"start_location\": {\"name\": \"GER02\", \"type\": \"TERM\"}, \"truck_number\": 2}": {
    "load": []
  },
  "{\"departure_date\": \"2025-06-16\", \"end_location\": {\"name\": \"FRA01\", \"type\": \"DEAL\"}, \"start_location\": {\"name\": \"GER02\", \"type\": \"TERM\"}, \"truck_number\": 2}": {
    "load": []
  },
  "{\"departure_date\": \"2025-06-17\", \"end_location\": {\"name\": \"FRA01\", \"type\": \"DEAL\"}, \"start_location\": {\"name\": \"GER02\", \"type\": \"TERM\"}, \"truck_number\": 2}": {
    "load": []
  },
  "{\"departure_date\": \"2025-06-19\", \"end_location\": {\"name\": \"FRA01\", \"type\": \"DEAL\"}, \"start_location\": {\"name\": \"GER02\", \"type\": \"TERM\"}, \"truck_number\": 2}": {
    "load": []
  },
  "{\"departure_date\": \"2025-06-20\", \"end_location\": {\"name\": \"FRA01\", \"type\": \"DEAL\"}, \"start_location\": {\"name\": \"GER02\", \"type\": \"TERM\"}, \"truck_number\": 2}": {
    "load": []
  },
  "{\"departure_date\": \"2025-06-23\", \"end_location\": {\"name\": \"FRA01\", \"type\": \"DEAL\"}, \"start_location\": {\"name\": \"GER02\", \"type\": \"TERM\"}, \"truck_number\": 2}": {
    "load": []
  },
  "{\"departure_date\": \"2025-06-24\", \"end_location\": {\"name\": \"FRA01\", \"type\": \"DEAL\"}, \"start_location\": {\"name\": \"GER02\", \"type\": \"TERM\"}, \"truck_number\": 2}": {
    "load": []
  },
  "{\"departure_date\": \"2025-06-25\", \"end_location\": {\"name\": \"FRA01\", \"type\": \"DEAL\"}, \"start_location\": {\"name\": \"GER02\", \"type\": \"TERM\"}, \"truck_number\": 2}": {
    "load": []
  },
  "{\"departure_date\": \"2025-06-26\", \"end_location\": {\"name\": \"FRA01\", \"type\": \"DEAL\"}, \"start_location\": {\"name\": \"GER02\", \"type\": \"TERM\"}, \"truck_number\": 2}": {
    "load": []
  },
  "{\"departure_date\": \"2025-06-27\", \"end_location\": {\"name\": \"FRA01\", \"type\": \"DEAL\"}, \"start_location\": {\"name\": \"GER02\", \"type\": \"TERM\"}, \"truck_number\": 2}": {
    "load": []
  },
  "{\"departure_date\": \"2025-06-30\", \"end_location\": {\"name\": \"FRA01\", \"type\": \"DEAL\"}, \"start_location\": {\"name\": \"GER02\", \"type\": \"TERM\"}, \"truck_number\": 2}": {
    "load": []
  },
  "{\"departure_date\": \"2025-07-01\", \"end_location\": {\"name\": \"FRA01\", \"type\": \"DEAL\"}, \"start_location\": {\"name\": \"GER02\", \"type\": \"TERM\"}, \"truck_number\": 2}": {
    "load": []
  },
  "{\"departure_date\": \"2025-07-03\", \"end_location\": {\"name\": \"FRA01\", \"type\": \"DEAL\"}, \"start_location\": {\"name\": \"GER02\", \"type\": \"TERM\"}, \"truck_number\": 2}": {
    "load": []
  },
  "{\"departure_date\": \"2025-07-04\", \"end_location\": {\"name\": \"FRA01\", \"type\": \"DEAL\"}, \"start_location\": {\"name\": \"GER02\", \"type\": \"TERM\"}, \"truck_number\": 2}": {
    "load": []
  },
  "{\"departure_date\": \"2025-07-07\", \"end_location\": {\"name\": \"FRA01\", \"type\": \"DEAL\"}, \"start_location\": {\"name\": \"GER02\", \"type\": \"TERM\"}, \"truck_number\": 2}": {
    "load": []
  },
  "{\"departure_date\": \"2025-07-08\", \"end_location\": {\"name\": \"FRA01\", \"type\": \"DEAL\"}, \"start_location\": {\"name\": \"GER02\", \"type\": \"TERM\"}, \"truck_number\": 2}": {
    "load": []
  },
  "{\"departure_date\": \"2025-07-09\", \"end_location\": {\"name\": \"FRA01\", \"type\": \"DEAL\"}, \"start_location\": {\"name\": \"GER02\", \"type\": \"TERM\"}, \"truck_number\": 2}": {
    "load": []
  },
  "{\"departure_date\": \"2025-07-10\", \"end_location\": {\"name\": \"FRA01\", \"type\": \"DEAL\"}, \"start_location\": {\"name\": \"GER02\", \"type\": \"TERM\"}, \"truck_number\": 2}": {
    "load": []
  },
  "{\"departure_date\": \"2025-07-11\", \"end_location\": {\"name\": \"FRA01\", \"type\": \"DEAL\"}, \"start_location\": {\"name\": \"GER02\", \"type\": \"TERM\"}, \"truck_number\": 2}": {
    "load": []
  },
  "{\"departure_date\": \"2025-07-14\", \"end_location\": {\"name\": \"FRA01\", \"type\": \"DEAL\"}, \"start_location\": {\"name\": \"GER02\", \"type\": \"TERM\"}, \"truck_number\": 2}": {
    "load": []
  },
  "{\"departure_date\": \"2025-07-15\", \"end_location\": {\"name\": \"FRA01\", \"type\": \"DEAL\"}, \"start_location\": {\"name\": \"GER02\", \"type\": \"TERM\"}, \"truck_number\": 2}": {
    "load": []
  },
  "{\"departure_date\": \"2025-07-17\", \"end_location\": {\"name\": \"FRA01\", \"type\": \"DEAL\"}, \"start_location\": {\"name\": \"GER02\", \"type\": \"TERM\"}, \"truck_number\": 2}": {
    "load": []
  },
  "{\"departure_date\": \"2025-07-18\", \"end_location\": {\"name\": \"FRA01\", \"type\": \"DEAL\"}, \"start_location\": {\"name\": \"GER02\", \"type\": \"TERM\"}, \"truck_number\": 2}": {
    "load": []
  },
  "{\"departure_date\": \"2025-07-21\", \"end_location\": {\"name\": \"FRA01\", \"type\": \"DEAL\"}, \"start_location\": {\"name\": \"GER02\", \"type\": \"TERM\"}, \"truck_number\": 2}": {
    "load": []
  },
  "{\"departure_date\": \"2025-07-22\", \"end_location\": {\"name\": \"FRA01\", \"type\": \"DEAL\"}, \"start_location\": {\"name\": \"GER02\", \"type\": \"TERM\"}, \"truck_number\": 2}": {
    "load": []
  },
  "{\"departure_date\": \"2025-07-23\", \"end_location\": {\"name\": \"FRA01\", \"type\": \"DEAL\"}, \"start_location\": {\"name\": \"GER02\", \"type\": \"TERM\"}, \"truck_number\": 2}": {
    "load": []
  },
  "{\"departure_date\": \"2025-07-24\", \"end_location\": {\"name\": \"FRA01\", \"type\": \"DEAL\"}, \"start_location\": {\"name\": \"GER02\", \"type\": \"TERM\"}, \"truck_number\": 2}": {
    "load": []
  },
  "{\"departure_date\": \"2025-07-25\", \"end_location\": {\"name\": \"FRA01\", \"type\": \"DEAL\"}, \"start_location\": {\"name\": \"GER02\", \"type\": \"TERM\"}, \"truck_number\": 2}": {
    "load": []
  },
  "{\"departure_date\": \"2025-07-28\", \"end_location\": {\"name\": \"FRA01\", \"type\": \"DEAL\"}, \"start_location\": {\"name\": \"GER02\", \"type\": \"TERM\"}, \"truck_number\": 2}": {
    "load": []
  },
  "{\"departure_date\": \"2025-07-29\", \"end_location\": {\"name\": \"FRA01\", \"type\": \"DEAL\"}, \"start_location\": {\"name\": \"GER02\", \"type\": \"TERM\"}, \"truck_number\": 2}": {
    "load": []
  },
  "{\"departure_date\": \"2025-07-31\", \"end_location\": {\"name\": \"FRA01\", \"type\": \"DEAL\"}, \"start_location\": {\"name\": \"GER02\", \"type\": \"TERM\"}, \"truck_number\": 2}": {
    "load": []
  },
  "{\"departure_date\": \"2025-08-01\", \"end_location\": {\"name\": \"FRA01\", \"type\": \"DEAL\"}, \"start_location\": {\"name\": \"GER02\", \"type\": \"TERM\"}, \"truck_number\": 2}": {
    "load": []
  },
  "{\"departure_date\": \"2025-06-02\", \"end_location\": {\"name\": \"FRA01\", \"type\": \"DEAL\"}, \"start_location\": {\"name\": \"BEL01\", \"type\": \"TERM\"}, \"truck_number\": 1}": {
    "load": []
  },
  "{\"departure_date\": \"2025-06-03\", \"end_location\": {\"name\": \"FRA01\", \"type\": \"DEAL\"}, \"start_location\": {\"name\": \"BEL01\", \"type\": \"TERM\"}, \"truck_number\": 1}": {
    "load": []
  },
  "{\"departure_date\": \"2025-06-04\", \"end_location\": {\"name\": \"FRA01\", \"type\": \"DEAL\"}, \"start_location\": {\"name\": \"BEL01\", \"type\": \"TERM\"}, \"truck_number\": 1}": {
    "load": []
  },
  "{\"departure_date\": \"2025-07-22\", \"end_location\": {\"name\": \"FRA01\", \"type\": \"DEAL\"}, \"start_location\": {\"name\": \"BEL01\", \"type\": \"TERM\"}, \"truck_number\": 1}": {
    "load": []
  },
  "{\"departure_date\": \"2025-07-23\", \"end_location\": {\"name\": \"FRA01\", \"type\": \"DEAL\"}, \"start_location\": {\"name\": \"BEL01\", \"type\": \"TERM\"}, \"truck_number\": 1}": {
    "load": []
  },
  "{\"departure_date\": \"2025-07-24\", \"end_location\": {\"name\": \"FRA01\", \"type\": \"DEAL\"}, \"start_location\": {\"name\": \"BEL01\", \"type\": \"TERM\"}, \"truck_number\": 1}": {
    "load": []
  },
  "{\"departure_date\": \"2025-07-25\", \"end_location\": {\"name\": \"FRA01\", \"type\": \"DEAL\"}, \"start_location\": {\"name\": \"BEL01\", \"type\": \"TERM\"}, \"truck_number\": 1}": {
    "load": []
  },
  "{\"departure_date\": \"2025-07-28\", \"end_location\": {\"name\": \"FRA01\", \"type\": \"DEAL\"}, \"start_location\": {\"name\": \"BEL01\", \"type\": \"TERM\"}, \"truck_number\": 1}": {
    "load": []
  },
  "{\"departure_date\": \"2025-07-29\", \"end_location\": {\"name\": \"FRA01\", \"type\": \"DEAL\"}, \"start_location\": {\"name\": \"BEL01\", \"type\": \"TERM\"}, \"truck_number\": 1}": {
    "load": []
  },
  "{\"departure_date\": \"2025-07-30\", \"end_location\": {\"name\": \"FRA01\", \"type\": \"DEAL\"}, \"start_location\": {\"name\": \"BEL01\", \"type\": \"TERM\"}, \"truck_number\": 1}": {
    "load": []
  },
  "{\"departure_date\": \"2025-07-31\", \"end_location\": {\"name\": \"FRA01\", \"type\": \"DEAL\"}, \"start_location\": {\"name\": \"BEL01\", \"type\": \"TERM\"}, \"truck_number\": 1}": {
    "load": []
  },
  "{\"departure_date\": \"2025-08-01\", \"end_location\": {\"name\": \"FRA01\", \"type\": \"DEAL\"}, \"start_location\": {\"name\": \"BEL01\", \"type\": \"TERM\"}, \"truck_number\": 1}": {
    "load": []
  },
  "{\"departure_date\": \"2025-06-02\", \"end_location\": {\"name\": \"FRA01\", \"type\": \"DEAL\"}, \"start_location\": {\"name\": \"BEL01\", \"type\": \"TERM\"}, \"truck_number\": 2}": {
    "load": []
  },
  "{\"departure_date\": \"2025-06-03\", \"end_location\": {\"name\": \"FRA01\", \"type\": \"DEAL\"}, \"start_location\": {\"name\": \"BEL01\", \"type\": \"TERM\"}, \"truck_number\": 2}": {
    "load": []
  },
  "{\"departure_date\": \"2025-06-04\", \"end_location\": {\"name\": \"FRA01\", \"type\": \"DEAL\"}, \"start_location\": {\"name\": \"BEL01\", \"type\": \"TERM\"}, \"truck_number\": 2}": {
    "load": []
  },
  "{\"departure_date\": \"2025-06-05\", \"end_location\": {\"name\": \"FRA01\", \"type\": \"DEAL\"}, \"start_location\": {\"name\": \"BEL01\", \"type\": \"TERM\"}, \"truck_number\": 2}": {
    "load": []
  },
  "{\"departure_date\": \"2025-06-06\", \"end_location\": {\"name\": \"FRA01\", \"type\": \"DEAL\"}, \"start_location\": {\"name\": \"BEL01\", \"type\": \"TERM\"}, \"truck_number\": 2}": {
    "load": []
  },
  "{\"departure_date\": \"2025-06-09\", \"end_location\": {\"name\": \"FRA01\", \"type\": \"DEAL\"}, \"start_location\": {\"name\": \"BEL01\", \"type\": \"TERM\"}, \"truck_number\": 2}": {
    "load": []
  },
  "{\"departure_date\": \"2025-06-10\", \"end_location\": {\"name\": \"FRA01\", \"type\": \"DEAL\"}, \"start_location\": {\"name\": \"BEL01\", \"type\": \"TERM\"}, \"truck_number\": 2}": {
    "load": []
  },
  "{\"departure_date\": \"2025-06-11\", \"end_location\": {\"name\": \"FRA01\", \"type\": \"DEAL\"}, \"start_location\": {\"name\": \"BEL01\", \"type\": \"TERM\"}, \"truck_number\": 2}": {
    "load": []
  },
  "{\"departure_date\": \"2025-06-12\", \"end_location\": {\"name\": \"FRA01\", \"type\": \"DEAL\"}, \"start_location\": {\"name\": \"BEL01\", \"type\": \"TERM\"}, \"truck_number\": 2}": {
    "load": []
  },
  "{\"departure_date\": \"2025-06-13\", \"end_location\": {\"name\": \"FRA01\", \"type\": \"DEAL\"}, \"start_location\": {\"name\": \"BEL01\", \"type\": \"TERM\"}, \"truck_number\": 2}": {
    "load": []
  },
  "{\"departure_date\": \"2025-06-16\", \"end_location\": {\"name\": \"FRA01\", \"type\": \"DEAL\"}, \"start_location\": {\"name\": \"BEL01\", \"type\": \"TERM\"}, \"truck_number\": 2}": {
    "load": []
  },
  "{\"departure_date\": \"2025-06-17\", \"end_location\": {\"name\": \"FRA01\", \"type\": \"DEAL\"}, \"start_location\": {\"name\": \"BEL01\", \"type\": \"TERM\"}, \"truck_number\": 2}": {
    "load": []
  },
  "{\"departure_date\": \"2025-06-18\", \"end_location\": {\"name\": \"FRA01\", \"type\": \"DEAL\"}, \"start_location\": {\"name\": \"BEL01\", \"type\": \"TERM\"}, \"truck_number\": 2}": {
    "load": []
  },
  "{\"departure_date\": \"2025-06-19\", \"end_location\": {\"name\": \"FRA01\", \"type\": \"DEAL\"}, \"start_location\": {\"name\": \"BEL01\", \"type\": \"TERM\"}, \"truck_number\": 2}": {
    "load": []
  },
  "{\"departure_date\": \"2025-06-20\", \"end_location\": {\"name\": \"FRA01\", \"type\": \"DEAL\"}, \"start_location\": {\"name\": \"BEL01\", \"type\": \"TERM\"}, \"truck_number\": 2}": {
    "load": []
  },
  "{\"departure_date\": \"2025-06-23\", \"end_location\": {\"name\": \"FRA01\", \"type\": \"DEAL\"}, \"start_location\": {\"name\": \"BEL01\", \"type\": \"TERM\"}, \"truck_number\": 2}": {
    "load": []
  },
  "{\"departure_date\": \"2025-06-24\", \"end_location\": {\"name\": \"FRA01\", \"type\": \"DEAL\"}, \"start_location\": {\"name\": \"BEL01\", \"type\": \"TERM\"}, \"truck_number\": 2}": {
    "load": []
  },
  "{\"departure_date\": \"2025-06-25\", \"end_location\": {\"name\": \"FRA01\", \"type\": \"DEAL\"}, \"start_location\": {\"name\": \"BEL01\", \"type\": \"TERM\"}, \"truck_number\": 2}": {
    "load": []
  },
  "{\"departure_date\": \"2025-06-26\", \"end_location\": {\"name\": \"FRA01\", \"type\": \"DEAL\"}, \"start_location\": {\"name\": \"BEL01\", \"type\": \"TERM\"}, \"truck_number\": 2}": {
    "load": []
  },
  "{\"departure_date\": \"2025-06-27\", \"end_location\": {\"name\": \"FRA01\", \"type\": \"DEAL\"}, \"start_location\": {\"name\": \"BEL01\", \"type\": \"TERM\"}, \"truck_number\": 2}": {
    "load": []
  },
  "{\"departure_date\": \"2025-07-01\", \"end_location\": {\"name\": \"FRA01\", \"type\": \"DEAL\"}, \"start_location\": {\"name\": \"BEL01\", \"type\": \"TERM\"}, \"truck_number\": 2}": {
    "load": []
  },
  "{\"departure_date\": \"2025-07-02\", \"end_location\": {\"name\": \"FRA01\", \"type\": \"DEAL\"}, \"start_location\": {\"name\": \"BEL01\", \"type\": \"TERM\"}, \"truck_number\": 2}": {
    "load": []
  },
  "{\"departure_date\": \"2025-07-03\", \"end_location\": {\"name\": \"FRA01\", \"type\": \"DEAL\"}, \"start_location\": {\"name\": \"BEL01\", \"type\": \"TERM\"}, \"truck_number\": 2}": {
    "load": []
  },
  "{\"departure_date\": \"2025-07-04\", \"end_location\": {\"name\": \"FRA01\", \"type\": \"DEAL\"}, \"start_location\": {\"name\": \"BEL01\", \"type\": \"TERM\"}, \"truck_number\": 2}": {
    "load": []
  },
  "{\"departure_date\": \"2025-07-08\", \"end_location\": {\"name\": \"FRA01\", \"type\": \"DEAL\"}, \"start_location\": {\"name\": \"BEL01\", \"type\": \"TERM\"}, \"truck_number\": 2}": {
    "load": []
  },
  "{\"departure_date\": \"2025-07-10\", \"end_location\": {\"name\": \"FRA01\", \"type\": \"DEAL\"}, \"start_location\": {\"name\": \"BEL01\", \"type\": \"TERM\"}, \"truck_number\": 2}": {
    "load": []
  },
  "{\"departure_date\": \"2025-07-11\", \"end_location\": {\"name\": \"FRA01\", \"type\": \"DEAL\"}, \"start_location\": {\"name\": \"BEL01\", \"type\": \"TERM\"}, \"truck_number\": 2}": {
    "load": []
  },
  "{\"departure_date\": \"2025-07-14\", \"end_location\": {\"name\": \"FRA01\", \"type\": \"DEAL\"}, \"start_location\": {\"name\": \"BEL01\", \"type\": \"TERM\"}, \"truck_number\": 2}": {
    "load": []
  },
  "{\"departure_date\": \"2025-07-15\", \"end_location\": {\"name\": \"FRA01\", \"type\": \"DEAL\"}, \"start_location\": {\"name\": \"BEL01\", \"type\": \"TERM\"}, \"truck_number\": 2}": {
    "load": []
  },
  "{\"departure_date\": \"2025-07-16\", \"end_location\": {\"name\": \"FRA01\", \"type\": \"DEAL\"}, \"start_location\": {\"name\": \"BEL01\", \"type\": \"TERM\"}, \"truck_number\": 2}": {
    "load": []
  },
  "{\"departure_date\": \"2025-07-17\", \"end_location\": {\"name\": \"FRA01\", \"type\": \"DEAL\"}, \"start_location\": {\"name\": \"BEL01\", \"type\": \"TERM\"}, \"truck_number\": 2}": {
    "load": []
  },
  "{\"departure_date\": \"2025-07-18\", \"end_location\": {\"name\": \"FRA01\", \"type\": \"DEAL\"}, \"start_location\": {\"name\": \"BEL01\", \"type\": \"TERM\"}, \"truck_number\": 2}": {
    "load": []
  },
  "{\"departure_date\": \"2025-07-21\", \"end_location\": {\"name\": \"FRA01\", \"type\": \"DEAL\"}, \"start_location\": {\"name\": \"BEL01\", \"type\": \"TERM\"}, \"truck_number\": 2}": {
    "load": []
  },
  "{\"departure_date\": \"2025-07-22\", \"end_location\": {\"name\": \"FRA01\", \"type\": \"DEAL\"}, \"start_location\": {\"name\": \"BEL01\", \"type\": \"TERM\"}, \"truck_number\": 2}": {
    "load": []
  },
  "{\"departure_date\": \"2025-07-23\", \"end_location\": {\"name\": \"FRA01\", \"type\": \"DEAL\"}, \"start_location\": {\"name\": \"BEL01\", \"type\": \"TERM\"}, \"truck_number\": 2}": {
    "load": []
  },
  "{\"departure_date\": \"2025-07-24\", \"end_location\": {\"name\": \"FRA01\", \"type\": \"DEAL\"}, \"start_location\": {\"name\": \"BEL01\", \"type\": \"TERM\"}, \"truck_number\": 2}": {
    "load": []
  },
  "{\"departure_date\": \"2025-07-25\", \"end_location\": {\"name\": \"FRA01\", \"type\": \"DEAL\"}, \"start_location\": {\"name\": \"BEL01\", \"type\": \"TERM\"}, \"truck_number\": 2}": {
    "load": []
  },
  "{\"departure_date\": \"2025-07-28\", \"end_location\": {\"name\": \"FRA01\", \"type\": \"DEAL\"}, \"start_location\": {\"name\": \"BEL01\", \"type\": \"TERM\"}, \"truck_number\": 2}": {
    "load": []
  },
  "{\"departure_date\": \"2025-07-29\", \"end_location\": {\"name\": \"FRA01\", \"type\": \"DEAL\"}, \"start_location\": {\"name\": \"BEL01\", \"type\": \"TERM\"}, \"truck_number\": 2}": {
    "load": []
  },
  "{\"departure_date\": \"2025-07-30\", \"end_location\": {\"name\": \"FRA01\", \"type\": \"DEAL\"}, \"start_location\": {\"name\": \"BEL01\", \"type\": \"TERM\"}, \"truck_number\": 2}": {
    "load": []
  },
  "{\"departure_date\": \"2025-07-31\", \"end_location\": {\"name\": \"FRA01\", \"type\": \"DEAL\"}, \"start_location\": {\"name\": \"BEL01\", \"type\": \"TERM\"}, \"truck_number\": 2}": {
    "load": []
  },
  "{\"departure_date\": \"2025-08-01\", \"end_location\": {\"name\": \"FRA01\", \"type\": \"DEAL\"}, \"start_location\": {\"name\": \"BEL01\", \"type\": \"TERM\"}, \"truck_number\": 2}": {
    "load": []
  }
}